Workbook
Name Employees: Timesheet!XEZ1:XFA999

Sheet Week 1 Roster
A1: Employee ID | B1: Store | C1: Preferred Name | D1: 46041 | E1: =TEXT(D1,"dddd") -> Monday | F1: =IF(ISNUMBER(MATCH(D1,'Public Holidays'!$A:$A,0)),"Pub",IF(WEEKDAY(D1,2)=7,"Sun",IF(WEEKDAY(D1,2)=6,"Sat","Ord"))) -> Ord | G1: =D1+1 -> 46042 | H1: =TEXT(G1,"dddd") -> Tuesday | I1: =IF(ISNUMBER(MATCH(G1,'Public Holidays'!$A:$A,0)),"Pub",IF(WEEKDAY(G1,2)=7,"Sun",IF(WEEKDAY(G1,2)=6,"Sat","Ord"))) -> Ord | J1: =G1+1 -> 46043 | K1: =TEXT(J1,"dddd") -> Wednesday | L1: =IF(ISNUMBER(MATCH(J1,'Public Holidays'!$A:$A,0)),"Pub",IF(WEEKDAY(J1,2)=7,"Sun",IF(WEEKDAY(J1,2)=6,"Sat","Ord"))) -> Ord | M1: =J1+1 -> 46044 | N1: =TEXT(M1,"dddd") -> Thursday | O1: =IF(ISNUMBER(MATCH(M1,'Public Holidays'!$A:$A,0)),"Pub",IF(WEEKDAY(M1,2)=7,"Sun",IF(WEEKDAY(M1,2)=6,"Sat","Ord"))) -> Ord | P1: =M1+1 -> 46045 | Q1: =TEXT(P1,"dddd") -> Friday | R1: =IF(ISNUMBER(MATCH(P1,'Public Holidays'!$A:$A,0)),"Pub",IF(WEEKDAY(P1,2)=7,"Sun",IF(WEEKDAY(P1,2)=6,"Sat","Ord"))) -> Ord | S1: =P1+1 -> 46046 | T1: =TEXT(S1,"dddd") -> Saturday | U1: =IF(ISNUMBER(MATCH(S1,'Public Holidays'!$A:$A,0)),"Pub",IF(WEEKDAY(S1,2)=7,"Sun",IF(WEEKDAY(S1,2)=6,"Sat","Ord"))) -> Sat | V1: =S1+1 -> 46047 | W1: =TEXT(V1,"dddd") -> Sunday | X1: =IF(ISNUMBER(MATCH(V1,'Public Holidays'!$A:$A,0)),"Pub",IF(WEEKDAY(V1,2)=7,"Sun",IF(WEEKDAY(V1,2)=6,"Sat","Ord"))) -> Sun | Y1: =V1+1 -> 46048 | Z1: =TEXT(Y1,"dddd") -> Monday | AA1: =IF(ISNUMBER(MATCH(Y1,'Public Holidays'!$A:$A,0)),"Pub",IF(WEEKDAY(Y1,2)=7,"Sun",IF(WEEKDAY(Y1,2)=6,"Sat","Ord"))) -> Pub | AB1: Rostered Total | AD1: Add | AE1: Ord | AF1: Add | AG1: Sat | AH1: Add | AI1: Sun | AJ1: Add | AK1: Pub | AL1: Add | AM1: Eve 1 | AN1: Add | AO1: Eve 2 | AP1: No. of Shifts | AQ1: Personal Leave | AR1: Annual Leave | AS1: Unpaid Leave | AT1: Adjusted Total | AU1: Comment | AV1: 0.91666667 | AW1: 1 | AX1: 5.5 | AY1: 9 | AZ1: Employee ID | BA1: Dr1 | BB1: Br1 | BC1: =F1 -> Ord | BD1: =IF(BC1="Ord","Eve 1", BC1) -> Eve 1 | BE1: =IF(BH1="Ord","Eve 2",BH1) -> Eve 2 | BF1: Dr2 | BG1: Br2 | BH1: =I1 -> Ord | BI1: =IF(BH1="Ord","Eve 1", BH1) -> Eve 1 | BJ1: =IF(BM1="Ord","Eve 2",BM1) -> Eve 2 | BK1: Dr3 | BL1: Br3 | BM1: =L1 -> Ord | BN1: =IF(BM1="Ord","Eve 1", BM1) -> Eve 1 | BO1: =IF(BR1="Ord","Eve 2",BR1) -> Eve 2 | BP1: Dr4 | BQ1: Br4 | BR1: =O1 -> Ord | BS1: =IF(BR1="Ord","Eve 1", BR1) -> Eve 1 | BT1: =IF(BW1="Ord","Eve 2",BW1) -> Eve 2 | BU1: Dr5 | BV1: Br5 | BW1: =R1 -> Ord | BX1: =IF(BW1="Ord","Eve 1", BW1) -> Eve 1 | BY1: =IF(CB1="Ord","Eve 2",CB1) -> Sat | BZ1: Dr6 | CA1: Br6 | CB1: =U1 -> Sat | CC1: =IF(CB1="Ord","Eve 1", CB1) -> Sat | CD1: =IF(CG1="Ord","Eve 2",CG1) -> Sun | CE1: Dr7 | CF1: Br7 | CG1: =X1 -> Sun | CH1: =IF(CG1="Ord","Eve 1", CG1) -> Sun | CI1: =IF(CJ1="Ord","Eve 2",CJ1) -> Pub | CJ1: =AA1 -> Pub | CK1: No. of Shifts
A2: =IF(ISNA(AZ2),"",AZ2) -> 10306 | B2: The Star | C2: Annie Pham | D2: 0.41666667 | E2: 0.64583333 | F2: =BA2-BB2 -> 5 | I2: =BF2-BG2 -> 0 | L2: =BK2-BL2 -> 0 | O2: =BP2-BQ2 -> 0 | P2: 0.63402778 | Q2: 0.975 | R2: =BU2-BV2 -> 7.6833333 | S2: 0.58333333 | T2: 0.99166667 | U2: =BZ2-CA2 -> 8.8 | X2: =CE2-CF2 -> 0 | AB2: =SUM(F2,I2,L2,O2,R2,U2,X2) -> 21.483333 | AD2: =1+2+1 -> 4 | AE2: =SUMIF($BC$1:$CI$1,AE$1,$BC2:$CI2)+AD2 -> 15.283333 | AG2: =SUMIF($BC$1:$CI$1,AG$1,$BC2:$CI2)+AF2 -> 8.8 | AI2: =SUMIF($BC$1:$CI$1,AI$1,$BC2:$CI2)+AH2 -> 0 | AK2: =SUMIF($BC$1:$CI$1,AK$1,$BC2:$CI2)+AJ2 -> 0 | AM2: =SUMIF($BC$1:$CI$1,AM$1,$BC2:$CI2)+AL2 -> 1.4 | AO2: =SUMIF($BC$1:$CI$1,AO$1,$BC2:$CI2)+AN2 -> 0 | AP2: =CK2 -> 3 | AT2: =AE2+AG2+AI2+AK2+AM2+AO2+SUM(AQ2:AS2) -> 25.483333 | AU2: + 1h roster making + 1h meeting + 2h deposit | AZ2: =VLOOKUP(C2,Employees!D:I,6,FALSE) -> 10306 | BA2: =IF(ISBLANK(D2),0,(E2-D2)*24) -> 5.5 | BB2: =IF(BA2>$AY$1,1,IF(BA2>=$AX$1,0.5,0)) -> 0.5 | BC2: =BA2-BB2-BD2-BE2 -> 5 | BD2: =IF(AND(E2>$AV$1, D2<$AW$1),(MIN(E2,$AW$1)-MAX(D2,$AV$1))*24,0) -> 0 | BE2: =IF(E2>$AW$1,(E2-MAX(D2,$AW$1))*24,0) -> 0 | BF2: =IF(ISBLANK(G2),0,(H2-G2)*24) -> 0 | BG2: =IF(BF2>$AY$1,1,IF(BF2>=$AX$1,0.5,0)) -> 0 | BH2: =BF2-BG2-BI2-BJ2 -> 0 | BI2: =IF(AND(H2>$AV$1,G2<$AW$1),(MIN(H2,$AW$1)-MAX(G2,$AV$1))*24,0) -> 0 | BJ2: =IF(H2>$AW$1,(H2-MAX(G2,$AW$1))*24,0) -> 0 | BK2: =IF(ISBLANK(J2),0,(K2-J2)*24) -> 0 | BL2: =IF(BK2>$AY$1,1,IF(BK2>=$AX$1,0.5,0)) -> 0 | BM2: =BK2-BL2-BN2-BO2 -> 0 | BN2: =IF(AND(K2>$AV$1, J2<$AW$1),(MIN(K2,$AW$1)-MAX(J2,$AV$1))*24,0) -> 0 | BO2: =IF(K2>$AW$1,(K2-MAX(J2,$AW$1))*24,0) -> 0 | BP2: =IF(ISBLANK(M2),0,(N2-M2)*24) -> 0 | BQ2: =IF(BP2>$AY$1,1,IF(BP2>=$AX$1,0.5,0)) -> 0 | BR2: =BP2-BQ2-BS2-BT2 -> 0 | BS2: =IF(AND(N2>$AV$1, M2<$AW$1),(MIN(N2,$AW$1)-MAX(M2,$AV$1))*24,0) -> 0 | BT2: =IF(N2>$AW$1,(N2-MAX(M2,$AW$1))*24,0) -> 0 | BU2: =IF(ISBLANK(P2),0,(Q2-P2)*24) -> 8.1833333 | BV2: =IF(BU2>$AY$1,1,IF(BU2>=$AX$1,0.5,0)) -> 0.5 | BW2: =BU2-BV2-BX2-BY2 -> 6.2833333 | BX2: =IF(AND(Q2>$AV$1, P2<$AW$1),(MIN(Q2,$AW$1)-MAX(P2,$AV$1))*24,0) -> 1.4 | BY2: =IF(Q2>$AW$1,(Q2-MAX(P2,$AW$1))*24,0) -> 0 | BZ2: =IF(ISBLANK(S2),0,(T2-S2)*24) -> 9.8 | CA2: =IF(BZ2>$AY$1,1,IF(BZ2>=$AX$1,0.5,0)) -> 1 | CB2: =BZ2-CA2-CC2-CD2 -> 7 | CC2: =IF(AND(T2>$AV$1, S2<$AW$1),(MIN(T2,$AW$1)-MAX(S2,$AV$1))*24,0) -> 1.8 | CD2: =IF(T2>$AW$1,(T2-MAX(S2,$AW$1))*24,0) -> 0 | CE2: =IF(ISBLANK(V2),0,(W2-V2)*24) -> 0 | CF2: =IF(CE2>$AY$1,1,IF(CE2>=$AX$1,0.5,0)) -> 0 | CG2: =CE2-CF2-CH2-CI2 -> 0 | CH2: =IF(AND(W2>$AV$1, V2<$AW$1),(MIN(W2,$AW$1)-MAX(V2,$AV$1))*24,0) -> 0 | CI2: =IF(W2>$AW$1,(W2-MAX(V2,$AW$1))*24,0) -> 0 | CK2: =SUM(IF(F2>0,1,0),IF(I2>0,1,0),IF(L2>0,1,0),IF(O2>0,1,0),IF(R2>0,1,0),IF(U2>0,1,0),IF(X2>0,1,0)) -> 3
A3: =IF(ISNA(AZ3),"",AZ3) -> 10386 | B3: The Star | C3: Nia Handoko | F3: =BA3-BB3 -> 0 | I3: =BF3-BG3 -> 0 | J3: 0.41666667 | K3: 0.75138889 | L3: =BK3-BL3 -> 7.5333333 | M3: 0.41666667 | N3: 0.625 | O3: =BP3-BQ3 -> 5 | P3: 0.41666667 | Q3: 0.63541667 | R3: =BU3-BV3 -> 5.25 | S3: 0.41666667 | T3: 0.79166667 | U3: =BZ3-CA3 -> 8.5 | X3: =CE3-CF3 -> 0 | AB3: =SUM(F3,I3,L3,O3,R3,U3,X3) -> 26.283333 | AD3: =0.5 -> 0.5 | AE3: =SUMIF($BC$1:$CI$1,AE$1,$BC3:$CI3)+AD3 -> 18.283333 | AG3: =SUMIF($BC$1:$CI$1,AG$1,$BC3:$CI3)+AF3 -> 8.5 | AI3: =SUMIF($BC$1:$CI$1,AI$1,$BC3:$CI3)+AH3 -> 0 | AK3: =SUMIF($BC$1:$CI$1,AK$1,$BC3:$CI3)+AJ3 -> 0 | AM3: =SUMIF($BC$1:$CI$1,AM$1,$BC3:$CI3)+AL3 -> 0 | AO3: =SUMIF($BC$1:$CI$1,AO$1,$BC3:$CI3)+AN3 -> 0 | AP3: =CK3 -> 4 | AT3: =AE3+AG3+AI3+AK3+AM3+AO3+SUM(AQ3:AS3) -> 26.783333 | AU3: + 0.5h break on Wed 1/21 | AZ3: =VLOOKUP(C3,Employees!D:I,6,FALSE) -> 10386 | BA3: =IF(ISBLANK(D3),0,(E3-D3)*24) -> 0 | BB3: =IF(BA3>$AY$1,1,IF(BA3>=$AX$1,0.5,0)) -> 0 | BC3: =BA3-BB3-BD3-BE3 -> 0 | BD3: =IF(AND(E3>$AV$1, D3<$AW$1),(MIN(E3,$AW$1)-MAX(D3,$AV$1))*24,0) -> 0 | BE3: =IF(E3>$AW$1,(E3-MAX(D3,$AW$1))*24,0) -> 0 | BF3: =IF(ISBLANK(G3),0,(H3-G3)*24) -> 0 | BG3: =IF(BF3>$AY$1,1,IF(BF3>=$AX$1,0.5,0)) -> 0 | BH3: =BF3-BG3-BI3-BJ3 -> 0 | BI3: =IF(AND(H3>$AV$1,G3<$AW$1),(MIN(H3,$AW$1)-MAX(G3,$AV$1))*24,0) -> 0 | BJ3: =IF(H3>$AW$1,(H3-MAX(G3,$AW$1))*24,0) -> 0 | BK3: =IF(ISBLANK(J3),0,(K3-J3)*24) -> 8.0333333 | BL3: =IF(BK3>$AY$1,1,IF(BK3>=$AX$1,0.5,0)) -> 0.5 | BM3: =BK3-BL3-BN3-BO3 -> 7.5333333 | BN3: =IF(AND(K3>$AV$1, J3<$AW$1),(MIN(K3,$AW$1)-MAX(J3,$AV$1))*24,0) -> 0 | BO3: =IF(K3>$AW$1,(K3-MAX(J3,$AW$1))*24,0) -> 0 | BP3: =IF(ISBLANK(M3),0,(N3-M3)*24) -> 5 | BQ3: =IF(BP3>$AY$1,1,IF(BP3>=$AX$1,0.5,0)) -> 0 | BR3: =BP3-BQ3-BS3-BT3 -> 5 | BS3: =IF(AND(N3>$AV$1, M3<$AW$1),(MIN(N3,$AW$1)-MAX(M3,$AV$1))*24,0) -> 0 | BT3: =IF(N3>$AW$1,(N3-MAX(M3,$AW$1))*24,0) -> 0 | BU3: =IF(ISBLANK(P3),0,(Q3-P3)*24) -> 5.25 | BV3: =IF(BU3>$AY$1,1,IF(BU3>=$AX$1,0.5,0)) -> 0 | BW3: =BU3-BV3-BX3-BY3 -> 5.25 | BX3: =IF(AND(Q3>$AV$1, P3<$AW$1),(MIN(Q3,$AW$1)-MAX(P3,$AV$1))*24,0) -> 0 | BY3: =IF(Q3>$AW$1,(Q3-MAX(P3,$AW$1))*24,0) -> 0 | BZ3: =IF(ISBLANK(S3),0,(T3-S3)*24) -> 9 | CA3: =IF(BZ3>$AY$1,1,IF(BZ3>=$AX$1,0.5,0)) -> 0.5 | CB3: =BZ3-CA3-CC3-CD3 -> 8.5 | CC3: =IF(AND(T3>$AV$1, S3<$AW$1),(MIN(T3,$AW$1)-MAX(S3,$AV$1))*24,0) -> 0 | CD3: =IF(T3>$AW$1,(T3-MAX(S3,$AW$1))*24,0) -> 0 | CE3: =IF(ISBLANK(V3),0,(W3-V3)*24) -> 0 | CF3: =IF(CE3>$AY$1,1,IF(CE3>=$AX$1,0.5,0)) -> 0 | CG3: =CE3-CF3-CH3-CI3 -> 0 | CH3: =IF(AND(W3>$AV$1, V3<$AW$1),(MIN(W3,$AW$1)-MAX(V3,$AV$1))*24,0) -> 0 | CI3: =IF(W3>$AW$1,(W3-MAX(V3,$AW$1))*24,0) -> 0 | CK3: =SUM(IF(F3>0,1,0),IF(I3>0,1,0),IF(L3>0,1,0),IF(O3>0,1,0),IF(R3>0,1,0),IF(U3>0,1,0),IF(X3>0,1,0)) -> 4
A4: =IF(ISNA(AZ4),"",AZ4) -> 10376 | B4: The Star | C4: Harry Le | D4: 0.64930556 | E4: 0.96180556 | F4: =BA4-BB4 -> 7 | I4: =BF4-BG4 -> 0 | J4: 0.75 | K4: 0.97638889 | L4: =BK4-BL4 -> 5.4333333 | O4: =BP4-BQ4 -> 0 | R4: =BU4-BV4 -> 0 | U4: =BZ4-CA4 -> 0 | V4: 0.41805556 | W4: 0.97847222 | X4: =CE4-CF4 -> 12.45 | AB4: =SUM(F4,I4,L4,O4,R4,U4,X4) -> 24.883333 | AE4: =SUMIF($BC$1:$CI$1,AE$1,$BC4:$CI4)+AD4 -> 9.9166667 | AG4: =SUMIF($BC$1:$CI$1,AG$1,$BC4:$CI4)+AF4 -> 0 | AI4: =SUMIF($BC$1:$CI$1,AI$1,$BC4:$CI4)+AH4 -> 12.45 | AK4: =SUMIF($BC$1:$CI$1,AK$1,$BC4:$CI4)+AJ4 -> 0 | AM4: =SUMIF($BC$1:$CI$1,AM$1,$BC4:$CI4)+AL4 -> 2.5166667 | AO4: =SUMIF($BC$1:$CI$1,AO$1,$BC4:$CI4)+AN4 -> 0 | AP4: =CK4 -> 3 | AT4: =AE4+AG4+AI4+AK4+AM4+AO4+SUM(AQ4:AS4) -> 24.883333 | AZ4: =VLOOKUP(C4,Employees!D:I,6,FALSE) -> 10376 | BA4: =IF(ISBLANK(D4),0,(E4-D4)*24) -> 7.5 | BB4: =IF(BA4>$AY$1,1,IF(BA4>=$AX$1,0.5,0)) -> 0.5 | BC4: =BA4-BB4-BD4-BE4 -> 5.9166667 | BD4: =IF(AND(E4>$AV$1, D4<$AW$1),(MIN(E4,$AW$1)-MAX(D4,$AV$1))*24,0) -> 1.0833333 | BE4: =IF(E4>$AW$1,(E4-MAX(D4,$AW$1))*24,0) -> 0 | BF4: =IF(ISBLANK(G4),0,(H4-G4)*24) -> 0 | BG4: =IF(BF4>$AY$1,1,IF(BF4>=$AX$1,0.5,0)) -> 0 | BH4: =BF4-BG4-BI4-BJ4 -> 0 | BI4: =IF(AND(H4>$AV$1,G4<$AW$1),(MIN(H4,$AW$1)-MAX(G4,$AV$1))*24,0) -> 0 | BJ4: =IF(H4>$AW$1,(H4-MAX(G4,$AW$1))*24,0) -> 0 | BK4: =IF(ISBLANK(J4),0,(K4-J4)*24) -> 5.4333333 | BL4: =IF(BK4>$AY$1,1,IF(BK4>=$AX$1,0.5,0)) -> 0 | BM4: =BK4-BL4-BN4-BO4 -> 4 | BN4: =IF(AND(K4>$AV$1, J4<$AW$1),(MIN(K4,$AW$1)-MAX(J4,$AV$1))*24,0) -> 1.4333333 | BO4: =IF(K4>$AW$1,(K4-MAX(J4,$AW$1))*24,0) -> 0 | BP4: =IF(ISBLANK(M4),0,(N4-M4)*24) -> 0 | BQ4: =IF(BP4>$AY$1,1,IF(BP4>=$AX$1,0.5,0)) -> 0 | BR4: =BP4-BQ4-BS4-BT4 -> 0 | BS4: =IF(AND(N4>$AV$1, M4<$AW$1),(MIN(N4,$AW$1)-MAX(M4,$AV$1))*24,0) -> 0 | BT4: =IF(N4>$AW$1,(N4-MAX(M4,$AW$1))*24,0) -> 0 | BU4: =IF(ISBLANK(P4),0,(Q4-P4)*24) -> 0 | BV4: =IF(BU4>$AY$1,1,IF(BU4>=$AX$1,0.5,0)) -> 0 | BW4: =BU4-BV4-BX4-BY4 -> 0 | BX4: =IF(AND(Q4>$AV$1, P4<$AW$1),(MIN(Q4,$AW$1)-MAX(P4,$AV$1))*24,0) -> 0 | BY4: =IF(Q4>$AW$1,(Q4-MAX(P4,$AW$1))*24,0) -> 0 | BZ4: =IF(ISBLANK(S4),0,(T4-S4)*24) -> 0 | CA4: =IF(BZ4>$AY$1,1,IF(BZ4>=$AX$1,0.5,0)) -> 0 | CB4: =BZ4-CA4-CC4-CD4 -> 0 | CC4: =IF(AND(T4>$AV$1, S4<$AW$1),(MIN(T4,$AW$1)-MAX(S4,$AV$1))*24,0) -> 0 | CD4: =IF(T4>$AW$1,(T4-MAX(S4,$AW$1))*24,0) -> 0 | CE4: =IF(ISBLANK(V4),0,(W4-V4)*24) -> 13.45 | CF4: =IF(CE4>$AY$1,1,IF(CE4>=$AX$1,0.5,0)) -> 1 | CG4: =CE4-CF4-CH4-CI4 -> 10.966667 | CH4: =IF(AND(W4>$AV$1, V4<$AW$1),(MIN(W4,$AW$1)-MAX(V4,$AV$1))*24,0) -> 1.4833333 | CI4: =IF(W4>$AW$1,(W4-MAX(V4,$AW$1))*24,0) -> 0 | CK4: =SUM(IF(F4>0,1,0),IF(I4>0,1,0),IF(L4>0,1,0),IF(O4>0,1,0),IF(R4>0,1,0),IF(U4>0,1,0),IF(X4>0,1,0)) -> 3
A5: =IF(ISNA(AZ5),"",AZ5) -> 210432 | B5: The Star | C5: Ashley Hmue | F5: =BA5-BB5 -> 0 | I5: =BF5-BG5 -> 0 | L5: =BK5-BL5 -> 0 | M5: 0.625 | N5: 0.96527778 | O5: =BP5-BQ5 -> 7.6666667 | R5: =BU5-BV5 -> 0 | U5: =BZ5-CA5 -> 0 | V5: 0.5 | W5: 0.77152778 | X5: =CE5-CF5 -> 6.0166667 | AB5: =SUM(F5,I5,L5,O5,R5,U5,X5) -> 13.683333 | AE5: =SUMIF($BC$1:$CI$1,AE$1,$BC5:$CI5)+AD5 -> 6.5 | AG5: =SUMIF($BC$1:$CI$1,AG$1,$BC5:$CI5)+AF5 -> 0 | AI5: =SUMIF($BC$1:$CI$1,AI$1,$BC5:$CI5)+AH5 -> 6.0166667 | AK5: =SUMIF($BC$1:$CI$1,AK$1,$BC5:$CI5)+AJ5 -> 0 | AM5: =SUMIF($BC$1:$CI$1,AM$1,$BC5:$CI5)+AL5 -> 1.1666667 | AO5: =SUMIF($BC$1:$CI$1,AO$1,$BC5:$CI5)+AN5 -> 0 | AP5: =CK5 -> 2 | AT5: =AE5+AG5+AI5+AK5+AM5+AO5+SUM(AQ5:AS5) -> 13.683333 | AZ5: =VLOOKUP(C5,Employees!D:I,6,FALSE) -> 210432 | BA5: =IF(ISBLANK(D5),0,(E5-D5)*24) -> 0 | BB5: =IF(BA5>$AY$1,1,IF(BA5>=$AX$1,0.5,0)) -> 0 | BC5: =BA5-BB5-BD5-BE5 -> 0 | BD5: =IF(AND(E5>$AV$1, D5<$AW$1),(MIN(E5,$AW$1)-MAX(D5,$AV$1))*24,0) -> 0 | BE5: =IF(E5>$AW$1,(E5-MAX(D5,$AW$1))*24,0) -> 0 | BF5: =IF(ISBLANK(G5),0,(H5-G5)*24) -> 0 | BG5: =IF(BF5>$AY$1,1,IF(BF5>=$AX$1,0.5,0)) -> 0 | BH5: =BF5-BG5-BI5-BJ5 -> 0 | BI5: =IF(AND(H5>$AV$1,G5<$AW$1),(MIN(H5,$AW$1)-MAX(G5,$AV$1))*24,0) -> 0 | BJ5: =IF(H5>$AW$1,(H5-MAX(G5,$AW$1))*24,0) -> 0 | BK5: =IF(ISBLANK(J5),0,(K5-J5)*24) -> 0 | BL5: =IF(BK5>$AY$1,1,IF(BK5>=$AX$1,0.5,0)) -> 0 | BM5: =BK5-BL5-BN5-BO5 -> 0 | BN5: =IF(AND(K5>$AV$1, J5<$AW$1),(MIN(K5,$AW$1)-MAX(J5,$AV$1))*24,0) -> 0 | BO5: =IF(K5>$AW$1,(K5-MAX(J5,$AW$1))*24,0) -> 0 | BP5: =IF(ISBLANK(M5),0,(N5-M5)*24) -> 8.1666667 | BQ5: =IF(BP5>$AY$1,1,IF(BP5>=$AX$1,0.5,0)) -> 0.5 | BR5: =BP5-BQ5-BS5-BT5 -> 6.5 | BS5: =IF(AND(N5>$AV$1, M5<$AW$1),(MIN(N5,$AW$1)-MAX(M5,$AV$1))*24,0) -> 1.1666667 | BT5: =IF(N5>$AW$1,(N5-MAX(M5,$AW$1))*24,0) -> 0 | BU5: =IF(ISBLANK(P5),0,(Q5-P5)*24) -> 0 | BV5: =IF(BU5>$AY$1,1,IF(BU5>=$AX$1,0.5,0)) -> 0 | BW5: =BU5-BV5-BX5-BY5 -> 0 | BX5: =IF(AND(Q5>$AV$1, P5<$AW$1),(MIN(Q5,$AW$1)-MAX(P5,$AV$1))*24,0) -> 0 | BY5: =IF(Q5>$AW$1,(Q5-MAX(P5,$AW$1))*24,0) -> 0 | BZ5: =IF(ISBLANK(S5),0,(T5-S5)*24) -> 0 | CA5: =IF(BZ5>$AY$1,1,IF(BZ5>=$AX$1,0.5,0)) -> 0 | CB5: =BZ5-CA5-CC5-CD5 -> 0 | CC5: =IF(AND(T5>$AV$1, S5<$AW$1),(MIN(T5,$AW$1)-MAX(S5,$AV$1))*24,0) -> 0 | CD5: =IF(T5>$AW$1,(T5-MAX(S5,$AW$1))*24,0) -> 0 | CE5: =IF(ISBLANK(V5),0,(W5-V5)*24) -> 6.5166667 | CF5: =IF(CE5>$AY$1,1,IF(CE5>=$AX$1,0.5,0)) -> 0.5 | CG5: =CE5-CF5-CH5-CI5 -> 6.0166667 | CH5: =IF(AND(W5>$AV$1, V5<$AW$1),(MIN(W5,$AW$1)-MAX(V5,$AV$1))*24,0) -> 0 | CI5: =IF(W5>$AW$1,(W5-MAX(V5,$AW$1))*24,0) -> 0 | CK5: =SUM(IF(F5>0,1,0),IF(I5>0,1,0),IF(L5>0,1,0),IF(O5>0,1,0),IF(R5>0,1,0),IF(U5>0,1,0),IF(X5>0,1,0)) -> 2
A6: =IF(ISNA(AZ6),"",AZ6) -> 210553 | B6: The Star | C6: Yunie Kang | F6: =BA6-BB6 -> 0 | G6: 0.75 | H6: 0.96527778 | I6: =BF6-BG6 -> 5.1666667 | L6: =BK6-BL6 -> 0 | O6: =BP6-BQ6 -> 0 | P6: 0.5 | Q6: 0.75 | R6: =BU6-BV6 -> 5.5 | U6: =BZ6-CA6 -> 0 | X6: =CE6-CF6 -> 0 | AB6: =SUM(F6,I6,L6,O6,R6,U6,X6) -> 10.666667 | AE6: =SUMIF($BC$1:$CI$1,AE$1,$BC6:$CI6)+AD6 -> 9.5 | AG6: =SUMIF($BC$1:$CI$1,AG$1,$BC6:$CI6)+AF6 -> 0 | AI6: =SUMIF($BC$1:$CI$1,AI$1,$BC6:$CI6)+AH6 -> 0 | AK6: =SUMIF($BC$1:$CI$1,AK$1,$BC6:$CI6)+AJ6 -> 0 | AM6: =SUMIF($BC$1:$CI$1,AM$1,$BC6:$CI6)+AL6 -> 1.1666667 | AO6: =SUMIF($BC$1:$CI$1,AO$1,$BC6:$CI6)+AN6 -> 0 | AP6: =CK6 -> 2 | AT6: =AE6+AG6+AI6+AK6+AM6+AO6+SUM(AQ6:AS6) -> 10.666667 | AZ6: =VLOOKUP(C6,Employees!D:I,6,FALSE) -> 210553 | BA6: =IF(ISBLANK(D6),0,(E6-D6)*24) -> 0 | BB6: =IF(BA6>$AY$1,1,IF(BA6>=$AX$1,0.5,0)) -> 0 | BC6: =BA6-BB6-BD6-BE6 -> 0 | BD6: =IF(AND(E6>$AV$1, D6<$AW$1),(MIN(E6,$AW$1)-MAX(D6,$AV$1))*24,0) -> 0 | BE6: =IF(E6>$AW$1,(E6-MAX(D6,$AW$1))*24,0) -> 0 | BF6: =IF(ISBLANK(G6),0,(H6-G6)*24) -> 5.1666667 | BG6: =IF(BF6>$AY$1,1,IF(BF6>=$AX$1,0.5,0)) -> 0 | BH6: =BF6-BG6-BI6-BJ6 -> 4 | BI6: =IF(AND(H6>$AV$1,G6<$AW$1),(MIN(H6,$AW$1)-MAX(G6,$AV$1))*24,0) -> 1.1666667 | BJ6: =IF(H6>$AW$1,(H6-MAX(G6,$AW$1))*24,0) -> 0 | BK6: =IF(ISBLANK(J6),0,(K6-J6)*24) -> 0 | BL6: =IF(BK6>$AY$1,1,IF(BK6>=$AX$1,0.5,0)) -> 0 | BM6: =BK6-BL6-BN6-BO6 -> 0 | BN6: =IF(AND(K6>$AV$1, J6<$AW$1),(MIN(K6,$AW$1)-MAX(J6,$AV$1))*24,0) -> 0 | BO6: =IF(K6>$AW$1,(K6-MAX(J6,$AW$1))*24,0) -> 0 | BP6: =IF(ISBLANK(M6),0,(N6-M6)*24) -> 0 | BQ6: =IF(BP6>$AY$1,1,IF(BP6>=$AX$1,0.5,0)) -> 0 | BR6: =BP6-BQ6-BS6-BT6 -> 0 | BS6: =IF(AND(N6>$AV$1, M6<$AW$1),(MIN(N6,$AW$1)-MAX(M6,$AV$1))*24,0) -> 0 | BT6: =IF(N6>$AW$1,(N6-MAX(M6,$AW$1))*24,0) -> 0 | BU6: =IF(ISBLANK(P6),0,(Q6-P6)*24) -> 6 | BV6: =IF(BU6>$AY$1,1,IF(BU6>=$AX$1,0.5,0)) -> 0.5 | BW6: =BU6-BV6-BX6-BY6 -> 5.5 | BX6: =IF(AND(Q6>$AV$1, P6<$AW$1),(MIN(Q6,$AW$1)-MAX(P6,$AV$1))*24,0) -> 0 | BY6: =IF(Q6>$AW$1,(Q6-MAX(P6,$AW$1))*24,0) -> 0 | BZ6: =IF(ISBLANK(S6),0,(T6-S6)*24) -> 0 | CA6: =IF(BZ6>$AY$1,1,IF(BZ6>=$AX$1,0.5,0)) -> 0 | CB6: =BZ6-CA6-CC6-CD6 -> 0 | CC6: =IF(AND(T6>$AV$1, S6<$AW$1),(MIN(T6,$AW$1)-MAX(S6,$AV$1))*24,0) -> 0 | CD6: =IF(T6>$AW$1,(T6-MAX(S6,$AW$1))*24,0) -> 0 | CE6: =IF(ISBLANK(V6),0,(W6-V6)*24) -> 0 | CF6: =IF(CE6>$AY$1,1,IF(CE6>=$AX$1,0.5,0)) -> 0 | CG6: =CE6-CF6-CH6-CI6 -> 0 | CH6: =IF(AND(W6>$AV$1, V6<$AW$1),(MIN(W6,$AW$1)-MAX(V6,$AV$1))*24,0) -> 0 | CI6: =IF(W6>$AW$1,(W6-MAX(V6,$AW$1))*24,0) -> 0 | CK6: =SUM(IF(F6>0,1,0),IF(I6>0,1,0),IF(L6>0,1,0),IF(O6>0,1,0),IF(R6>0,1,0),IF(U6>0,1,0),IF(X6>0,1,0)) -> 2
A7: =IF(ISNA(AZ7),"",AZ7) -> 10431 | B7: The Star | C7: Victoria Handoko | F7: =BA7-BB7 -> 0 | G7: 0.41666667 | H7: 0.73958333 | I7: =BF7-BG7 -> 7.25 | L7: =BK7-BL7 -> 0 | O7: =BP7-BQ7 -> 0 | R7: =BU7-BV7 -> 0 | U7: =BZ7-CA7 -> 0 | X7: =CE7-CF7 -> 0 | AB7: =SUM(F7,I7,L7,O7,R7,U7,X7) -> 7.25 | AD7: 0.5 | AE7: =SUMIF($BC$1:$CI$1,AE$1,$BC7:$CI7)+AD7 -> 7.75 | AG7: =SUMIF($BC$1:$CI$1,AG$1,$BC7:$CI7)+AF7 -> 0 | AI7: =SUMIF($BC$1:$CI$1,AI$1,$BC7:$CI7)+AH7 -> 0 | AK7: =SUMIF($BC$1:$CI$1,AK$1,$BC7:$CI7)+AJ7 -> 0 | AM7: =SUMIF($BC$1:$CI$1,AM$1,$BC7:$CI7)+AL7 -> 0 | AO7: =SUMIF($BC$1:$CI$1,AO$1,$BC7:$CI7)+AN7 -> 0 | AP7: =CK7 -> 1 | AT7: =AE7+AG7+AI7+AK7+AM7+AO7+SUM(AQ7:AS7) -> 7.75 | AU7: + 0.5h break on Tue 1/20 | AZ7: =VLOOKUP(C7,Employees!D:I,6,FALSE) -> 10431 | BA7: =IF(ISBLANK(D7),0,(E7-D7)*24) -> 0 | BB7: =IF(BA7>$AY$1,1,IF(BA7>=$AX$1,0.5,0)) -> 0 | BC7: =BA7-BB7-BD7-BE7 -> 0 | BD7: =IF(AND(E7>$AV$1, D7<$AW$1),(MIN(E7,$AW$1)-MAX(D7,$AV$1))*24,0) -> 0 | BE7: =IF(E7>$AW$1,(E7-MAX(D7,$AW$1))*24,0) -> 0 | BF7: =IF(ISBLANK(G7),0,(H7-G7)*24) -> 7.75 | BG7: =IF(BF7>$AY$1,1,IF(BF7>=$AX$1,0.5,0)) -> 0.5 | BH7: =BF7-BG7-BI7-BJ7 -> 7.25 | BI7: =IF(AND(H7>$AV$1,G7<$AW$1),(MIN(H7,$AW$1)-MAX(G7,$AV$1))*24,0) -> 0 | BJ7: =IF(H7>$AW$1,(H7-MAX(G7,$AW$1))*24,0) -> 0 | BK7: =IF(ISBLANK(J7),0,(K7-J7)*24) -> 0 | BL7: =IF(BK7>$AY$1,1,IF(BK7>=$AX$1,0.5,0)) -> 0 | BM7: =BK7-BL7-BN7-BO7 -> 0 | BN7: =IF(AND(K7>$AV$1, J7<$AW$1),(MIN(K7,$AW$1)-MAX(J7,$AV$1))*24,0) -> 0 | BO7: =IF(K7>$AW$1,(K7-MAX(J7,$AW$1))*24,0) -> 0 | BP7: =IF(ISBLANK(M7),0,(N7-M7)*24) -> 0 | BQ7: =IF(BP7>$AY$1,1,IF(BP7>=$AX$1,0.5,0)) -> 0 | BR7: =BP7-BQ7-BS7-BT7 -> 0 | BS7: =IF(AND(N7>$AV$1, M7<$AW$1),(MIN(N7,$AW$1)-MAX(M7,$AV$1))*24,0) -> 0 | BT7: =IF(N7>$AW$1,(N7-MAX(M7,$AW$1))*24,0) -> 0 | BU7: =IF(ISBLANK(P7),0,(Q7-P7)*24) -> 0 | BV7: =IF(BU7>$AY$1,1,IF(BU7>=$AX$1,0.5,0)) -> 0 | BW7: =BU7-BV7-BX7-BY7 -> 0 | BX7: =IF(AND(Q7>$AV$1, P7<$AW$1),(MIN(Q7,$AW$1)-MAX(P7,$AV$1))*24,0) -> 0 | BY7: =IF(Q7>$AW$1,(Q7-MAX(P7,$AW$1))*24,0) -> 0 | BZ7: =IF(ISBLANK(S7),0,(T7-S7)*24) -> 0 | CA7: =IF(BZ7>$AY$1,1,IF(BZ7>=$AX$1,0.5,0)) -> 0 | CB7: =BZ7-CA7-CC7-CD7 -> 0 | CC7: =IF(AND(T7>$AV$1, S7<$AW$1),(MIN(T7,$AW$1)-MAX(S7,$AV$1))*24,0) -> 0 | CD7: =IF(T7>$AW$1,(T7-MAX(S7,$AW$1))*24,0) -> 0 | CE7: =IF(ISBLANK(V7),0,(W7-V7)*24) -> 0 | CF7: =IF(CE7>$AY$1,1,IF(CE7>=$AX$1,0.5,0)) -> 0 | CG7: =CE7-CF7-CH7-CI7 -> 0 | CH7: =IF(AND(W7>$AV$1, V7<$AW$1),(MIN(W7,$AW$1)-MAX(V7,$AV$1))*24,0) -> 0 | CI7: =IF(W7>$AW$1,(W7-MAX(V7,$AW$1))*24,0) -> 0 | CK7: =SUM(IF(F7>0,1,0),IF(I7>0,1,0),IF(L7>0,1,0),IF(O7>0,1,0),IF(R7>0,1,0),IF(U7>0,1,0),IF(X7>0,1,0)) -> 1
A8: =IF(ISNA(AZ8),"",AZ8) -> 10090 | B8: The Star | C8: Ava Chiang | F8: =BA8-BB8 -> 0 | G8: 0.73958333 | H8: 0.96527778 | I8: =BF8-BG8 -> 5.4166667 | L8: =BK8-BL8 -> 0 | O8: =BP8-BQ8 -> 0 | R8: =BU8-BV8 -> 0 | U8: =BZ8-CA8 -> 0 | X8: =CE8-CF8 -> 0 | AB8: =SUM(F8,I8,L8,O8,R8,U8,X8) -> 5.4166667 | AE8: =SUMIF($BC$1:$CI$1,AE$1,$BC8:$CI8)+AD8 -> 4.25 | AG8: =SUMIF($BC$1:$CI$1,AG$1,$BC8:$CI8)+AF8 -> 0 | AI8: =SUMIF($BC$1:$CI$1,AI$1,$BC8:$CI8)+AH8 -> 0 | AK8: =SUMIF($BC$1:$CI$1,AK$1,$BC8:$CI8)+AJ8 -> 0 | AM8: =SUMIF($BC$1:$CI$1,AM$1,$BC8:$CI8)+AL8 -> 1.1666667 | AO8: =SUMIF($BC$1:$CI$1,AO$1,$BC8:$CI8)+AN8 -> 0 | AP8: =CK8 -> 1 | AT8: =AE8+AG8+AI8+AK8+AM8+AO8+SUM(AQ8:AS8) -> 5.4166667 | AZ8: =VLOOKUP(C8,Employees!D:I,6,FALSE) -> 10090 | BA8: =IF(ISBLANK(D8),0,(E8-D8)*24) -> 0 | BB8: =IF(BA8>$AY$1,1,IF(BA8>=$AX$1,0.5,0)) -> 0 | BC8: =BA8-BB8-BD8-BE8 -> 0 | BD8: =IF(AND(E8>$AV$1, D8<$AW$1),(MIN(E8,$AW$1)-MAX(D8,$AV$1))*24,0) -> 0 | BE8: =IF(E8>$AW$1,(E8-MAX(D8,$AW$1))*24,0) -> 0 | BF8: =IF(ISBLANK(G8),0,(H8-G8)*24) -> 5.4166667 | BG8: =IF(BF8>$AY$1,1,IF(BF8>=$AX$1,0.5,0)) -> 0 | BH8: =BF8-BG8-BI8-BJ8 -> 4.25 | BI8: =IF(AND(H8>$AV$1,G8<$AW$1),(MIN(H8,$AW$1)-MAX(G8,$AV$1))*24,0) -> 1.1666667 | BJ8: =IF(H8>$AW$1,(H8-MAX(G8,$AW$1))*24,0) -> 0 | BK8: =IF(ISBLANK(J8),0,(K8-J8)*24) -> 0 | BL8: =IF(BK8>$AY$1,1,IF(BK8>=$AX$1,0.5,0)) -> 0 | BM8: =BK8-BL8-BN8-BO8 -> 0 | BN8: =IF(AND(K8>$AV$1, J8<$AW$1),(MIN(K8,$AW$1)-MAX(J8,$AV$1))*24,0) -> 0 | BO8: =IF(K8>$AW$1,(K8-MAX(J8,$AW$1))*24,0) -> 0 | BP8: =IF(ISBLANK(M8),0,(N8-M8)*24) -> 0 | BQ8: =IF(BP8>$AY$1,1,IF(BP8>=$AX$1,0.5,0)) -> 0 | BR8: =BP8-BQ8-BS8-BT8 -> 0 | BS8: =IF(AND(N8>$AV$1, M8<$AW$1),(MIN(N8,$AW$1)-MAX(M8,$AV$1))*24,0) -> 0 | BT8: =IF(N8>$AW$1,(N8-MAX(M8,$AW$1))*24,0) -> 0 | BU8: =IF(ISBLANK(P8),0,(Q8-P8)*24) -> 0 | BV8: =IF(BU8>$AY$1,1,IF(BU8>=$AX$1,0.5,0)) -> 0 | BW8: =BU8-BV8-BX8-BY8 -> 0 | BX8: =IF(AND(Q8>$AV$1, P8<$AW$1),(MIN(Q8,$AW$1)-MAX(P8,$AV$1))*24,0) -> 0 | BY8: =IF(Q8>$AW$1,(Q8-MAX(P8,$AW$1))*24,0) -> 0 | BZ8: =IF(ISBLANK(S8),0,(T8-S8)*24) -> 0 | CA8: =IF(BZ8>$AY$1,1,IF(BZ8>=$AX$1,0.5,0)) -> 0 | CB8: =BZ8-CA8-CC8-CD8 -> 0 | CC8: =IF(AND(T8>$AV$1, S8<$AW$1),(MIN(T8,$AW$1)-MAX(S8,$AV$1))*24,0) -> 0 | CD8: =IF(T8>$AW$1,(T8-MAX(S8,$AW$1))*24,0) -> 0 | CE8: =IF(ISBLANK(V8),0,(W8-V8)*24) -> 0 | CF8: =IF(CE8>$AY$1,1,IF(CE8>=$AX$1,0.5,0)) -> 0 | CG8: =CE8-CF8-CH8-CI8 -> 0 | CH8: =IF(AND(W8>$AV$1, V8<$AW$1),(MIN(W8,$AW$1)-MAX(V8,$AV$1))*24,0) -> 0 | CI8: =IF(W8>$AW$1,(W8-MAX(V8,$AW$1))*24,0) -> 0 | CK8: =SUM(IF(F8>0,1,0),IF(I8>0,1,0),IF(L8>0,1,0),IF(O8>0,1,0),IF(R8>0,1,0),IF(U8>0,1,0),IF(X8>0,1,0)) -> 1
A9: =IF(ISNA(AZ9),"",AZ9) | F9: =BA9-BB9 -> 0 | I9: =BF9-BG9 -> 0 | L9: =BK9-BL9 -> 0 | O9: =BP9-BQ9 -> 0 | R9: =BU9-BV9 -> 0 | U9: =BZ9-CA9 -> 0 | X9: =CE9-CF9 -> 0 | AB9: =SUM(F9,I9,L9,O9,R9,U9,X9) -> 0 | AE9: =SUMIF($BC$1:$CI$1,AE$1,$BC9:$CI9)+AD9 -> 0 | AG9: =SUMIF($BC$1:$CI$1,AG$1,$BC9:$CI9)+AF9 -> 0 | AI9: =SUMIF($BC$1:$CI$1,AI$1,$BC9:$CI9)+AH9 -> 0 | AK9: =SUMIF($BC$1:$CI$1,AK$1,$BC9:$CI9)+AJ9 -> 0 | AM9: =SUMIF($BC$1:$CI$1,AM$1,$BC9:$CI9)+AL9 -> 0 | AO9: =SUMIF($BC$1:$CI$1,AO$1,$BC9:$CI9)+AN9 -> 0 | AP9: =CK9 -> 0 | AT9: =AE9+AG9+AI9+AK9+AM9+AO9+SUM(AQ9:AS9) -> 0 | AZ9: =VLOOKUP(C9,Employees!D:I,6,FALSE) -> #N/A | BA9: =IF(ISBLANK(D9),0,(E9-D9)*24) -> 0 | BB9: =IF(BA9>$AY$1,1,IF(BA9>=$AX$1,0.5,0)) -> 0 | BC9: =BA9-BB9-BD9-BE9 -> 0 | BD9: =IF(AND(E9>$AV$1, D9<$AW$1),(MIN(E9,$AW$1)-MAX(D9,$AV$1))*24,0) -> 0 | BE9: =IF(E9>$AW$1,(E9-MAX(D9,$AW$1))*24,0) -> 0 | BF9: =IF(ISBLANK(G9),0,(H9-G9)*24) -> 0 | BG9: =IF(BF9>$AY$1,1,IF(BF9>=$AX$1,0.5,0)) -> 0 | BH9: =BF9-BG9-BI9-BJ9 -> 0 | BI9: =IF(AND(H9>$AV$1,G9<$AW$1),(MIN(H9,$AW$1)-MAX(G9,$AV$1))*24,0) -> 0 | BJ9: =IF(H9>$AW$1,(H9-MAX(G9,$AW$1))*24,0) -> 0 | BK9: =IF(ISBLANK(J9),0,(K9-J9)*24) -> 0 | BL9: =IF(BK9>$AY$1,1,IF(BK9>=$AX$1,0.5,0)) -> 0 | BM9: =BK9-BL9-BN9-BO9 -> 0 | BN9: =IF(AND(K9>$AV$1, J9<$AW$1),(MIN(K9,$AW$1)-MAX(J9,$AV$1))*24,0) -> 0 | BO9: =IF(K9>$AW$1,(K9-MAX(J9,$AW$1))*24,0) -> 0 | BP9: =IF(ISBLANK(M9),0,(N9-M9)*24) -> 0 | BQ9: =IF(BP9>$AY$1,1,IF(BP9>=$AX$1,0.5,0)) -> 0 | BR9: =BP9-BQ9-BS9-BT9 -> 0 | BS9: =IF(AND(N9>$AV$1, M9<$AW$1),(MIN(N9,$AW$1)-MAX(M9,$AV$1))*24,0) -> 0 | BT9: =IF(N9>$AW$1,(N9-MAX(M9,$AW$1))*24,0) -> 0 | BU9: =IF(ISBLANK(P9),0,(Q9-P9)*24) -> 0 | BV9: =IF(BU9>$AY$1,1,IF(BU9>=$AX$1,0.5,0)) -> 0 | BW9: =BU9-BV9-BX9-BY9 -> 0 | BX9: =IF(AND(Q9>$AV$1, P9<$AW$1),(MIN(Q9,$AW$1)-MAX(P9,$AV$1))*24,0) -> 0 | BY9: =IF(Q9>$AW$1,(Q9-MAX(P9,$AW$1))*24,0) -> 0 | BZ9: =IF(ISBLANK(S9),0,(T9-S9)*24) -> 0 | CA9: =IF(BZ9>$AY$1,1,IF(BZ9>=$AX$1,0.5,0)) -> 0 | CB9: =BZ9-CA9-CC9-CD9 -> 0 | CC9: =IF(AND(T9>$AV$1, S9<$AW$1),(MIN(T9,$AW$1)-MAX(S9,$AV$1))*24,0) -> 0 | CD9: =IF(T9>$AW$1,(T9-MAX(S9,$AW$1))*24,0) -> 0 | CE9: =IF(ISBLANK(V9),0,(W9-V9)*24) -> 0 | CF9: =IF(CE9>$AY$1,1,IF(CE9>=$AX$1,0.5,0)) -> 0 | CG9: =CE9-CF9-CH9-CI9 -> 0 | CH9: =IF(AND(W9>$AV$1, V9<$AW$1),(MIN(W9,$AW$1)-MAX(V9,$AV$1))*24,0) -> 0 | CI9: =IF(W9>$AW$1,(W9-MAX(V9,$AW$1))*24,0) -> 0 | CK9: =SUM(IF(F9>0,1,0),IF(I9>0,1,0),IF(L9>0,1,0),IF(O9>0,1,0),IF(R9>0,1,0),IF(U9>0,1,0),IF(X9>0,1,0)) -> 0
A10: =IF(ISNA(AZ10),"",AZ10) | F10: =BA10-BB10 -> 0 | I10: =BF10-BG10 -> 0 | L10: =BK10-BL10 -> 0 | O10: =BP10-BQ10 -> 0 | R10: =BU10-BV10 -> 0 | U10: =BZ10-CA10 -> 0 | X10: =CE10-CF10 -> 0 | AB10: =SUM(F10,I10,L10,O10,R10,U10,X10) -> 0 | AE10: =SUMIF($BC$1:$CI$1,AE$1,$BC10:$CI10)+AD10 -> 0 | AG10: =SUMIF($BC$1:$CI$1,AG$1,$BC10:$CI10)+AF10 -> 0 | AI10: =SUMIF($BC$1:$CI$1,AI$1,$BC10:$CI10)+AH10 -> 0 | AK10: =SUMIF($BC$1:$CI$1,AK$1,$BC10:$CI10)+AJ10 -> 0 | AM10: =SUMIF($BC$1:$CI$1,AM$1,$BC10:$CI10)+AL10 -> 0 | AO10: =SUMIF($BC$1:$CI$1,AO$1,$BC10:$CI10)+AN10 -> 0 | AP10: =CK10 -> 0 | AT10: =AE10+AG10+AI10+AK10+AM10+AO10+SUM(AQ10:AS10) -> 0 | AZ10: =VLOOKUP(C10,Employees!D:I,6,FALSE) -> #N/A | BA10: =IF(ISBLANK(D10),0,(E10-D10)*24) -> 0 | BB10: =IF(BA10>$AY$1,1,IF(BA10>=$AX$1,0.5,0)) -> 0 | BC10: =BA10-BB10-BD10-BE10 -> 0 | BD10: =IF(AND(E10>$AV$1, D10<$AW$1),(MIN(E10,$AW$1)-MAX(D10,$AV$1))*24,0) -> 0 | BE10: =IF(E10>$AW$1,(E10-MAX(D10,$AW$1))*24,0) -> 0 | BF10: =IF(ISBLANK(G10),0,(H10-G10)*24) -> 0 | BG10: =IF(BF10>$AY$1,1,IF(BF10>=$AX$1,0.5,0)) -> 0 | BH10: =BF10-BG10-BI10-BJ10 -> 0 | BI10: =IF(AND(H10>$AV$1,G10<$AW$1),(MIN(H10,$AW$1)-MAX(G10,$AV$1))*24,0) -> 0 | BJ10: =IF(H10>$AW$1,(H10-MAX(G10,$AW$1))*24,0) -> 0 | BK10: =IF(ISBLANK(J10),0,(K10-J10)*24) -> 0 | BL10: =IF(BK10>$AY$1,1,IF(BK10>=$AX$1,0.5,0)) -> 0 | BM10: =BK10-BL10-BN10-BO10 -> 0 | BN10: =IF(AND(K10>$AV$1, J10<$AW$1),(MIN(K10,$AW$1)-MAX(J10,$AV$1))*24,0) -> 0 | BO10: =IF(K10>$AW$1,(K10-MAX(J10,$AW$1))*24,0) -> 0 | BP10: =IF(ISBLANK(M10),0,(N10-M10)*24) -> 0 | BQ10: =IF(BP10>$AY$1,1,IF(BP10>=$AX$1,0.5,0)) -> 0 | BR10: =BP10-BQ10-BS10-BT10 -> 0 | BS10: =IF(AND(N10>$AV$1, M10<$AW$1),(MIN(N10,$AW$1)-MAX(M10,$AV$1))*24,0) -> 0 | BT10: =IF(N10>$AW$1,(N10-MAX(M10,$AW$1))*24,0) -> 0 | BU10: =IF(ISBLANK(P10),0,(Q10-P10)*24) -> 0 | BV10: =IF(BU10>$AY$1,1,IF(BU10>=$AX$1,0.5,0)) -> 0 | BW10: =BU10-BV10-BX10-BY10 -> 0 | BX10: =IF(AND(Q10>$AV$1, P10<$AW$1),(MIN(Q10,$AW$1)-MAX(P10,$AV$1))*24,0) -> 0 | BY10: =IF(Q10>$AW$1,(Q10-MAX(P10,$AW$1))*24,0) -> 0 | BZ10: =IF(ISBLANK(S10),0,(T10-S10)*24) -> 0 | CA10: =IF(BZ10>$AY$1,1,IF(BZ10>=$AX$1,0.5,0)) -> 0 | CB10: =BZ10-CA10-CC10-CD10 -> 0 | CC10: =IF(AND(T10>$AV$1, S10<$AW$1),(MIN(T10,$AW$1)-MAX(S10,$AV$1))*24,0) -> 0 | CD10: =IF(T10>$AW$1,(T10-MAX(S10,$AW$1))*24,0) -> 0 | CE10: =IF(ISBLANK(V10),0,(W10-V10)*24) -> 0 | CF10: =IF(CE10>$AY$1,1,IF(CE10>=$AX$1,0.5,0)) -> 0 | CG10: =CE10-CF10-CH10-CI10 -> 0 | CH10: =IF(AND(W10>$AV$1, V10<$AW$1),(MIN(W10,$AW$1)-MAX(V10,$AV$1))*24,0) -> 0 | CI10: =IF(W10>$AW$1,(W10-MAX(V10,$AW$1))*24,0) -> 0 | CK10: =SUM(IF(F10>0,1,0),IF(I10>0,1,0),IF(L10>0,1,0),IF(O10>0,1,0),IF(R10>0,1,0),IF(U10>0,1,0),IF(X10>0,1,0)) -> 0
A11: =IF(ISNA(AZ11),"",AZ11) | F11: =BA11-BB11 -> 0 | I11: =BF11-BG11 -> 0 | L11: =BK11-BL11 -> 0 | O11: =BP11-BQ11 -> 0 | R11: =BU11-BV11 -> 0 | U11: =BZ11-CA11 -> 0 | X11: =CE11-CF11 -> 0 | AB11: =SUM(F11,I11,L11,O11,R11,U11,X11) -> 0 | AE11: =SUMIF($BC$1:$CI$1,AE$1,$BC11:$CI11)+AD11 -> 0 | AG11: =SUMIF($BC$1:$CI$1,AG$1,$BC11:$CI11)+AF11 -> 0 | AI11: =SUMIF($BC$1:$CI$1,AI$1,$BC11:$CI11)+AH11 -> 0 | AK11: =SUMIF($BC$1:$CI$1,AK$1,$BC11:$CI11)+AJ11 -> 0 | AM11: =SUMIF($BC$1:$CI$1,AM$1,$BC11:$CI11)+AL11 -> 0 | AO11: =SUMIF($BC$1:$CI$1,AO$1,$BC11:$CI11)+AN11 -> 0 | AP11: =CK11 -> 0 | AT11: =AE11+AG11+AI11+AK11+AM11+AO11+SUM(AQ11:AS11) -> 0 | AZ11: =VLOOKUP(C11,Employees!D:I,6,FALSE) -> #N/A | BA11: =IF(ISBLANK(D11),0,(E11-D11)*24) -> 0 | BB11: =IF(BA11>$AY$1,1,IF(BA11>=$AX$1,0.5,0)) -> 0 | BC11: =BA11-BB11-BD11-BE11 -> 0 | BD11: =IF(AND(E11>$AV$1, D11<$AW$1),(MIN(E11,$AW$1)-MAX(D11,$AV$1))*24,0) -> 0 | BE11: =IF(E11>$AW$1,(E11-MAX(D11,$AW$1))*24,0) -> 0 | BF11: =IF(ISBLANK(G11),0,(H11-G11)*24) -> 0 | BG11: =IF(BF11>$AY$1,1,IF(BF11>=$AX$1,0.5,0)) -> 0 | BH11: =BF11-BG11-BI11-BJ11 -> 0 | BI11: =IF(AND(H11>$AV$1,G11<$AW$1),(MIN(H11,$AW$1)-MAX(G11,$AV$1))*24,0) -> 0 | BJ11: =IF(H11>$AW$1,(H11-MAX(G11,$AW$1))*24,0) -> 0 | BK11: =IF(ISBLANK(J11),0,(K11-J11)*24) -> 0 | BL11: =IF(BK11>$AY$1,1,IF(BK11>=$AX$1,0.5,0)) -> 0 | BM11: =BK11-BL11-BN11-BO11 -> 0 | BN11: =IF(AND(K11>$AV$1, J11<$AW$1),(MIN(K11,$AW$1)-MAX(J11,$AV$1))*24,0) -> 0 | BO11: =IF(K11>$AW$1,(K11-MAX(J11,$AW$1))*24,0) -> 0 | BP11: =IF(ISBLANK(M11),0,(N11-M11)*24) -> 0 | BQ11: =IF(BP11>$AY$1,1,IF(BP11>=$AX$1,0.5,0)) -> 0 | BR11: =BP11-BQ11-BS11-BT11 -> 0 | BS11: =IF(AND(N11>$AV$1, M11<$AW$1),(MIN(N11,$AW$1)-MAX(M11,$AV$1))*24,0) -> 0 | BT11: =IF(N11>$AW$1,(N11-MAX(M11,$AW$1))*24,0) -> 0 | BU11: =IF(ISBLANK(P11),0,(Q11-P11)*24) -> 0 | BV11: =IF(BU11>$AY$1,1,IF(BU11>=$AX$1,0.5,0)) -> 0 | BW11: =BU11-BV11-BX11-BY11 -> 0 | BX11: =IF(AND(Q11>$AV$1, P11<$AW$1),(MIN(Q11,$AW$1)-MAX(P11,$AV$1))*24,0) -> 0 | BY11: =IF(Q11>$AW$1,(Q11-MAX(P11,$AW$1))*24,0) -> 0 | BZ11: =IF(ISBLANK(S11),0,(T11-S11)*24) -> 0 | CA11: =IF(BZ11>$AY$1,1,IF(BZ11>=$AX$1,0.5,0)) -> 0 | CB11: =BZ11-CA11-CC11-CD11 -> 0 | CC11: =IF(AND(T11>$AV$1, S11<$AW$1),(MIN(T11,$AW$1)-MAX(S11,$AV$1))*24,0) -> 0 | CD11: =IF(T11>$AW$1,(T11-MAX(S11,$AW$1))*24,0) -> 0 | CE11: =IF(ISBLANK(V11),0,(W11-V11)*24) -> 0 | CF11: =IF(CE11>$AY$1,1,IF(CE11>=$AX$1,0.5,0)) -> 0 | CG11: =CE11-CF11-CH11-CI11 -> 0 | CH11: =IF(AND(W11>$AV$1, V11<$AW$1),(MIN(W11,$AW$1)-MAX(V11,$AV$1))*24,0) -> 0 | CI11: =IF(W11>$AW$1,(W11-MAX(V11,$AW$1))*24,0) -> 0 | CK11: =SUM(IF(F11>0,1,0),IF(I11>0,1,0),IF(L11>0,1,0),IF(O11>0,1,0),IF(R11>0,1,0),IF(U11>0,1,0),IF(X11>0,1,0)) -> 0
A12: =IF(ISNA(AZ12),"",AZ12) | F12: =BA12-BB12 -> 0 | I12: =BF12-BG12 -> 0 | L12: =BK12-BL12 -> 0 | O12: =BP12-BQ12 -> 0 | R12: =BU12-BV12 -> 0 | U12: =BZ12-CA12 -> 0 | X12: =CE12-CF12 -> 0 | AB12: =SUM(F12,I12,L12,O12,R12,U12,X12) -> 0 | AE12: =SUMIF($BC$1:$CI$1,AE$1,$BC12:$CI12)+AD12 -> 0 | AG12: =SUMIF($BC$1:$CI$1,AG$1,$BC12:$CI12)+AF12 -> 0 | AI12: =SUMIF($BC$1:$CI$1,AI$1,$BC12:$CI12)+AH12 -> 0 | AK12: =SUMIF($BC$1:$CI$1,AK$1,$BC12:$CI12)+AJ12 -> 0 | AM12: =SUMIF($BC$1:$CI$1,AM$1,$BC12:$CI12)+AL12 -> 0 | AO12: =SUMIF($BC$1:$CI$1,AO$1,$BC12:$CI12)+AN12 -> 0 | AP12: =CK12 -> 0 | AT12: =AE12+AG12+AI12+AK12+AM12+AO12+SUM(AQ12:AS12) -> 0 | AZ12: =VLOOKUP(C12,Employees!D:I,6,FALSE) -> #N/A | BA12: =IF(ISBLANK(D12),0,(E12-D12)*24) -> 0 | BB12: =IF(BA12>$AY$1,1,IF(BA12>=$AX$1,0.5,0)) -> 0 | BC12: =BA12-BB12-BD12-BE12 -> 0 | BD12: =IF(AND(E12>$AV$1, D12<$AW$1),(MIN(E12,$AW$1)-MAX(D12,$AV$1))*24,0) -> 0 | BE12: =IF(E12>$AW$1,(E12-MAX(D12,$AW$1))*24,0) -> 0 | BF12: =IF(ISBLANK(G12),0,(H12-G12)*24) -> 0 | BG12: =IF(BF12>$AY$1,1,IF(BF12>=$AX$1,0.5,0)) -> 0 | BH12: =BF12-BG12-BI12-BJ12 -> 0 | BI12: =IF(AND(H12>$AV$1,G12<$AW$1),(MIN(H12,$AW$1)-MAX(G12,$AV$1))*24,0) -> 0 | BJ12: =IF(H12>$AW$1,(H12-MAX(G12,$AW$1))*24,0) -> 0 | BK12: =IF(ISBLANK(J12),0,(K12-J12)*24) -> 0 | BL12: =IF(BK12>$AY$1,1,IF(BK12>=$AX$1,0.5,0)) -> 0 | BM12: =BK12-BL12-BN12-BO12 -> 0 | BN12: =IF(AND(K12>$AV$1, J12<$AW$1),(MIN(K12,$AW$1)-MAX(J12,$AV$1))*24,0) -> 0 | BO12: =IF(K12>$AW$1,(K12-MAX(J12,$AW$1))*24,0) -> 0 | BP12: =IF(ISBLANK(M12),0,(N12-M12)*24) -> 0 | BQ12: =IF(BP12>$AY$1,1,IF(BP12>=$AX$1,0.5,0)) -> 0 | BR12: =BP12-BQ12-BS12-BT12 -> 0 | BS12: =IF(AND(N12>$AV$1, M12<$AW$1),(MIN(N12,$AW$1)-MAX(M12,$AV$1))*24,0) -> 0 | BT12: =IF(N12>$AW$1,(N12-MAX(M12,$AW$1))*24,0) -> 0 | BU12: =IF(ISBLANK(P12),0,(Q12-P12)*24) -> 0 | BV12: =IF(BU12>$AY$1,1,IF(BU12>=$AX$1,0.5,0)) -> 0 | BW12: =BU12-BV12-BX12-BY12 -> 0 | BX12: =IF(AND(Q12>$AV$1, P12<$AW$1),(MIN(Q12,$AW$1)-MAX(P12,$AV$1))*24,0) -> 0 | BY12: =IF(Q12>$AW$1,(Q12-MAX(P12,$AW$1))*24,0) -> 0 | BZ12: =IF(ISBLANK(S12),0,(T12-S12)*24) -> 0 | CA12: =IF(BZ12>$AY$1,1,IF(BZ12>=$AX$1,0.5,0)) -> 0 | CB12: =BZ12-CA12-CC12-CD12 -> 0 | CC12: =IF(AND(T12>$AV$1, S12<$AW$1),(MIN(T12,$AW$1)-MAX(S12,$AV$1))*24,0) -> 0 | CD12: =IF(T12>$AW$1,(T12-MAX(S12,$AW$1))*24,0) -> 0 | CE12: =IF(ISBLANK(V12),0,(W12-V12)*24) -> 0 | CF12: =IF(CE12>$AY$1,1,IF(CE12>=$AX$1,0.5,0)) -> 0 | CG12: =CE12-CF12-CH12-CI12 -> 0 | CH12: =IF(AND(W12>$AV$1, V12<$AW$1),(MIN(W12,$AW$1)-MAX(V12,$AV$1))*24,0) -> 0 | CI12: =IF(W12>$AW$1,(W12-MAX(V12,$AW$1))*24,0) -> 0 | CK12: =SUM(IF(F12>0,1,0),IF(I12>0,1,0),IF(L12>0,1,0),IF(O12>0,1,0),IF(R12>0,1,0),IF(U12>0,1,0),IF(X12>0,1,0)) -> 0
A13: =IF(ISNA(AZ13),"",AZ13) | F13: =BA13-BB13 -> 0 | I13: =BF13-BG13 -> 0 | L13: =BK13-BL13 -> 0 | O13: =BP13-BQ13 -> 0 | R13: =BU13-BV13 -> 0 | U13: =BZ13-CA13 -> 0 | X13: =CE13-CF13 -> 0 | AB13: =SUM(F13,I13,L13,O13,R13,U13,X13) -> 0 | AE13: =SUMIF($BC$1:$CI$1,AE$1,$BC13:$CI13)+AD13 -> 0 | AG13: =SUMIF($BC$1:$CI$1,AG$1,$BC13:$CI13)+AF13 -> 0 | AI13: =SUMIF($BC$1:$CI$1,AI$1,$BC13:$CI13)+AH13 -> 0 | AK13: =SUMIF($BC$1:$CI$1,AK$1,$BC13:$CI13)+AJ13 -> 0 | AM13: =SUMIF($BC$1:$CI$1,AM$1,$BC13:$CI13)+AL13 -> 0 | AO13: =SUMIF($BC$1:$CI$1,AO$1,$BC13:$CI13)+AN13 -> 0 | AP13: =CK13 -> 0 | AT13: =AE13+AG13+AI13+AK13+AM13+AO13+SUM(AQ13:AS13) -> 0 | AZ13: =VLOOKUP(C13,Employees!D:I,6,FALSE) -> #N/A | BA13: =IF(ISBLANK(D13),0,(E13-D13)*24) -> 0 | BB13: =IF(BA13>$AY$1,1,IF(BA13>=$AX$1,0.5,0)) -> 0 | BC13: =BA13-BB13-BD13-BE13 -> 0 | BD13: =IF(AND(E13>$AV$1, D13<$AW$1),(MIN(E13,$AW$1)-MAX(D13,$AV$1))*24,0) -> 0 | BE13: =IF(E13>$AW$1,(E13-MAX(D13,$AW$1))*24,0) -> 0 | BF13: =IF(ISBLANK(G13),0,(H13-G13)*24) -> 0 | BG13: =IF(BF13>$AY$1,1,IF(BF13>=$AX$1,0.5,0)) -> 0 | BH13: =BF13-BG13-BI13-BJ13 -> 0 | BI13: =IF(AND(H13>$AV$1,G13<$AW$1),(MIN(H13,$AW$1)-MAX(G13,$AV$1))*24,0) -> 0 | BJ13: =IF(H13>$AW$1,(H13-MAX(G13,$AW$1))*24,0) -> 0 | BK13: =IF(ISBLANK(J13),0,(K13-J13)*24) -> 0 | BL13: =IF(BK13>$AY$1,1,IF(BK13>=$AX$1,0.5,0)) -> 0 | BM13: =BK13-BL13-BN13-BO13 -> 0 | BN13: =IF(AND(K13>$AV$1, J13<$AW$1),(MIN(K13,$AW$1)-MAX(J13,$AV$1))*24,0) -> 0 | BO13: =IF(K13>$AW$1,(K13-MAX(J13,$AW$1))*24,0) -> 0 | BP13: =IF(ISBLANK(M13),0,(N13-M13)*24) -> 0 | BQ13: =IF(BP13>$AY$1,1,IF(BP13>=$AX$1,0.5,0)) -> 0 | BR13: =BP13-BQ13-BS13-BT13 -> 0 | BS13: =IF(AND(N13>$AV$1, M13<$AW$1),(MIN(N13,$AW$1)-MAX(M13,$AV$1))*24,0) -> 0 | BT13: =IF(N13>$AW$1,(N13-MAX(M13,$AW$1))*24,0) -> 0 | BU13: =IF(ISBLANK(P13),0,(Q13-P13)*24) -> 0 | BV13: =IF(BU13>$AY$1,1,IF(BU13>=$AX$1,0.5,0)) -> 0 | BW13: =BU13-BV13-BX13-BY13 -> 0 | BX13: =IF(AND(Q13>$AV$1, P13<$AW$1),(MIN(Q13,$AW$1)-MAX(P13,$AV$1))*24,0) -> 0 | BY13: =IF(Q13>$AW$1,(Q13-MAX(P13,$AW$1))*24,0) -> 0 | BZ13: =IF(ISBLANK(S13),0,(T13-S13)*24) -> 0 | CA13: =IF(BZ13>$AY$1,1,IF(BZ13>=$AX$1,0.5,0)) -> 0 | CB13: =BZ13-CA13-CC13-CD13 -> 0 | CC13: =IF(AND(T13>$AV$1, S13<$AW$1),(MIN(T13,$AW$1)-MAX(S13,$AV$1))*24,0) -> 0 | CD13: =IF(T13>$AW$1,(T13-MAX(S13,$AW$1))*24,0) -> 0 | CE13: =IF(ISBLANK(V13),0,(W13-V13)*24) -> 0 | CF13: =IF(CE13>$AY$1,1,IF(CE13>=$AX$1,0.5,0)) -> 0 | CG13: =CE13-CF13-CH13-CI13 -> 0 | CH13: =IF(AND(W13>$AV$1, V13<$AW$1),(MIN(W13,$AW$1)-MAX(V13,$AV$1))*24,0) -> 0 | CI13: =IF(W13>$AW$1,(W13-MAX(V13,$AW$1))*24,0) -> 0 | CK13: =SUM(IF(F13>0,1,0),IF(I13>0,1,0),IF(L13>0,1,0),IF(O13>0,1,0),IF(R13>0,1,0),IF(U13>0,1,0),IF(X13>0,1,0)) -> 0
A14: =IF(ISNA(AZ14),"",AZ14) | F14: =BA14-BB14 -> 0 | I14: =BF14-BG14 -> 0 | L14: =BK14-BL14 -> 0 | O14: =BP14-BQ14 -> 0 | R14: =BU14-BV14 -> 0 | U14: =BZ14-CA14 -> 0 | X14: =CE14-CF14 -> 0 | AB14: =SUM(F14,I14,L14,O14,R14,U14,X14) -> 0 | AE14: =SUMIF($BC$1:$CI$1,AE$1,$BC14:$CI14)+AD14 -> 0 | AG14: =SUMIF($BC$1:$CI$1,AG$1,$BC14:$CI14)+AF14 -> 0 | AI14: =SUMIF($BC$1:$CI$1,AI$1,$BC14:$CI14)+AH14 -> 0 | AK14: =SUMIF($BC$1:$CI$1,AK$1,$BC14:$CI14)+AJ14 -> 0 | AM14: =SUMIF($BC$1:$CI$1,AM$1,$BC14:$CI14)+AL14 -> 0 | AO14: =SUMIF($BC$1:$CI$1,AO$1,$BC14:$CI14)+AN14 -> 0 | AP14: =CK14 -> 0 | AT14: =AE14+AG14+AI14+AK14+AM14+AO14+SUM(AQ14:AS14) -> 0 | AZ14: =VLOOKUP(C14,Employees!D:I,6,FALSE) -> #N/A | BA14: =IF(ISBLANK(D14),0,(E14-D14)*24) -> 0 | BB14: =IF(BA14>$AY$1,1,IF(BA14>=$AX$1,0.5,0)) -> 0 | BC14: =BA14-BB14-BD14-BE14 -> 0 | BD14: =IF(AND(E14>$AV$1, D14<$AW$1),(MIN(E14,$AW$1)-MAX(D14,$AV$1))*24,0) -> 0 | BE14: =IF(E14>$AW$1,(E14-MAX(D14,$AW$1))*24,0) -> 0 | BF14: =IF(ISBLANK(G14),0,(H14-G14)*24) -> 0 | BG14: =IF(BF14>$AY$1,1,IF(BF14>=$AX$1,0.5,0)) -> 0 | BH14: =BF14-BG14-BI14-BJ14 -> 0 | BI14: =IF(AND(H14>$AV$1,G14<$AW$1),(MIN(H14,$AW$1)-MAX(G14,$AV$1))*24,0) -> 0 | BJ14: =IF(H14>$AW$1,(H14-MAX(G14,$AW$1))*24,0) -> 0 | BK14: =IF(ISBLANK(J14),0,(K14-J14)*24) -> 0 | BL14: =IF(BK14>$AY$1,1,IF(BK14>=$AX$1,0.5,0)) -> 0 | BM14: =BK14-BL14-BN14-BO14 -> 0 | BN14: =IF(AND(K14>$AV$1, J14<$AW$1),(MIN(K14,$AW$1)-MAX(J14,$AV$1))*24,0) -> 0 | BO14: =IF(K14>$AW$1,(K14-MAX(J14,$AW$1))*24,0) -> 0 | BP14: =IF(ISBLANK(M14),0,(N14-M14)*24) -> 0 | BQ14: =IF(BP14>$AY$1,1,IF(BP14>=$AX$1,0.5,0)) -> 0 | BR14: =BP14-BQ14-BS14-BT14 -> 0 | BS14: =IF(AND(N14>$AV$1, M14<$AW$1),(MIN(N14,$AW$1)-MAX(M14,$AV$1))*24,0) -> 0 | BT14: =IF(N14>$AW$1,(N14-MAX(M14,$AW$1))*24,0) -> 0 | BU14: =IF(ISBLANK(P14),0,(Q14-P14)*24) -> 0 | BV14: =IF(BU14>$AY$1,1,IF(BU14>=$AX$1,0.5,0)) -> 0 | BW14: =BU14-BV14-BX14-BY14 -> 0 | BX14: =IF(AND(Q14>$AV$1, P14<$AW$1),(MIN(Q14,$AW$1)-MAX(P14,$AV$1))*24,0) -> 0 | BY14: =IF(Q14>$AW$1,(Q14-MAX(P14,$AW$1))*24,0) -> 0 | BZ14: =IF(ISBLANK(S14),0,(T14-S14)*24) -> 0 | CA14: =IF(BZ14>$AY$1,1,IF(BZ14>=$AX$1,0.5,0)) -> 0 | CB14: =BZ14-CA14-CC14-CD14 -> 0 | CC14: =IF(AND(T14>$AV$1, S14<$AW$1),(MIN(T14,$AW$1)-MAX(S14,$AV$1))*24,0) -> 0 | CD14: =IF(T14>$AW$1,(T14-MAX(S14,$AW$1))*24,0) -> 0 | CE14: =IF(ISBLANK(V14),0,(W14-V14)*24) -> 0 | CF14: =IF(CE14>$AY$1,1,IF(CE14>=$AX$1,0.5,0)) -> 0 | CG14: =CE14-CF14-CH14-CI14 -> 0 | CH14: =IF(AND(W14>$AV$1, V14<$AW$1),(MIN(W14,$AW$1)-MAX(V14,$AV$1))*24,0) -> 0 | CI14: =IF(W14>$AW$1,(W14-MAX(V14,$AW$1))*24,0) -> 0 | CK14: =SUM(IF(F14>0,1,0),IF(I14>0,1,0),IF(L14>0,1,0),IF(O14>0,1,0),IF(R14>0,1,0),IF(U14>0,1,0),IF(X14>0,1,0)) -> 0
A15: =IF(ISNA(AZ15),"",AZ15) | F15: =BA15-BB15 -> 0 | I15: =BF15-BG15 -> 0 | L15: =BK15-BL15 -> 0 | O15: =BP15-BQ15 -> 0 | R15: =BU15-BV15 -> 0 | U15: =BZ15-CA15 -> 0 | X15: =CE15-CF15 -> 0 | AB15: =SUM(F15,I15,L15,O15,R15,U15,X15) -> 0 | AE15: =SUMIF($BC$1:$CI$1,AE$1,$BC15:$CI15)+AD15 -> 0 | AG15: =SUMIF($BC$1:$CI$1,AG$1,$BC15:$CI15)+AF15 -> 0 | AI15: =SUMIF($BC$1:$CI$1,AI$1,$BC15:$CI15)+AH15 -> 0 | AK15: =SUMIF($BC$1:$CI$1,AK$1,$BC15:$CI15)+AJ15 -> 0 | AM15: =SUMIF($BC$1:$CI$1,AM$1,$BC15:$CI15)+AL15 -> 0 | AO15: =SUMIF($BC$1:$CI$1,AO$1,$BC15:$CI15)+AN15 -> 0 | AP15: =CK15 -> 0 | AT15: =AE15+AG15+AI15+AK15+AM15+AO15+SUM(AQ15:AS15) -> 0 | AZ15: =VLOOKUP(C15,Employees!D:I,6,FALSE) -> #N/A | BA15: =IF(ISBLANK(D15),0,(E15-D15)*24) -> 0 | BB15: =IF(BA15>$AY$1,1,IF(BA15>=$AX$1,0.5,0)) -> 0 | BC15: =BA15-BB15-BD15-BE15 -> 0 | BD15: =IF(AND(E15>$AV$1, D15<$AW$1),(MIN(E15,$AW$1)-MAX(D15,$AV$1))*24,0) -> 0 | BE15: =IF(E15>$AW$1,(E15-MAX(D15,$AW$1))*24,0) -> 0 | BF15: =IF(ISBLANK(G15),0,(H15-G15)*24) -> 0 | BG15: =IF(BF15>$AY$1,1,IF(BF15>=$AX$1,0.5,0)) -> 0 | BH15: =BF15-BG15-BI15-BJ15 -> 0 | BI15: =IF(AND(H15>$AV$1,G15<$AW$1),(MIN(H15,$AW$1)-MAX(G15,$AV$1))*24,0) -> 0 | BJ15: =IF(H15>$AW$1,(H15-MAX(G15,$AW$1))*24,0) -> 0 | BK15: =IF(ISBLANK(J15),0,(K15-J15)*24) -> 0 | BL15: =IF(BK15>$AY$1,1,IF(BK15>=$AX$1,0.5,0)) -> 0 | BM15: =BK15-BL15-BN15-BO15 -> 0 | BN15: =IF(AND(K15>$AV$1, J15<$AW$1),(MIN(K15,$AW$1)-MAX(J15,$AV$1))*24,0) -> 0 | BO15: =IF(K15>$AW$1,(K15-MAX(J15,$AW$1))*24,0) -> 0 | BP15: =IF(ISBLANK(M15),0,(N15-M15)*24) -> 0 | BQ15: =IF(BP15>$AY$1,1,IF(BP15>=$AX$1,0.5,0)) -> 0 | BR15: =BP15-BQ15-BS15-BT15 -> 0 | BS15: =IF(AND(N15>$AV$1, M15<$AW$1),(MIN(N15,$AW$1)-MAX(M15,$AV$1))*24,0) -> 0 | BT15: =IF(N15>$AW$1,(N15-MAX(M15,$AW$1))*24,0) -> 0 | BU15: =IF(ISBLANK(P15),0,(Q15-P15)*24) -> 0 | BV15: =IF(BU15>$AY$1,1,IF(BU15>=$AX$1,0.5,0)) -> 0 | BW15: =BU15-BV15-BX15-BY15 -> 0 | BX15: =IF(AND(Q15>$AV$1, P15<$AW$1),(MIN(Q15,$AW$1)-MAX(P15,$AV$1))*24,0) -> 0 | BY15: =IF(Q15>$AW$1,(Q15-MAX(P15,$AW$1))*24,0) -> 0 | BZ15: =IF(ISBLANK(S15),0,(T15-S15)*24) -> 0 | CA15: =IF(BZ15>$AY$1,1,IF(BZ15>=$AX$1,0.5,0)) -> 0 | CB15: =BZ15-CA15-CC15-CD15 -> 0 | CC15: =IF(AND(T15>$AV$1, S15<$AW$1),(MIN(T15,$AW$1)-MAX(S15,$AV$1))*24,0) -> 0 | CD15: =IF(T15>$AW$1,(T15-MAX(S15,$AW$1))*24,0) -> 0 | CE15: =IF(ISBLANK(V15),0,(W15-V15)*24) -> 0 | CF15: =IF(CE15>$AY$1,1,IF(CE15>=$AX$1,0.5,0)) -> 0 | CG15: =CE15-CF15-CH15-CI15 -> 0 | CH15: =IF(AND(W15>$AV$1, V15<$AW$1),(MIN(W15,$AW$1)-MAX(V15,$AV$1))*24,0) -> 0 | CI15: =IF(W15>$AW$1,(W15-MAX(V15,$AW$1))*24,0) -> 0 | CK15: =SUM(IF(F15>0,1,0),IF(I15>0,1,0),IF(L15>0,1,0),IF(O15>0,1,0),IF(R15>0,1,0),IF(U15>0,1,0),IF(X15>0,1,0)) -> 0
A16: =IF(ISNA(AZ16),"",AZ16) | F16: =BA16-BB16 -> 0 | I16: =BF16-BG16 -> 0 | L16: =BK16-BL16 -> 0 | O16: =BP16-BQ16 -> 0 | R16: =BU16-BV16 -> 0 | U16: =BZ16-CA16 -> 0 | X16: =CE16-CF16 -> 0 | AB16: =SUM(F16,I16,L16,O16,R16,U16,X16) -> 0 | AE16: =SUMIF($BC$1:$CI$1,AE$1,$BC16:$CI16)+AD16 -> 0 | AG16: =SUMIF($BC$1:$CI$1,AG$1,$BC16:$CI16)+AF16 -> 0 | AI16: =SUMIF($BC$1:$CI$1,AI$1,$BC16:$CI16)+AH16 -> 0 | AK16: =SUMIF($BC$1:$CI$1,AK$1,$BC16:$CI16)+AJ16 -> 0 | AM16: =SUMIF($BC$1:$CI$1,AM$1,$BC16:$CI16)+AL16 -> 0 | AO16: =SUMIF($BC$1:$CI$1,AO$1,$BC16:$CI16)+AN16 -> 0 | AP16: =CK16 -> 0 | AT16: =AE16+AG16+AI16+AK16+AM16+AO16+SUM(AQ16:AS16) -> 0 | AZ16: =VLOOKUP(C16,Employees!D:I,6,FALSE) -> #N/A | BA16: =IF(ISBLANK(D16),0,(E16-D16)*24) -> 0 | BB16: =IF(BA16>$AY$1,1,IF(BA16>=$AX$1,0.5,0)) -> 0 | BC16: =BA16-BB16-BD16-BE16 -> 0 | BD16: =IF(AND(E16>$AV$1, D16<$AW$1),(MIN(E16,$AW$1)-MAX(D16,$AV$1))*24,0) -> 0 | BE16: =IF(E16>$AW$1,(E16-MAX(D16,$AW$1))*24,0) -> 0 | BF16: =IF(ISBLANK(G16),0,(H16-G16)*24) -> 0 | BG16: =IF(BF16>$AY$1,1,IF(BF16>=$AX$1,0.5,0)) -> 0 | BH16: =BF16-BG16-BI16-BJ16 -> 0 | BI16: =IF(AND(H16>$AV$1,G16<$AW$1),(MIN(H16,$AW$1)-MAX(G16,$AV$1))*24,0) -> 0 | BJ16: =IF(H16>$AW$1,(H16-MAX(G16,$AW$1))*24,0) -> 0 | BK16: =IF(ISBLANK(J16),0,(K16-J16)*24) -> 0 | BL16: =IF(BK16>$AY$1,1,IF(BK16>=$AX$1,0.5,0)) -> 0 | BM16: =BK16-BL16-BN16-BO16 -> 0 | BN16: =IF(AND(K16>$AV$1, J16<$AW$1),(MIN(K16,$AW$1)-MAX(J16,$AV$1))*24,0) -> 0 | BO16: =IF(K16>$AW$1,(K16-MAX(J16,$AW$1))*24,0) -> 0 | BP16: =IF(ISBLANK(M16),0,(N16-M16)*24) -> 0 | BQ16: =IF(BP16>$AY$1,1,IF(BP16>=$AX$1,0.5,0)) -> 0 | BR16: =BP16-BQ16-BS16-BT16 -> 0 | BS16: =IF(AND(N16>$AV$1, M16<$AW$1),(MIN(N16,$AW$1)-MAX(M16,$AV$1))*24,0) -> 0 | BT16: =IF(N16>$AW$1,(N16-MAX(M16,$AW$1))*24,0) -> 0 | BU16: =IF(ISBLANK(P16),0,(Q16-P16)*24) -> 0 | BV16: =IF(BU16>$AY$1,1,IF(BU16>=$AX$1,0.5,0)) -> 0 | BW16: =BU16-BV16-BX16-BY16 -> 0 | BX16: =IF(AND(Q16>$AV$1, P16<$AW$1),(MIN(Q16,$AW$1)-MAX(P16,$AV$1))*24,0) -> 0 | BY16: =IF(Q16>$AW$1,(Q16-MAX(P16,$AW$1))*24,0) -> 0 | BZ16: =IF(ISBLANK(S16),0,(T16-S16)*24) -> 0 | CA16: =IF(BZ16>$AY$1,1,IF(BZ16>=$AX$1,0.5,0)) -> 0 | CB16: =BZ16-CA16-CC16-CD16 -> 0 | CC16: =IF(AND(T16>$AV$1, S16<$AW$1),(MIN(T16,$AW$1)-MAX(S16,$AV$1))*24,0) -> 0 | CD16: =IF(T16>$AW$1,(T16-MAX(S16,$AW$1))*24,0) -> 0 | CE16: =IF(ISBLANK(V16),0,(W16-V16)*24) -> 0 | CF16: =IF(CE16>$AY$1,1,IF(CE16>=$AX$1,0.5,0)) -> 0 | CG16: =CE16-CF16-CH16-CI16 -> 0 | CH16: =IF(AND(W16>$AV$1, V16<$AW$1),(MIN(W16,$AW$1)-MAX(V16,$AV$1))*24,0) -> 0 | CI16: =IF(W16>$AW$1,(W16-MAX(V16,$AW$1))*24,0) -> 0 | CK16: =SUM(IF(F16>0,1,0),IF(I16>0,1,0),IF(L16>0,1,0),IF(O16>0,1,0),IF(R16>0,1,0),IF(U16>0,1,0),IF(X16>0,1,0)) -> 0
A17: =IF(ISNA(AZ17),"",AZ17) | F17: =BA17-BB17 -> 0 | I17: =BF17-BG17 -> 0 | L17: =BK17-BL17 -> 0 | O17: =BP17-BQ17 -> 0 | R17: =BU17-BV17 -> 0 | U17: =BZ17-CA17 -> 0 | X17: =CE17-CF17 -> 0 | AB17: =SUM(F17,I17,L17,O17,R17,U17,X17) -> 0 | AE17: =SUMIF($BC$1:$CI$1,AE$1,$BC17:$CI17)+AD17 -> 0 | AG17: =SUMIF($BC$1:$CI$1,AG$1,$BC17:$CI17)+AF17 -> 0 | AI17: =SUMIF($BC$1:$CI$1,AI$1,$BC17:$CI17)+AH17 -> 0 | AK17: =SUMIF($BC$1:$CI$1,AK$1,$BC17:$CI17)+AJ17 -> 0 | AM17: =SUMIF($BC$1:$CI$1,AM$1,$BC17:$CI17)+AL17 -> 0 | AO17: =SUMIF($BC$1:$CI$1,AO$1,$BC17:$CI17)+AN17 -> 0 | AP17: =CK17 -> 0 | AT17: =AE17+AG17+AI17+AK17+AM17+AO17+SUM(AQ17:AS17) -> 0 | AZ17: =VLOOKUP(C17,Employees!D:I,6,FALSE) -> #N/A | BA17: =IF(ISBLANK(D17),0,(E17-D17)*24) -> 0 | BB17: =IF(BA17>$AY$1,1,IF(BA17>=$AX$1,0.5,0)) -> 0 | BC17: =BA17-BB17-BD17-BE17 -> 0 | BD17: =IF(AND(E17>$AV$1, D17<$AW$1),(MIN(E17,$AW$1)-MAX(D17,$AV$1))*24,0) -> 0 | BE17: =IF(E17>$AW$1,(E17-MAX(D17,$AW$1))*24,0) -> 0 | BF17: =IF(ISBLANK(G17),0,(H17-G17)*24) -> 0 | BG17: =IF(BF17>$AY$1,1,IF(BF17>=$AX$1,0.5,0)) -> 0 | BH17: =BF17-BG17-BI17-BJ17 -> 0 | BI17: =IF(AND(H17>$AV$1,G17<$AW$1),(MIN(H17,$AW$1)-MAX(G17,$AV$1))*24,0) -> 0 | BJ17: =IF(H17>$AW$1,(H17-MAX(G17,$AW$1))*24,0) -> 0 | BK17: =IF(ISBLANK(J17),0,(K17-J17)*24) -> 0 | BL17: =IF(BK17>$AY$1,1,IF(BK17>=$AX$1,0.5,0)) -> 0 | BM17: =BK17-BL17-BN17-BO17 -> 0 | BN17: =IF(AND(K17>$AV$1, J17<$AW$1),(MIN(K17,$AW$1)-MAX(J17,$AV$1))*24,0) -> 0 | BO17: =IF(K17>$AW$1,(K17-MAX(J17,$AW$1))*24,0) -> 0 | BP17: =IF(ISBLANK(M17),0,(N17-M17)*24) -> 0 | BQ17: =IF(BP17>$AY$1,1,IF(BP17>=$AX$1,0.5,0)) -> 0 | BR17: =BP17-BQ17-BS17-BT17 -> 0 | BS17: =IF(AND(N17>$AV$1, M17<$AW$1),(MIN(N17,$AW$1)-MAX(M17,$AV$1))*24,0) -> 0 | BT17: =IF(N17>$AW$1,(N17-MAX(M17,$AW$1))*24,0) -> 0 | BU17: =IF(ISBLANK(P17),0,(Q17-P17)*24) -> 0 | BV17: =IF(BU17>$AY$1,1,IF(BU17>=$AX$1,0.5,0)) -> 0 | BW17: =BU17-BV17-BX17-BY17 -> 0 | BX17: =IF(AND(Q17>$AV$1, P17<$AW$1),(MIN(Q17,$AW$1)-MAX(P17,$AV$1))*24,0) -> 0 | BY17: =IF(Q17>$AW$1,(Q17-MAX(P17,$AW$1))*24,0) -> 0 | BZ17: =IF(ISBLANK(S17),0,(T17-S17)*24) -> 0 | CA17: =IF(BZ17>$AY$1,1,IF(BZ17>=$AX$1,0.5,0)) -> 0 | CB17: =BZ17-CA17-CC17-CD17 -> 0 | CC17: =IF(AND(T17>$AV$1, S17<$AW$1),(MIN(T17,$AW$1)-MAX(S17,$AV$1))*24,0) -> 0 | CD17: =IF(T17>$AW$1,(T17-MAX(S17,$AW$1))*24,0) -> 0 | CE17: =IF(ISBLANK(V17),0,(W17-V17)*24) -> 0 | CF17: =IF(CE17>$AY$1,1,IF(CE17>=$AX$1,0.5,0)) -> 0 | CG17: =CE17-CF17-CH17-CI17 -> 0 | CH17: =IF(AND(W17>$AV$1, V17<$AW$1),(MIN(W17,$AW$1)-MAX(V17,$AV$1))*24,0) -> 0 | CI17: =IF(W17>$AW$1,(W17-MAX(V17,$AW$1))*24,0) -> 0 | CK17: =SUM(IF(F17>0,1,0),IF(I17>0,1,0),IF(L17>0,1,0),IF(O17>0,1,0),IF(R17>0,1,0),IF(U17>0,1,0),IF(X17>0,1,0)) -> 0
A18: =IF(ISNA(AZ18),"",AZ18) | F18: =BA18-BB18 -> 0 | I18: =BF18-BG18 -> 0 | L18: =BK18-BL18 -> 0 | O18: =BP18-BQ18 -> 0 | R18: =BU18-BV18 -> 0 | U18: =BZ18-CA18 -> 0 | X18: =CE18-CF18 -> 0 | AB18: =SUM(F18,I18,L18,O18,R18,U18,X18) -> 0 | AE18: =SUMIF($BC$1:$CI$1,AE$1,$BC18:$CI18)+AD18 -> 0 | AG18: =SUMIF($BC$1:$CI$1,AG$1,$BC18:$CI18)+AF18 -> 0 | AI18: =SUMIF($BC$1:$CI$1,AI$1,$BC18:$CI18)+AH18 -> 0 | AK18: =SUMIF($BC$1:$CI$1,AK$1,$BC18:$CI18)+AJ18 -> 0 | AM18: =SUMIF($BC$1:$CI$1,AM$1,$BC18:$CI18)+AL18 -> 0 | AO18: =SUMIF($BC$1:$CI$1,AO$1,$BC18:$CI18)+AN18 -> 0 | AP18: =CK18 -> 0 | AT18: =AE18+AG18+AI18+AK18+AM18+AO18+SUM(AQ18:AS18) -> 0 | AZ18: =VLOOKUP(C18,Employees!D:I,6,FALSE) -> #N/A | BA18: =IF(ISBLANK(D18),0,(E18-D18)*24) -> 0 | BB18: =IF(BA18>$AY$1,1,IF(BA18>=$AX$1,0.5,0)) -> 0 | BC18: =BA18-BB18-BD18-BE18 -> 0 | BD18: =IF(AND(E18>$AV$1, D18<$AW$1),(MIN(E18,$AW$1)-MAX(D18,$AV$1))*24,0) -> 0 | BE18: =IF(E18>$AW$1,(E18-MAX(D18,$AW$1))*24,0) -> 0 | BF18: =IF(ISBLANK(G18),0,(H18-G18)*24) -> 0 | BG18: =IF(BF18>$AY$1,1,IF(BF18>=$AX$1,0.5,0)) -> 0 | BH18: =BF18-BG18-BI18-BJ18 -> 0 | BI18: =IF(AND(H18>$AV$1,G18<$AW$1),(MIN(H18,$AW$1)-MAX(G18,$AV$1))*24,0) -> 0 | BJ18: =IF(H18>$AW$1,(H18-MAX(G18,$AW$1))*24,0) -> 0 | BK18: =IF(ISBLANK(J18),0,(K18-J18)*24) -> 0 | BL18: =IF(BK18>$AY$1,1,IF(BK18>=$AX$1,0.5,0)) -> 0 | BM18: =BK18-BL18-BN18-BO18 -> 0 | BN18: =IF(AND(K18>$AV$1, J18<$AW$1),(MIN(K18,$AW$1)-MAX(J18,$AV$1))*24,0) -> 0 | BO18: =IF(K18>$AW$1,(K18-MAX(J18,$AW$1))*24,0) -> 0 | BP18: =IF(ISBLANK(M18),0,(N18-M18)*24) -> 0 | BQ18: =IF(BP18>$AY$1,1,IF(BP18>=$AX$1,0.5,0)) -> 0 | BR18: =BP18-BQ18-BS18-BT18 -> 0 | BS18: =IF(AND(N18>$AV$1, M18<$AW$1),(MIN(N18,$AW$1)-MAX(M18,$AV$1))*24,0) -> 0 | BT18: =IF(N18>$AW$1,(N18-MAX(M18,$AW$1))*24,0) -> 0 | BU18: =IF(ISBLANK(P18),0,(Q18-P18)*24) -> 0 | BV18: =IF(BU18>$AY$1,1,IF(BU18>=$AX$1,0.5,0)) -> 0 | BW18: =BU18-BV18-BX18-BY18 -> 0 | BX18: =IF(AND(Q18>$AV$1, P18<$AW$1),(MIN(Q18,$AW$1)-MAX(P18,$AV$1))*24,0) -> 0 | BY18: =IF(Q18>$AW$1,(Q18-MAX(P18,$AW$1))*24,0) -> 0 | BZ18: =IF(ISBLANK(S18),0,(T18-S18)*24) -> 0 | CA18: =IF(BZ18>$AY$1,1,IF(BZ18>=$AX$1,0.5,0)) -> 0 | CB18: =BZ18-CA18-CC18-CD18 -> 0 | CC18: =IF(AND(T18>$AV$1, S18<$AW$1),(MIN(T18,$AW$1)-MAX(S18,$AV$1))*24,0) -> 0 | CD18: =IF(T18>$AW$1,(T18-MAX(S18,$AW$1))*24,0) -> 0 | CE18: =IF(ISBLANK(V18),0,(W18-V18)*24) -> 0 | CF18: =IF(CE18>$AY$1,1,IF(CE18>=$AX$1,0.5,0)) -> 0 | CG18: =CE18-CF18-CH18-CI18 -> 0 | CH18: =IF(AND(W18>$AV$1, V18<$AW$1),(MIN(W18,$AW$1)-MAX(V18,$AV$1))*24,0) -> 0 | CI18: =IF(W18>$AW$1,(W18-MAX(V18,$AW$1))*24,0) -> 0 | CK18: =SUM(IF(F18>0,1,0),IF(I18>0,1,0),IF(L18>0,1,0),IF(O18>0,1,0),IF(R18>0,1,0),IF(U18>0,1,0),IF(X18>0,1,0)) -> 0
A19: =IF(ISNA(AZ19),"",AZ19) | F19: =BA19-BB19 -> 0 | I19: =BF19-BG19 -> 0 | L19: =BK19-BL19 -> 0 | O19: =BP19-BQ19 -> 0 | R19: =BU19-BV19 -> 0 | U19: =BZ19-CA19 -> 0 | X19: =CE19-CF19 -> 0 | AB19: =SUM(F19,I19,L19,O19,R19,U19,X19) -> 0 | AE19: =SUMIF($BC$1:$CI$1,AE$1,$BC19:$CI19)+AD19 -> 0 | AG19: =SUMIF($BC$1:$CI$1,AG$1,$BC19:$CI19)+AF19 -> 0 | AI19: =SUMIF($BC$1:$CI$1,AI$1,$BC19:$CI19)+AH19 -> 0 | AK19: =SUMIF($BC$1:$CI$1,AK$1,$BC19:$CI19)+AJ19 -> 0 | AM19: =SUMIF($BC$1:$CI$1,AM$1,$BC19:$CI19)+AL19 -> 0 | AO19: =SUMIF($BC$1:$CI$1,AO$1,$BC19:$CI19)+AN19 -> 0 | AP19: =CK19 -> 0 | AT19: =AE19+AG19+AI19+AK19+AM19+AO19+SUM(AQ19:AS19) -> 0 | AZ19: =VLOOKUP(C19,Employees!D:I,6,FALSE) -> #N/A | BA19: =IF(ISBLANK(D19),0,(E19-D19)*24) -> 0 | BB19: =IF(BA19>$AY$1,1,IF(BA19>=$AX$1,0.5,0)) -> 0 | BC19: =BA19-BB19-BD19-BE19 -> 0 | BD19: =IF(AND(E19>$AV$1, D19<$AW$1),(MIN(E19,$AW$1)-MAX(D19,$AV$1))*24,0) -> 0 | BE19: =IF(E19>$AW$1,(E19-MAX(D19,$AW$1))*24,0) -> 0 | BF19: =IF(ISBLANK(G19),0,(H19-G19)*24) -> 0 | BG19: =IF(BF19>$AY$1,1,IF(BF19>=$AX$1,0.5,0)) -> 0 | BH19: =BF19-BG19-BI19-BJ19 -> 0 | BI19: =IF(AND(H19>$AV$1,G19<$AW$1),(MIN(H19,$AW$1)-MAX(G19,$AV$1))*24,0) -> 0 | BJ19: =IF(H19>$AW$1,(H19-MAX(G19,$AW$1))*24,0) -> 0 | BK19: =IF(ISBLANK(J19),0,(K19-J19)*24) -> 0 | BL19: =IF(BK19>$AY$1,1,IF(BK19>=$AX$1,0.5,0)) -> 0 | BM19: =BK19-BL19-BN19-BO19 -> 0 | BN19: =IF(AND(K19>$AV$1, J19<$AW$1),(MIN(K19,$AW$1)-MAX(J19,$AV$1))*24,0) -> 0 | BO19: =IF(K19>$AW$1,(K19-MAX(J19,$AW$1))*24,0) -> 0 | BP19: =IF(ISBLANK(M19),0,(N19-M19)*24) -> 0 | BQ19: =IF(BP19>$AY$1,1,IF(BP19>=$AX$1,0.5,0)) -> 0 | BR19: =BP19-BQ19-BS19-BT19 -> 0 | BS19: =IF(AND(N19>$AV$1, M19<$AW$1),(MIN(N19,$AW$1)-MAX(M19,$AV$1))*24,0) -> 0 | BT19: =IF(N19>$AW$1,(N19-MAX(M19,$AW$1))*24,0) -> 0 | BU19: =IF(ISBLANK(P19),0,(Q19-P19)*24) -> 0 | BV19: =IF(BU19>$AY$1,1,IF(BU19>=$AX$1,0.5,0)) -> 0 | BW19: =BU19-BV19-BX19-BY19 -> 0 | BX19: =IF(AND(Q19>$AV$1, P19<$AW$1),(MIN(Q19,$AW$1)-MAX(P19,$AV$1))*24,0) -> 0 | BY19: =IF(Q19>$AW$1,(Q19-MAX(P19,$AW$1))*24,0) -> 0 | BZ19: =IF(ISBLANK(S19),0,(T19-S19)*24) -> 0 | CA19: =IF(BZ19>$AY$1,1,IF(BZ19>=$AX$1,0.5,0)) -> 0 | CB19: =BZ19-CA19-CC19-CD19 -> 0 | CC19: =IF(AND(T19>$AV$1, S19<$AW$1),(MIN(T19,$AW$1)-MAX(S19,$AV$1))*24,0) -> 0 | CD19: =IF(T19>$AW$1,(T19-MAX(S19,$AW$1))*24,0) -> 0 | CE19: =IF(ISBLANK(V19),0,(W19-V19)*24) -> 0 | CF19: =IF(CE19>$AY$1,1,IF(CE19>=$AX$1,0.5,0)) -> 0 | CG19: =CE19-CF19-CH19-CI19 -> 0 | CH19: =IF(AND(W19>$AV$1, V19<$AW$1),(MIN(W19,$AW$1)-MAX(V19,$AV$1))*24,0) -> 0 | CI19: =IF(W19>$AW$1,(W19-MAX(V19,$AW$1))*24,0) -> 0 | CK19: =SUM(IF(F19>0,1,0),IF(I19>0,1,0),IF(L19>0,1,0),IF(O19>0,1,0),IF(R19>0,1,0),IF(U19>0,1,0),IF(X19>0,1,0)) -> 0
A20: =IF(ISNA(AZ20),"",AZ20) | F20: =BA20-BB20 -> 0 | I20: =BF20-BG20 -> 0 | L20: =BK20-BL20 -> 0 | O20: =BP20-BQ20 -> 0 | R20: =BU20-BV20 -> 0 | U20: =BZ20-CA20 -> 0 | X20: =CE20-CF20 -> 0 | AB20: =SUM(F20,I20,L20,O20,R20,U20,X20) -> 0 | AE20: =SUMIF($BC$1:$CI$1,AE$1,$BC20:$CI20)+AD20 -> 0 | AG20: =SUMIF($BC$1:$CI$1,AG$1,$BC20:$CI20)+AF20 -> 0 | AI20: =SUMIF($BC$1:$CI$1,AI$1,$BC20:$CI20)+AH20 -> 0 | AK20: =SUMIF($BC$1:$CI$1,AK$1,$BC20:$CI20)+AJ20 -> 0 | AM20: =SUMIF($BC$1:$CI$1,AM$1,$BC20:$CI20)+AL20 -> 0 | AO20: =SUMIF($BC$1:$CI$1,AO$1,$BC20:$CI20)+AN20 -> 0 | AP20: =CK20 -> 0 | AT20: =AE20+AG20+AI20+AK20+AM20+AO20+SUM(AQ20:AS20) -> 0 | AZ20: =VLOOKUP(C20,Employees!D:I,6,FALSE) -> #N/A | BA20: =IF(ISBLANK(D20),0,(E20-D20)*24) -> 0 | BB20: =IF(BA20>$AY$1,1,IF(BA20>=$AX$1,0.5,0)) -> 0 | BC20: =BA20-BB20-BD20-BE20 -> 0 | BD20: =IF(AND(E20>$AV$1, D20<$AW$1),(MIN(E20,$AW$1)-MAX(D20,$AV$1))*24,0) -> 0 | BE20: =IF(E20>$AW$1,(E20-MAX(D20,$AW$1))*24,0) -> 0 | BF20: =IF(ISBLANK(G20),0,(H20-G20)*24) -> 0 | BG20: =IF(BF20>$AY$1,1,IF(BF20>=$AX$1,0.5,0)) -> 0 | BH20: =BF20-BG20-BI20-BJ20 -> 0 | BI20: =IF(AND(H20>$AV$1,G20<$AW$1),(MIN(H20,$AW$1)-MAX(G20,$AV$1))*24,0) -> 0 | BJ20: =IF(H20>$AW$1,(H20-MAX(G20,$AW$1))*24,0) -> 0 | BK20: =IF(ISBLANK(J20),0,(K20-J20)*24) -> 0 | BL20: =IF(BK20>$AY$1,1,IF(BK20>=$AX$1,0.5,0)) -> 0 | BM20: =BK20-BL20-BN20-BO20 -> 0 | BN20: =IF(AND(K20>$AV$1, J20<$AW$1),(MIN(K20,$AW$1)-MAX(J20,$AV$1))*24,0) -> 0 | BO20: =IF(K20>$AW$1,(K20-MAX(J20,$AW$1))*24,0) -> 0 | BP20: =IF(ISBLANK(M20),0,(N20-M20)*24) -> 0 | BQ20: =IF(BP20>$AY$1,1,IF(BP20>=$AX$1,0.5,0)) -> 0 | BR20: =BP20-BQ20-BS20-BT20 -> 0 | BS20: =IF(AND(N20>$AV$1, M20<$AW$1),(MIN(N20,$AW$1)-MAX(M20,$AV$1))*24,0) -> 0 | BT20: =IF(N20>$AW$1,(N20-MAX(M20,$AW$1))*24,0) -> 0 | BU20: =IF(ISBLANK(P20),0,(Q20-P20)*24) -> 0 | BV20: =IF(BU20>$AY$1,1,IF(BU20>=$AX$1,0.5,0)) -> 0 | BW20: =BU20-BV20-BX20-BY20 -> 0 | BX20: =IF(AND(Q20>$AV$1, P20<$AW$1),(MIN(Q20,$AW$1)-MAX(P20,$AV$1))*24,0) -> 0 | BY20: =IF(Q20>$AW$1,(Q20-MAX(P20,$AW$1))*24,0) -> 0 | BZ20: =IF(ISBLANK(S20),0,(T20-S20)*24) -> 0 | CA20: =IF(BZ20>$AY$1,1,IF(BZ20>=$AX$1,0.5,0)) -> 0 | CB20: =BZ20-CA20-CC20-CD20 -> 0 | CC20: =IF(AND(T20>$AV$1, S20<$AW$1),(MIN(T20,$AW$1)-MAX(S20,$AV$1))*24,0) -> 0 | CD20: =IF(T20>$AW$1,(T20-MAX(S20,$AW$1))*24,0) -> 0 | CE20: =IF(ISBLANK(V20),0,(W20-V20)*24) -> 0 | CF20: =IF(CE20>$AY$1,1,IF(CE20>=$AX$1,0.5,0)) -> 0 | CG20: =CE20-CF20-CH20-CI20 -> 0 | CH20: =IF(AND(W20>$AV$1, V20<$AW$1),(MIN(W20,$AW$1)-MAX(V20,$AV$1))*24,0) -> 0 | CI20: =IF(W20>$AW$1,(W20-MAX(V20,$AW$1))*24,0) -> 0 | CK20: =SUM(IF(F20>0,1,0),IF(I20>0,1,0),IF(L20>0,1,0),IF(O20>0,1,0),IF(R20>0,1,0),IF(U20>0,1,0),IF(X20>0,1,0)) -> 0
... A100: =IF(ISNA(AZ100),"",AZ100) | F100: =BA100-BB100 -> 0 | I100: =BF100-BG100 -> 0 | L100: =BK100-BL100 -> 0 | O100: =BP100-BQ100 -> 0 | R100: =BU100-BV100 -> 0 | U100: =BZ100-CA100 -> 0 | X100: =CE100-CF100 -> 0 | AB100: =SUM(F100,I100,L100,O100,R100,U100,X100) -> 0 | AE100: =SUMIF($BC$1:$CI$1,AE$1,$BC100:$CI100)+AD100 -> 0 | AG100: =SUMIF($BC$1:$CI$1,AG$1,$BC100:$CI100)+AF100 -> 0 | AI100: =SUMIF($BC$1:$CI$1,AI$1,$BC100:$CI100)+AH100 -> 0 | AK100: =SUMIF($BC$1:$CI$1,AK$1,$BC100:$CI100)+AJ100 -> 0 | AM100: =SUMIF($BC$1:$CI$1,AM$1,$BC100:$CI100)+AL100 -> 0 | AO100: =SUMIF($BC$1:$CI$1,AO$1,$BC100:$CI100)+AN100 -> 0 | AP100: =CK100 -> 0 | AT100: =AE100+AG100+AI100+AK100+AM100+AO100+SUM(AQ100:AS100) -> 0 | AZ100: =VLOOKUP(C100,Employees!D:I,6,FALSE) -> #N/A | BA100: =IF(ISBLANK(D100),0,(E100-D100)*24) -> 0 | BB100: =IF(BA100>$AY$1,1,IF(BA100>=$AX$1,0.5,0)) -> 0 | BC100: =BA100-BB100-BD100-BE100 -> 0 | BD100: =IF(AND(E100>$AV$1, D100<$AW$1),(MIN(E100,$AW$1)-MAX(D100,$AV$1))*24,0) -> 0 | BE100: =IF(E100>$AW$1,(E100-MAX(D100,$AW$1))*24,0) -> 0 | BF100: =IF(ISBLANK(G100),0,(H100-G100)*24) -> 0 | BG100: =IF(BF100>$AY$1,1,IF(BF100>=$AX$1,0.5,0)) -> 0 | BH100: =BF100-BG100-BI100-BJ100 -> 0 | BI100: =IF(AND(H100>$AV$1,G100<$AW$1),(MIN(H100,$AW$1)-MAX(G100,$AV$1))*24,0) -> 0 | BJ100: =IF(H100>$AW$1,(H100-MAX(G100,$AW$1))*24,0) -> 0 | BK100: =IF(ISBLANK(J100),0,(K100-J100)*24) -> 0 | BL100: =IF(BK100>$AY$1,1,IF(BK100>=$AX$1,0.5,0)) -> 0 | BM100: =BK100-BL100-BN100-BO100 -> 0 | BN100: =IF(AND(K100>$AV$1, J100<$AW$1),(MIN(K100,$AW$1)-MAX(J100,$AV$1))*24,0) -> 0 | BO100: =IF(K100>$AW$1,(K100-MAX(J100,$AW$1))*24,0) -> 0 | BP100: =IF(ISBLANK(M100),0,(N100-M100)*24) -> 0 | BQ100: =IF(BP100>$AY$1,1,IF(BP100>=$AX$1,0.5,0)) -> 0 | BR100: =BP100-BQ100-BS100-BT100 -> 0 | BS100: =IF(AND(N100>$AV$1, M100<$AW$1),(MIN(N100,$AW$1)-MAX(M100,$AV$1))*24,0) -> 0 | BT100: =IF(N100>$AW$1,(N100-MAX(M100,$AW$1))*24,0) -> 0 | BU100: =IF(ISBLANK(P100),0,(Q100-P100)*24) -> 0 | BV100: =IF(BU100>$AY$1,1,IF(BU100>=$AX$1,0.5,0)) -> 0 | BW100: =BU100-BV100-BX100-BY100 -> 0 | BX100: =IF(AND(Q100>$AV$1, P100<$AW$1),(MIN(Q100,$AW$1)-MAX(P100,$AV$1))*24,0) -> 0 | BY100: =IF(Q100>$AW$1,(Q100-MAX(P100,$AW$1))*24,0) -> 0 | BZ100: =IF(ISBLANK(S100),0,(T100-S100)*24) -> 0 | CA100: =IF(BZ100>$AY$1,1,IF(BZ100>=$AX$1,0.5,0)) -> 0 | CB100: =BZ100-CA100-CC100-CD100 -> 0 | CC100: =IF(AND(T100>$AV$1, S100<$AW$1),(MIN(T100,$AW$1)-MAX(S100,$AV$1))*24,0) -> 0 | CD100: =IF(T100>$AW$1,(T100-MAX(S100,$AW$1))*24,0) -> 0 | CE100: =IF(ISBLANK(V100),0,(W100-V100)*24) -> 0 | CF100: =IF(CE100>$AY$1,1,IF(CE100>=$AX$1,0.5,0)) -> 0 | CG100: =CE100-CF100-CH100-CI100 -> 0 | CH100: =IF(AND(W100>$AV$1, V100<$AW$1),(MIN(W100,$AW$1)-MAX(V100,$AV$1))*24,0) -> 0 | CI100: =IF(W100>$AW$1,(W100-MAX(V100,$AW$1))*24,0) -> 0 | CK100: =SUM(IF(F100>0,1,0),IF(I100>0,1,0),IF(L100>0,1,0),IF(O100>0,1,0),IF(R100>0,1,0),IF(U100>0,1,0),IF(X100>0,1,0)) -> 0

Sheet Week 2 Roster
A1: Employee ID | B1: Store | C1: Preferred Name | D1: ='Week 1 Roster'!V1+1 -> 46048 | E1: =TEXT(D1,"dddd") -> Monday | F1: =IF(ISNUMBER(MATCH(D1,'Public Holidays'!$A:$A,0)),"Pub",IF(WEEKDAY(D1,2)=7,"Sun",IF(WEEKDAY(D1,2)=6,"Sat","Ord"))) -> Pub | G1: =D1+1 -> 46049 | H1: =TEXT(G1,"dddd") -> Tuesday | I1: =IF(ISNUMBER(MATCH(G1,'Public Holidays'!$A:$A,0)),"Pub",IF(WEEKDAY(G1,2)=7,"Sun",IF(WEEKDAY(G1,2)=6,"Sat","Ord"))) -> Ord | J1: =G1+1 -> 46050 | K1: =TEXT(J1,"dddd") -> Wednesday | L1: =IF(ISNUMBER(MATCH(J1,'Public Holidays'!$A:$A,0)),"Pub",IF(WEEKDAY(J1,2)=7,"Sun",IF(WEEKDAY(J1,2)=6,"Sat","Ord"))) -> Ord | M1: =J1+1 -> 46051 | N1: =TEXT(M1,"dddd") -> Thursday | O1: =IF(ISNUMBER(MATCH(M1,'Public Holidays'!$A:$A,0)),"Pub",IF(WEEKDAY(M1,2)=7,"Sun",IF(WEEKDAY(M1,2)=6,"Sat","Ord"))) -> Ord | P1: =M1+1 -> 46052 | Q1: =TEXT(P1,"dddd") -> Friday | R1: =IF(ISNUMBER(MATCH(P1,'Public Holidays'!$A:$A,0)),"Pub",IF(WEEKDAY(P1,2)=7,"Sun",IF(WEEKDAY(P1,2)=6,"Sat","Ord"))) -> Ord | S1: =P1+1 -> 46053 | T1: =TEXT(S1,"dddd") -> Saturday | U1: =IF(ISNUMBER(MATCH(S1,'Public Holidays'!$A:$A,0)),"Pub",IF(WEEKDAY(S1,2)=7,"Sun",IF(WEEKDAY(S1,2)=6,"Sat","Ord"))) -> Sat | V1: =S1+1 -> 46054 | W1: =TEXT(V1,"dddd") -> Sunday | X1: =IF(ISNUMBER(MATCH(V1,'Public Holidays'!$A:$A,0)),"Pub",IF(WEEKDAY(V1,2)=7,"Sun",IF(WEEKDAY(V1,2)=6,"Sat","Ord"))) -> Sun | Y1: =V1+1 -> 46055 | Z1: =TEXT(Y1,"dddd") -> Monday | AA1: =IF(ISNUMBER(MATCH(Y1,'Public Holidays'!$A:$A,0)),"Pub",IF(WEEKDAY(Y1,2)=7,"Sun",IF(WEEKDAY(Y1,2)=6,"Sat","Ord"))) -> Ord | AB1: Rostered Total | AD1: Add | AE1: Ord | AF1: Add | AG1: Sat | AH1: Add | AI1: Sun | AJ1: Add | AK1: Pub | AL1: Add | AM1: Eve 1 | AN1: Add | AO1: Eve 2 | AP1: No. of Shifts | AQ1: Personal Leave | AR1: Annual Leave | AS1: Unpaid Leave | AT1: Adjusted Total | AU1: Comment | AV1: 0.91666667 | AW1: 1 | AX1: 5.5 | AY1: 9 | AZ1: Employee ID | BA1: Dr1 | BB1: Br1 | BC1: =F1 -> Pub | BD1: =IF(BC1="Ord","Eve 1", BC1) -> Pub | BE1: =IF(BH1="Ord","Eve 2",BH1) -> Eve 2 | BF1: Dr2 | BG1: Br2 | BH1: =I1 -> Ord | BI1: =IF(BH1="Ord","Eve 1", BH1) -> Eve 1 | BJ1: =IF(BM1="Ord","Eve 2",BM1) -> Eve 2 | BK1: Dr3 | BL1: Br3 | BM1: =L1 -> Ord | BN1: =IF(BM1="Ord","Eve 1", BM1) -> Eve 1 | BO1: =IF(BR1="Ord","Eve 2",BR1) -> Eve 2 | BP1: Dr4 | BQ1: Br4 | BR1: =O1 -> Ord | BS1: =IF(BR1="Ord","Eve 1", BR1) -> Eve 1 | BT1: =IF(BW1="Ord","Eve 2",BW1) -> Eve 2 | BU1: Dr5 | BV1: Br5 | BW1: =R1 -> Ord | BX1: =IF(BW1="Ord","Eve 1", BW1) -> Eve 1 | BY1: =IF(CB1="Ord","Eve 2",CB1) -> Sat | BZ1: Dr6 | CA1: Br6 | CB1: =U1 -> Sat | CC1: =IF(CB1="Ord","Eve 1", CB1) -> Sat | CD1: =IF(CG1="Ord","Eve 2",CG1) -> Sun | CE1: Dr7 | CF1: Br7 | CG1: =X1 -> Sun | CH1: =IF(CG1="Ord","Eve 1", CG1) -> Sun | CI1: =IF(CJ1="Ord","Eve 2",CJ1) -> Eve 2 | CJ1: =AA1 -> Ord | CK1: No. of Shifts
A2: =IF(ISNA(AZ2),"",AZ2) -> 10306 | B2: The Star | C2: Annie Pham | D2: 0.79166667 | E2: 0.95902778 | F2: =BA2-BB2 -> 4.0166667 | I2: =BF2-BG2 -> 0 | J2: 0.75 | K2: 0.95902778 | L2: =BK2-BL2 -> 5.0166667 | O2: =BP2-BQ2 -> 0 | P2: 0.76805556 | Q2: 0.96597222 | R2: =BU2-BV2 -> 4.75 | S2: 0.42222222 | T2: 0.85416667 | U2: =BZ2-CA2 -> 9.3666667 | X2: =CE2-CF2 -> 0 | AB2: =SUM(F2,I2,L2,O2,R2,U2,X2) -> 23.15 | AD2: 1 | AE2: =SUMIF($BC$1:$CI$1,AE$1,$BC2:$CI2)+AD2 -> 8.5666667 | AG2: =SUMIF($BC$1:$CI$1,AG$1,$BC2:$CI2)+AF2 -> 9.3666667 | AI2: =SUMIF($BC$1:$CI$1,AI$1,$BC2:$CI2)+AH2 -> 0 | AK2: =SUMIF($BC$1:$CI$1,AK$1,$BC2:$CI2)+AJ2 -> 4.0166667 | AM2: =SUMIF($BC$1:$CI$1,AM$1,$BC2:$CI2)+AL2 -> 2.2 | AO2: =SUMIF($BC$1:$CI$1,AO$1,$BC2:$CI2)+AN2 -> 0 | AP2: =CK2 -> 4 | AT2: =AE2+AG2+AI2+AK2+AM2+AO2+SUM(AQ2:AS2) -> 24.15 | AU2: + 1h roster making | AZ2: =VLOOKUP(C2,Employees!D:I,6,FALSE) -> 10306 | BA2: =IF(ISBLANK(D2),0,(E2-D2)*24) -> 4.0166667 | BB2: =IF(BA2>$AY$1,1,IF(BA2>=$AX$1,0.5,0)) -> 0 | BC2: =BA2-BB2-BD2-BE2 -> 3 | BD2: =IF(AND(E2>$AV$1, D2<$AW$1),(MIN(E2,$AW$1)-MAX(D2,$AV$1))*24,0) -> 1.0166667 | BE2: =IF(E2>$AW$1,(E2-MAX(D2,$AW$1))*24,0) -> 0 | BF2: =IF(ISBLANK(G2),0,(H2-G2)*24) -> 0 | BG2: =IF(BF2>$AY$1,1,IF(BF2>=$AX$1,0.5,0)) -> 0 | BH2: =BF2-BG2-BI2-BJ2 -> 0 | BI2: =IF(AND(H2>$AV$1,G2<$AW$1),(MIN(H2,$AW$1)-MAX(G2,$AV$1))*24,0) -> 0 | BJ2: =IF(H2>$AW$1,(H2-MAX(G2,$AW$1))*24,0) -> 0 | BK2: =IF(ISBLANK(J2),0,(K2-J2)*24) -> 5.0166667 | BL2: =IF(BK2>$AY$1,1,IF(BK2>=$AX$1,0.5,0)) -> 0 | BM2: =BK2-BL2-BN2-BO2 -> 4 | BN2: =IF(AND(K2>$AV$1, J2<$AW$1),(MIN(K2,$AW$1)-MAX(J2,$AV$1))*24,0) -> 1.0166667 | BO2: =IF(K2>$AW$1,(K2-MAX(J2,$AW$1))*24,0) -> 0 | BP2: =IF(ISBLANK(M2),0,(N2-M2)*24) -> 0 | BQ2: =IF(BP2>$AY$1,1,IF(BP2>=$AX$1,0.5,0)) -> 0 | BR2: =BP2-BQ2-BS2-BT2 -> 0 | BS2: =IF(AND(N2>$AV$1, M2<$AW$1),(MIN(N2,$AW$1)-MAX(M2,$AV$1))*24,0) -> 0 | BT2: =IF(N2>$AW$1,(N2-MAX(M2,$AW$1))*24,0) -> 0 | BU2: =IF(ISBLANK(P2),0,(Q2-P2)*24) -> 4.75 | BV2: =IF(BU2>$AY$1,1,IF(BU2>=$AX$1,0.5,0)) -> 0 | BW2: =BU2-BV2-BX2-BY2 -> 3.5666667 | BX2: =IF(AND(Q2>$AV$1, P2<$AW$1),(MIN(Q2,$AW$1)-MAX(P2,$AV$1))*24,0) -> 1.1833333 | BY2: =IF(Q2>$AW$1,(Q2-MAX(P2,$AW$1))*24,0) -> 0 | BZ2: =IF(ISBLANK(S2),0,(T2-S2)*24) -> 10.366667 | CA2: =IF(BZ2>$AY$1,1,IF(BZ2>=$AX$1,0.5,0)) -> 1 | CB2: =BZ2-CA2-CC2-CD2 -> 9.3666667 | CC2: =IF(AND(T2>$AV$1, S2<$AW$1),(MIN(T2,$AW$1)-MAX(S2,$AV$1))*24,0) -> 0 | CD2: =IF(T2>$AW$1,(T2-MAX(S2,$AW$1))*24,0) -> 0 | CE2: =IF(ISBLANK(V2),0,(W2-V2)*24) -> 0 | CF2: =IF(CE2>$AY$1,1,IF(CE2>=$AX$1,0.5,0)) -> 0 | CG2: =CE2-CF2-CH2-CI2 -> 0 | CH2: =IF(AND(W2>$AV$1, V2<$AW$1),(MIN(W2,$AW$1)-MAX(V2,$AV$1))*24,0) -> 0 | CI2: =IF(W2>$AW$1,(W2-MAX(V2,$AW$1))*24,0) -> 0 | CK2: =SUM(IF(F2>0,1,0),IF(I2>0,1,0),IF(L2>0,1,0),IF(O2>0,1,0),IF(R2>0,1,0),IF(U2>0,1,0),IF(X2>0,1,0)) -> 4
A3: =IF(ISNA(AZ3),"",AZ3) -> 10386 | B3: The Star | C3: Nia Handoko | D3: 0.41666667 | E3: 0.60555556 | F3: =BA3-BB3 -> 4.5333333 | I3: =BF3-BG3 -> 0 | J3: 0.41666667 | K3: 0.75138889 | L3: =BK3-BL3 -> 7.5333333 | M3: 0.41666667 | N3: 0.75277778 | O3: =BP3-BQ3 -> 7.5666667 | P3: 0.41666667 | Q3: 0.75138889 | R3: =BU3-BV3 -> 7.5333333 | S3: 0.70833333 | T3: 0.9625 | U3: =BZ3-CA3 -> 5.6 | V3: 0.59652778 | W3: 0.96111111 | X3: =CE3-CF3 -> 8.25 | AB3: =SUM(F3,I3,L3,O3,R3,U3,X3) -> 41.016667 | AD3: =0.5+0.5+0.5 -> 1.5 | AE3: =SUMIF($BC$1:$CI$1,AE$1,$BC3:$CI3)+AD3 -> 24.133333 | AF3: 0.5 | AG3: =SUMIF($BC$1:$CI$1,AG$1,$BC3:$CI3)+AF3 -> 6.1 | AI3: =SUMIF($BC$1:$CI$1,AI$1,$BC3:$CI3)+AH3 -> 8.25 | AK3: =SUMIF($BC$1:$CI$1,AK$1,$BC3:$CI3)+AJ3 -> 4.5333333 | AM3: =SUMIF($BC$1:$CI$1,AM$1,$BC3:$CI3)+AL3 -> 0 | AO3: =SUMIF($BC$1:$CI$1,AO$1,$BC3:$CI3)+AN3 -> 0 | AP3: =CK3 -> 6 | AT3: =AE3+AG3+AI3+AK3+AM3+AO3+SUM(AQ3:AS3) -> 43.016667 | AU3: + 0.5h break on Wed 1/28 + 0.5h break on Thu 1/29 + 0.5h break on Fri 1/30 + 0.5h break on Sat 1/31 | AZ3: =VLOOKUP(C3,Employees!D:I,6,FALSE) -> 10386 | BA3: =IF(ISBLANK(D3),0,(E3-D3)*24) -> 4.5333333 | BB3: =IF(BA3>$AY$1,1,IF(BA3>=$AX$1,0.5,0)) -> 0 | BC3: =BA3-BB3-BD3-BE3 -> 4.5333333 | BD3: =IF(AND(E3>$AV$1, D3<$AW$1),(MIN(E3,$AW$1)-MAX(D3,$AV$1))*24,0) -> 0 | BE3: =IF(E3>$AW$1,(E3-MAX(D3,$AW$1))*24,0) -> 0 | BF3: =IF(ISBLANK(G3),0,(H3-G3)*24) -> 0 | BG3: =IF(BF3>$AY$1,1,IF(BF3>=$AX$1,0.5,0)) -> 0 | BH3: =BF3-BG3-BI3-BJ3 -> 0 | BI3: =IF(AND(H3>$AV$1,G3<$AW$1),(MIN(H3,$AW$1)-MAX(G3,$AV$1))*24,0) -> 0 | BJ3: =IF(H3>$AW$1,(H3-MAX(G3,$AW$1))*24,0) -> 0 | BK3: =IF(ISBLANK(J3),0,(K3-J3)*24) -> 8.0333333 | BL3: =IF(BK3>$AY$1,1,IF(BK3>=$AX$1,0.5,0)) -> 0.5 | BM3: =BK3-BL3-BN3-BO3 -> 7.5333333 | BN3: =IF(AND(K3>$AV$1, J3<$AW$1),(MIN(K3,$AW$1)-MAX(J3,$AV$1))*24,0) -> 0 | BO3: =IF(K3>$AW$1,(K3-MAX(J3,$AW$1))*24,0) -> 0 | BP3: =IF(ISBLANK(M3),0,(N3-M3)*24) -> 8.0666667 | BQ3: =IF(BP3>$AY$1,1,IF(BP3>=$AX$1,0.5,0)) -> 0.5 | BR3: =BP3-BQ3-BS3-BT3 -> 7.5666667 | BS3: =IF(AND(N3>$AV$1, M3<$AW$1),(MIN(N3,$AW$1)-MAX(M3,$AV$1))*24,0) -> 0 | BT3: =IF(N3>$AW$1,(N3-MAX(M3,$AW$1))*24,0) -> 0 | BU3: =IF(ISBLANK(P3),0,(Q3-P3)*24) -> 8.0333333 | BV3: =IF(BU3>$AY$1,1,IF(BU3>=$AX$1,0.5,0)) -> 0.5 | BW3: =BU3-BV3-BX3-BY3 -> 7.5333333 | BX3: =IF(AND(Q3>$AV$1, P3<$AW$1),(MIN(Q3,$AW$1)-MAX(P3,$AV$1))*24,0) -> 0 | BY3: =IF(Q3>$AW$1,(Q3-MAX(P3,$AW$1))*24,0) -> 0 | BZ3: =IF(ISBLANK(S3),0,(T3-S3)*24) -> 6.1 | CA3: =IF(BZ3>$AY$1,1,IF(BZ3>=$AX$1,0.5,0)) -> 0.5 | CB3: =BZ3-CA3-CC3-CD3 -> 4.5 | CC3: =IF(AND(T3>$AV$1, S3<$AW$1),(MIN(T3,$AW$1)-MAX(S3,$AV$1))*24,0) -> 1.1 | CD3: =IF(T3>$AW$1,(T3-MAX(S3,$AW$1))*24,0) -> 0 | CE3: =IF(ISBLANK(V3),0,(W3-V3)*24) -> 8.75 | CF3: =IF(CE3>$AY$1,1,IF(CE3>=$AX$1,0.5,0)) -> 0.5 | CG3: =CE3-CF3-CH3-CI3 -> 7.1833333 | CH3: =IF(AND(W3>$AV$1, V3<$AW$1),(MIN(W3,$AW$1)-MAX(V3,$AV$1))*24,0) -> 1.0666667 | CI3: =IF(W3>$AW$1,(W3-MAX(V3,$AW$1))*24,0) -> 0 | CK3: =SUM(IF(F3>0,1,0),IF(I3>0,1,0),IF(L3>0,1,0),IF(O3>0,1,0),IF(R3>0,1,0),IF(U3>0,1,0),IF(X3>0,1,0)) -> 6
A4: =IF(ISNA(AZ4),"",AZ4) -> 10376 | B4: The Star | C4: Harry Le | D4: 0.60555556 | E4: 0.79236111 | F4: =BA4-BB4 -> 4.4833333 | G4: 0.45833333 | H4: 0.75138889 | I4: =BF4-BG4 -> 6.5333333 | L4: =BK4-BL4 -> 0 | O4: =BP4-BQ4 -> 0 | R4: =BU4-BV4 -> 0 | U4: =BZ4-CA4 -> 0 | X4: =CE4-CF4 -> 0 | AB4: =SUM(F4,I4,L4,O4,R4,U4,X4) -> 11.016667 | AD4: 0.5 | AE4: =SUMIF($BC$1:$CI$1,AE$1,$BC4:$CI4)+AD4 -> 7.0333333 | AG4: =SUMIF($BC$1:$CI$1,AG$1,$BC4:$CI4)+AF4 -> 0 | AI4: =SUMIF($BC$1:$CI$1,AI$1,$BC4:$CI4)+AH4 -> 0 | AK4: =SUMIF($BC$1:$CI$1,AK$1,$BC4:$CI4)+AJ4 -> 4.4833333 | AM4: =SUMIF($BC$1:$CI$1,AM$1,$BC4:$CI4)+AL4 -> 0 | AO4: =SUMIF($BC$1:$CI$1,AO$1,$BC4:$CI4)+AN4 -> 0 | AP4: =CK4 -> 2 | AT4: =AE4+AG4+AI4+AK4+AM4+AO4+SUM(AQ4:AS4) -> 11.516667 | AU4: + 0.5h break on Tue 1/27 | AZ4: =VLOOKUP(C4,Employees!D:I,6,FALSE) -> 10376 | BA4: =IF(ISBLANK(D4),0,(E4-D4)*24) -> 4.4833333 | BB4: =IF(BA4>$AY$1,1,IF(BA4>=$AX$1,0.5,0)) -> 0 | BC4: =BA4-BB4-BD4-BE4 -> 4.4833333 | BD4: =IF(AND(E4>$AV$1, D4<$AW$1),(MIN(E4,$AW$1)-MAX(D4,$AV$1))*24,0) -> 0 | BE4: =IF(E4>$AW$1,(E4-MAX(D4,$AW$1))*24,0) -> 0 | BF4: =IF(ISBLANK(G4),0,(H4-G4)*24) -> 7.0333333 | BG4: =IF(BF4>$AY$1,1,IF(BF4>=$AX$1,0.5,0)) -> 0.5 | BH4: =BF4-BG4-BI4-BJ4 -> 6.5333333 | BI4: =IF(AND(H4>$AV$1,G4<$AW$1),(MIN(H4,$AW$1)-MAX(G4,$AV$1))*24,0) -> 0 | BJ4: =IF(H4>$AW$1,(H4-MAX(G4,$AW$1))*24,0) -> 0 | BK4: =IF(ISBLANK(J4),0,(K4-J4)*24) -> 0 | BL4: =IF(BK4>$AY$1,1,IF(BK4>=$AX$1,0.5,0)) -> 0 | BM4: =BK4-BL4-BN4-BO4 -> 0 | BN4: =IF(AND(K4>$AV$1, J4<$AW$1),(MIN(K4,$AW$1)-MAX(J4,$AV$1))*24,0) -> 0 | BO4: =IF(K4>$AW$1,(K4-MAX(J4,$AW$1))*24,0) -> 0 | BP4: =IF(ISBLANK(M4),0,(N4-M4)*24) -> 0 | BQ4: =IF(BP4>$AY$1,1,IF(BP4>=$AX$1,0.5,0)) -> 0 | BR4: =BP4-BQ4-BS4-BT4 -> 0 | BS4: =IF(AND(N4>$AV$1, M4<$AW$1),(MIN(N4,$AW$1)-MAX(M4,$AV$1))*24,0) -> 0 | BT4: =IF(N4>$AW$1,(N4-MAX(M4,$AW$1))*24,0) -> 0 | BU4: =IF(ISBLANK(P4),0,(Q4-P4)*24) -> 0 | BV4: =IF(BU4>$AY$1,1,IF(BU4>=$AX$1,0.5,0)) -> 0 | BW4: =BU4-BV4-BX4-BY4 -> 0 | BX4: =IF(AND(Q4>$AV$1, P4<$AW$1),(MIN(Q4,$AW$1)-MAX(P4,$AV$1))*24,0) -> 0 | BY4: =IF(Q4>$AW$1,(Q4-MAX(P4,$AW$1))*24,0) -> 0 | BZ4: =IF(ISBLANK(S4),0,(T4-S4)*24) -> 0 | CA4: =IF(BZ4>$AY$1,1,IF(BZ4>=$AX$1,0.5,0)) -> 0 | CB4: =BZ4-CA4-CC4-CD4 -> 0 | CC4: =IF(AND(T4>$AV$1, S4<$AW$1),(MIN(T4,$AW$1)-MAX(S4,$AV$1))*24,0) -> 0 | CD4: =IF(T4>$AW$1,(T4-MAX(S4,$AW$1))*24,0) -> 0 | CE4: =IF(ISBLANK(V4),0,(W4-V4)*24) -> 0 | CF4: =IF(CE4>$AY$1,1,IF(CE4>=$AX$1,0.5,0)) -> 0 | CG4: =CE4-CF4-CH4-CI4 -> 0 | CH4: =IF(AND(W4>$AV$1, V4<$AW$1),(MIN(W4,$AW$1)-MAX(V4,$AV$1))*24,0) -> 0 | CI4: =IF(W4>$AW$1,(W4-MAX(V4,$AW$1))*24,0) -> 0 | CK4: =SUM(IF(F4>0,1,0),IF(I4>0,1,0),IF(L4>0,1,0),IF(O4>0,1,0),IF(R4>0,1,0),IF(U4>0,1,0),IF(X4>0,1,0)) -> 2
A5: =IF(ISNA(AZ5),"",AZ5) -> 210432 | B5: The Star | C5: Ashley Hmue | F5: =BA5-BB5 -> 0 | G5: 0.75972222 | H5: 0.96180556 | I5: =BF5-BG5 -> 4.85 | L5: =BK5-BL5 -> 0 | M5: 0.75277778 | N5: 0.97152778 | O5: =BP5-BQ5 -> 5.25 | R5: =BU5-BV5 -> 0 | U5: =BZ5-CA5 -> 0 | V5: 0.425 | W5: 0.79305556 | X5: =CE5-CF5 -> 8.3333333 | AB5: =SUM(F5,I5,L5,O5,R5,U5,X5) -> 18.433333 | AE5: =SUMIF($BC$1:$CI$1,AE$1,$BC5:$CI5)+AD5 -> 7.7 | AG5: =SUMIF($BC$1:$CI$1,AG$1,$BC5:$CI5)+AF5 -> 0 | AI5: =SUMIF($BC$1:$CI$1,AI$1,$BC5:$CI5)+AH5 -> 8.3333333 | AK5: =SUMIF($BC$1:$CI$1,AK$1,$BC5:$CI5)+AJ5 -> 0 | AM5: =SUMIF($BC$1:$CI$1,AM$1,$BC5:$CI5)+AL5 -> 2.4 | AO5: =SUMIF($BC$1:$CI$1,AO$1,$BC5:$CI5)+AN5 -> 0 | AP5: =CK5 -> 3 | AT5: =AE5+AG5+AI5+AK5+AM5+AO5+SUM(AQ5:AS5) -> 18.433333 | AZ5: =VLOOKUP(C5,Employees!D:I,6,FALSE) -> 210432 | BA5: =IF(ISBLANK(D5),0,(E5-D5)*24) -> 0 | BB5: =IF(BA5>$AY$1,1,IF(BA5>=$AX$1,0.5,0)) -> 0 | BC5: =BA5-BB5-BD5-BE5 -> 0 | BD5: =IF(AND(E5>$AV$1, D5<$AW$1),(MIN(E5,$AW$1)-MAX(D5,$AV$1))*24,0) -> 0 | BE5: =IF(E5>$AW$1,(E5-MAX(D5,$AW$1))*24,0) -> 0 | BF5: =IF(ISBLANK(G5),0,(H5-G5)*24) -> 4.85 | BG5: =IF(BF5>$AY$1,1,IF(BF5>=$AX$1,0.5,0)) -> 0 | BH5: =BF5-BG5-BI5-BJ5 -> 3.7666667 | BI5: =IF(AND(H5>$AV$1,G5<$AW$1),(MIN(H5,$AW$1)-MAX(G5,$AV$1))*24,0) -> 1.0833333 | BJ5: =IF(H5>$AW$1,(H5-MAX(G5,$AW$1))*24,0) -> 0 | BK5: =IF(ISBLANK(J5),0,(K5-J5)*24) -> 0 | BL5: =IF(BK5>$AY$1,1,IF(BK5>=$AX$1,0.5,0)) -> 0 | BM5: =BK5-BL5-BN5-BO5 -> 0 | BN5: =IF(AND(K5>$AV$1, J5<$AW$1),(MIN(K5,$AW$1)-MAX(J5,$AV$1))*24,0) -> 0 | BO5: =IF(K5>$AW$1,(K5-MAX(J5,$AW$1))*24,0) -> 0 | BP5: =IF(ISBLANK(M5),0,(N5-M5)*24) -> 5.25 | BQ5: =IF(BP5>$AY$1,1,IF(BP5>=$AX$1,0.5,0)) -> 0 | BR5: =BP5-BQ5-BS5-BT5 -> 3.9333333 | BS5: =IF(AND(N5>$AV$1, M5<$AW$1),(MIN(N5,$AW$1)-MAX(M5,$AV$1))*24,0) -> 1.3166667 | BT5: =IF(N5>$AW$1,(N5-MAX(M5,$AW$1))*24,0) -> 0 | BU5: =IF(ISBLANK(P5),0,(Q5-P5)*24) -> 0 | BV5: =IF(BU5>$AY$1,1,IF(BU5>=$AX$1,0.5,0)) -> 0 | BW5: =BU5-BV5-BX5-BY5 -> 0 | BX5: =IF(AND(Q5>$AV$1, P5<$AW$1),(MIN(Q5,$AW$1)-MAX(P5,$AV$1))*24,0) -> 0 | BY5: =IF(Q5>$AW$1,(Q5-MAX(P5,$AW$1))*24,0) -> 0 | BZ5: =IF(ISBLANK(S5),0,(T5-S5)*24) -> 0 | CA5: =IF(BZ5>$AY$1,1,IF(BZ5>=$AX$1,0.5,0)) -> 0 | CB5: =BZ5-CA5-CC5-CD5 -> 0 | CC5: =IF(AND(T5>$AV$1, S5<$AW$1),(MIN(T5,$AW$1)-MAX(S5,$AV$1))*24,0) -> 0 | CD5: =IF(T5>$AW$1,(T5-MAX(S5,$AW$1))*24,0) -> 0 | CE5: =IF(ISBLANK(V5),0,(W5-V5)*24) -> 8.8333333 | CF5: =IF(CE5>$AY$1,1,IF(CE5>=$AX$1,0.5,0)) -> 0.5 | CG5: =CE5-CF5-CH5-CI5 -> 8.3333333 | CH5: =IF(AND(W5>$AV$1, V5<$AW$1),(MIN(W5,$AW$1)-MAX(V5,$AV$1))*24,0) -> 0 | CI5: =IF(W5>$AW$1,(W5-MAX(V5,$AW$1))*24,0) -> 0 | CK5: =SUM(IF(F5>0,1,0),IF(I5>0,1,0),IF(L5>0,1,0),IF(O5>0,1,0),IF(R5>0,1,0),IF(U5>0,1,0),IF(X5>0,1,0)) -> 3
A6: =IF(ISNA(AZ6),"",AZ6) -> 210553 | B6: The Star | C6: Yunie Kang | F6: =BA6-BB6 -> 0 | G6: 0.41666667 | H6: 0.62569444 | I6: =BF6-BG6 -> 5.0166667 | L6: =BK6-BL6 -> 0 | O6: =BP6-BQ6 -> 0 | P6: 0.75 | Q6: 0.96666667 | R6: =BU6-BV6 -> 5.2 | U6: =BZ6-CA6 -> 0 | X6: =CE6-CF6 -> 0 | AB6: =SUM(F6,I6,L6,O6,R6,U6,X6) -> 10.216667 | AE6: =SUMIF($BC$1:$CI$1,AE$1,$BC6:$CI6)+AD6 -> 9.0166667 | AG6: =SUMIF($BC$1:$CI$1,AG$1,$BC6:$CI6)+AF6 -> 0 | AI6: =SUMIF($BC$1:$CI$1,AI$1,$BC6:$CI6)+AH6 -> 0 | AK6: =SUMIF($BC$1:$CI$1,AK$1,$BC6:$CI6)+AJ6 -> 0 | AM6: =SUMIF($BC$1:$CI$1,AM$1,$BC6:$CI6)+AL6 -> 1.2 | AO6: =SUMIF($BC$1:$CI$1,AO$1,$BC6:$CI6)+AN6 -> 0 | AP6: =CK6 -> 2 | AT6: =AE6+AG6+AI6+AK6+AM6+AO6+SUM(AQ6:AS6) -> 10.216667 | AZ6: =VLOOKUP(C6,Employees!D:I,6,FALSE) -> 210553 | BA6: =IF(ISBLANK(D6),0,(E6-D6)*24) -> 0 | BB6: =IF(BA6>$AY$1,1,IF(BA6>=$AX$1,0.5,0)) -> 0 | BC6: =BA6-BB6-BD6-BE6 -> 0 | BD6: =IF(AND(E6>$AV$1, D6<$AW$1),(MIN(E6,$AW$1)-MAX(D6,$AV$1))*24,0) -> 0 | BE6: =IF(E6>$AW$1,(E6-MAX(D6,$AW$1))*24,0) -> 0 | BF6: =IF(ISBLANK(G6),0,(H6-G6)*24) -> 5.0166667 | BG6: =IF(BF6>$AY$1,1,IF(BF6>=$AX$1,0.5,0)) -> 0 | BH6: =BF6-BG6-BI6-BJ6 -> 5.0166667 | BI6: =IF(AND(H6>$AV$1,G6<$AW$1),(MIN(H6,$AW$1)-MAX(G6,$AV$1))*24,0) -> 0 | BJ6: =IF(H6>$AW$1,(H6-MAX(G6,$AW$1))*24,0) -> 0 | BK6: =IF(ISBLANK(J6),0,(K6-J6)*24) -> 0 | BL6: =IF(BK6>$AY$1,1,IF(BK6>=$AX$1,0.5,0)) -> 0 | BM6: =BK6-BL6-BN6-BO6 -> 0 | BN6: =IF(AND(K6>$AV$1, J6<$AW$1),(MIN(K6,$AW$1)-MAX(J6,$AV$1))*24,0) -> 0 | BO6: =IF(K6>$AW$1,(K6-MAX(J6,$AW$1))*24,0) -> 0 | BP6: =IF(ISBLANK(M6),0,(N6-M6)*24) -> 0 | BQ6: =IF(BP6>$AY$1,1,IF(BP6>=$AX$1,0.5,0)) -> 0 | BR6: =BP6-BQ6-BS6-BT6 -> 0 | BS6: =IF(AND(N6>$AV$1, M6<$AW$1),(MIN(N6,$AW$1)-MAX(M6,$AV$1))*24,0) -> 0 | BT6: =IF(N6>$AW$1,(N6-MAX(M6,$AW$1))*24,0) -> 0 | BU6: =IF(ISBLANK(P6),0,(Q6-P6)*24) -> 5.2 | BV6: =IF(BU6>$AY$1,1,IF(BU6>=$AX$1,0.5,0)) -> 0 | BW6: =BU6-BV6-BX6-BY6 -> 4 | BX6: =IF(AND(Q6>$AV$1, P6<$AW$1),(MIN(Q6,$AW$1)-MAX(P6,$AV$1))*24,0) -> 1.2 | BY6: =IF(Q6>$AW$1,(Q6-MAX(P6,$AW$1))*24,0) -> 0 | BZ6: =IF(ISBLANK(S6),0,(T6-S6)*24) -> 0 | CA6: =IF(BZ6>$AY$1,1,IF(BZ6>=$AX$1,0.5,0)) -> 0 | CB6: =BZ6-CA6-CC6-CD6 -> 0 | CC6: =IF(AND(T6>$AV$1, S6<$AW$1),(MIN(T6,$AW$1)-MAX(S6,$AV$1))*24,0) -> 0 | CD6: =IF(T6>$AW$1,(T6-MAX(S6,$AW$1))*24,0) -> 0 | CE6: =IF(ISBLANK(V6),0,(W6-V6)*24) -> 0 | CF6: =IF(CE6>$AY$1,1,IF(CE6>=$AX$1,0.5,0)) -> 0 | CG6: =CE6-CF6-CH6-CI6 -> 0 | CH6: =IF(AND(W6>$AV$1, V6<$AW$1),(MIN(W6,$AW$1)-MAX(V6,$AV$1))*24,0) -> 0 | CI6: =IF(W6>$AW$1,(W6-MAX(V6,$AW$1))*24,0) -> 0 | CK6: =SUM(IF(F6>0,1,0),IF(I6>0,1,0),IF(L6>0,1,0),IF(O6>0,1,0),IF(R6>0,1,0),IF(U6>0,1,0),IF(X6>0,1,0)) -> 2
A7: =IF(ISNA(AZ7),"",AZ7) | F7: =BA7-BB7 -> 0 | I7: =BF7-BG7 -> 0 | L7: =BK7-BL7 -> 0 | O7: =BP7-BQ7 -> 0 | R7: =BU7-BV7 -> 0 | U7: =BZ7-CA7 -> 0 | X7: =CE7-CF7 -> 0 | AB7: =SUM(F7,I7,L7,O7,R7,U7,X7) -> 0 | AE7: =SUMIF($BC$1:$CI$1,AE$1,$BC7:$CI7)+AD7 -> 0 | AG7: =SUMIF($BC$1:$CI$1,AG$1,$BC7:$CI7)+AF7 -> 0 | AI7: =SUMIF($BC$1:$CI$1,AI$1,$BC7:$CI7)+AH7 -> 0 | AK7: =SUMIF($BC$1:$CI$1,AK$1,$BC7:$CI7)+AJ7 -> 0 | AM7: =SUMIF($BC$1:$CI$1,AM$1,$BC7:$CI7)+AL7 -> 0 | AO7: =SUMIF($BC$1:$CI$1,AO$1,$BC7:$CI7)+AN7 -> 0 | AP7: =CK7 -> 0 | AT7: =AE7+AG7+AI7+AK7+AM7+AO7+SUM(AQ7:AS7) -> 0 | AZ7: =VLOOKUP(C7,Employees!D:I,6,FALSE) -> #N/A | BA7: =IF(ISBLANK(D7),0,(E7-D7)*24) -> 0 | BB7: =IF(BA7>$AY$1,1,IF(BA7>=$AX$1,0.5,0)) -> 0 | BC7: =BA7-BB7-BD7-BE7 -> 0 | BD7: =IF(AND(E7>$AV$1, D7<$AW$1),(MIN(E7,$AW$1)-MAX(D7,$AV$1))*24,0) -> 0 | BE7: =IF(E7>$AW$1,(E7-MAX(D7,$AW$1))*24,0) -> 0 | BF7: =IF(ISBLANK(G7),0,(H7-G7)*24) -> 0 | BG7: =IF(BF7>$AY$1,1,IF(BF7>=$AX$1,0.5,0)) -> 0 | BH7: =BF7-BG7-BI7-BJ7 -> 0 | BI7: =IF(AND(H7>$AV$1,G7<$AW$1),(MIN(H7,$AW$1)-MAX(G7,$AV$1))*24,0) -> 0 | BJ7: =IF(H7>$AW$1,(H7-MAX(G7,$AW$1))*24,0) -> 0 | BK7: =IF(ISBLANK(J7),0,(K7-J7)*24) -> 0 | BL7: =IF(BK7>$AY$1,1,IF(BK7>=$AX$1,0.5,0)) -> 0 | BM7: =BK7-BL7-BN7-BO7 -> 0 | BN7: =IF(AND(K7>$AV$1, J7<$AW$1),(MIN(K7,$AW$1)-MAX(J7,$AV$1))*24,0) -> 0 | BO7: =IF(K7>$AW$1,(K7-MAX(J7,$AW$1))*24,0) -> 0 | BP7: =IF(ISBLANK(M7),0,(N7-M7)*24) -> 0 | BQ7: =IF(BP7>$AY$1,1,IF(BP7>=$AX$1,0.5,0)) -> 0 | BR7: =BP7-BQ7-BS7-BT7 -> 0 | BS7: =IF(AND(N7>$AV$1, M7<$AW$1),(MIN(N7,$AW$1)-MAX(M7,$AV$1))*24,0) -> 0 | BT7: =IF(N7>$AW$1,(N7-MAX(M7,$AW$1))*24,0) -> 0 | BU7: =IF(ISBLANK(P7),0,(Q7-P7)*24) -> 0 | BV7: =IF(BU7>$AY$1,1,IF(BU7>=$AX$1,0.5,0)) -> 0 | BW7: =BU7-BV7-BX7-BY7 -> 0 | BX7: =IF(AND(Q7>$AV$1, P7<$AW$1),(MIN(Q7,$AW$1)-MAX(P7,$AV$1))*24,0) -> 0 | BY7: =IF(Q7>$AW$1,(Q7-MAX(P7,$AW$1))*24,0) -> 0 | BZ7: =IF(ISBLANK(S7),0,(T7-S7)*24) -> 0 | CA7: =IF(BZ7>$AY$1,1,IF(BZ7>=$AX$1,0.5,0)) -> 0 | CB7: =BZ7-CA7-CC7-CD7 -> 0 | CC7: =IF(AND(T7>$AV$1, S7<$AW$1),(MIN(T7,$AW$1)-MAX(S7,$AV$1))*24,0) -> 0 | CD7: =IF(T7>$AW$1,(T7-MAX(S7,$AW$1))*24,0) -> 0 | CE7: =IF(ISBLANK(V7),0,(W7-V7)*24) -> 0 | CF7: =IF(CE7>$AY$1,1,IF(CE7>=$AX$1,0.5,0)) -> 0 | CG7: =CE7-CF7-CH7-CI7 -> 0 | CH7: =IF(AND(W7>$AV$1, V7<$AW$1),(MIN(W7,$AW$1)-MAX(V7,$AV$1))*24,0) -> 0 | CI7: =IF(W7>$AW$1,(W7-MAX(V7,$AW$1))*24,0) -> 0 | CK7: =SUM(IF(F7>0,1,0),IF(I7>0,1,0),IF(L7>0,1,0),IF(O7>0,1,0),IF(R7>0,1,0),IF(U7>0,1,0),IF(X7>0,1,0)) -> 0
A8: =IF(ISNA(AZ8),"",AZ8) | F8: =BA8-BB8 -> 0 | I8: =BF8-BG8 -> 0 | L8: =BK8-BL8 -> 0 | O8: =BP8-BQ8 -> 0 | R8: =BU8-BV8 -> 0 | U8: =BZ8-CA8 -> 0 | X8: =CE8-CF8 -> 0 | AB8: =SUM(F8,I8,L8,O8,R8,U8,X8) -> 0 | AE8: =SUMIF($BC$1:$CI$1,AE$1,$BC8:$CI8)+AD8 -> 0 | AG8: =SUMIF($BC$1:$CI$1,AG$1,$BC8:$CI8)+AF8 -> 0 | AI8: =SUMIF($BC$1:$CI$1,AI$1,$BC8:$CI8)+AH8 -> 0 | AK8: =SUMIF($BC$1:$CI$1,AK$1,$BC8:$CI8)+AJ8 -> 0 | AM8: =SUMIF($BC$1:$CI$1,AM$1,$BC8:$CI8)+AL8 -> 0 | AO8: =SUMIF($BC$1:$CI$1,AO$1,$BC8:$CI8)+AN8 -> 0 | AP8: =CK8 -> 0 | AT8: =AE8+AG8+AI8+AK8+AM8+AO8+SUM(AQ8:AS8) -> 0 | AZ8: =VLOOKUP(C8,Employees!D:I,6,FALSE) -> #N/A | BA8: =IF(ISBLANK(D8),0,(E8-D8)*24) -> 0 | BB8: =IF(BA8>$AY$1,1,IF(BA8>=$AX$1,0.5,0)) -> 0 | BC8: =BA8-BB8-BD8-BE8 -> 0 | BD8: =IF(AND(E8>$AV$1, D8<$AW$1),(MIN(E8,$AW$1)-MAX(D8,$AV$1))*24,0) -> 0 | BE8: =IF(E8>$AW$1,(E8-MAX(D8,$AW$1))*24,0) -> 0 | BF8: =IF(ISBLANK(G8),0,(H8-G8)*24) -> 0 | BG8: =IF(BF8>$AY$1,1,IF(BF8>=$AX$1,0.5,0)) -> 0 | BH8: =BF8-BG8-BI8-BJ8 -> 0 | BI8: =IF(AND(H8>$AV$1,G8<$AW$1),(MIN(H8,$AW$1)-MAX(G8,$AV$1))*24,0) -> 0 | BJ8: =IF(H8>$AW$1,(H8-MAX(G8,$AW$1))*24,0) -> 0 | BK8: =IF(ISBLANK(J8),0,(K8-J8)*24) -> 0 | BL8: =IF(BK8>$AY$1,1,IF(BK8>=$AX$1,0.5,0)) -> 0 | BM8: =BK8-BL8-BN8-BO8 -> 0 | BN8: =IF(AND(K8>$AV$1, J8<$AW$1),(MIN(K8,$AW$1)-MAX(J8,$AV$1))*24,0) -> 0 | BO8: =IF(K8>$AW$1,(K8-MAX(J8,$AW$1))*24,0) -> 0 | BP8: =IF(ISBLANK(M8),0,(N8-M8)*24) -> 0 | BQ8: =IF(BP8>$AY$1,1,IF(BP8>=$AX$1,0.5,0)) -> 0 | BR8: =BP8-BQ8-BS8-BT8 -> 0 | BS8: =IF(AND(N8>$AV$1, M8<$AW$1),(MIN(N8,$AW$1)-MAX(M8,$AV$1))*24,0) -> 0 | BT8: =IF(N8>$AW$1,(N8-MAX(M8,$AW$1))*24,0) -> 0 | BU8: =IF(ISBLANK(P8),0,(Q8-P8)*24) -> 0 | BV8: =IF(BU8>$AY$1,1,IF(BU8>=$AX$1,0.5,0)) -> 0 | BW8: =BU8-BV8-BX8-BY8 -> 0 | BX8: =IF(AND(Q8>$AV$1, P8<$AW$1),(MIN(Q8,$AW$1)-MAX(P8,$AV$1))*24,0) -> 0 | BY8: =IF(Q8>$AW$1,(Q8-MAX(P8,$AW$1))*24,0) -> 0 | BZ8: =IF(ISBLANK(S8),0,(T8-S8)*24) -> 0 | CA8: =IF(BZ8>$AY$1,1,IF(BZ8>=$AX$1,0.5,0)) -> 0 | CB8: =BZ8-CA8-CC8-CD8 -> 0 | CC8: =IF(AND(T8>$AV$1, S8<$AW$1),(MIN(T8,$AW$1)-MAX(S8,$AV$1))*24,0) -> 0 | CD8: =IF(T8>$AW$1,(T8-MAX(S8,$AW$1))*24,0) -> 0 | CE8: =IF(ISBLANK(V8),0,(W8-V8)*24) -> 0 | CF8: =IF(CE8>$AY$1,1,IF(CE8>=$AX$1,0.5,0)) -> 0 | CG8: =CE8-CF8-CH8-CI8 -> 0 | CH8: =IF(AND(W8>$AV$1, V8<$AW$1),(MIN(W8,$AW$1)-MAX(V8,$AV$1))*24,0) -> 0 | CI8: =IF(W8>$AW$1,(W8-MAX(V8,$AW$1))*24,0) -> 0 | CK8: =SUM(IF(F8>0,1,0),IF(I8>0,1,0),IF(L8>0,1,0),IF(O8>0,1,0),IF(R8>0,1,0),IF(U8>0,1,0),IF(X8>0,1,0)) -> 0
A9: =IF(ISNA(AZ9),"",AZ9) | F9: =BA9-BB9 -> 0 | I9: =BF9-BG9 -> 0 | L9: =BK9-BL9 -> 0 | O9: =BP9-BQ9 -> 0 | R9: =BU9-BV9 -> 0 | U9: =BZ9-CA9 -> 0 | X9: =CE9-CF9 -> 0 | AB9: =SUM(F9,I9,L9,O9,R9,U9,X9) -> 0 | AE9: =SUMIF($BC$1:$CI$1,AE$1,$BC9:$CI9)+AD9 -> 0 | AG9: =SUMIF($BC$1:$CI$1,AG$1,$BC9:$CI9)+AF9 -> 0 | AI9: =SUMIF($BC$1:$CI$1,AI$1,$BC9:$CI9)+AH9 -> 0 | AK9: =SUMIF($BC$1:$CI$1,AK$1,$BC9:$CI9)+AJ9 -> 0 | AM9: =SUMIF($BC$1:$CI$1,AM$1,$BC9:$CI9)+AL9 -> 0 | AO9: =SUMIF($BC$1:$CI$1,AO$1,$BC9:$CI9)+AN9 -> 0 | AP9: =CK9 -> 0 | AT9: =AE9+AG9+AI9+AK9+AM9+AO9+SUM(AQ9:AS9) -> 0 | AZ9: =VLOOKUP(C9,Employees!D:I,6,FALSE) -> #N/A | BA9: =IF(ISBLANK(D9),0,(E9-D9)*24) -> 0 | BB9: =IF(BA9>$AY$1,1,IF(BA9>=$AX$1,0.5,0)) -> 0 | BC9: =BA9-BB9-BD9-BE9 -> 0 | BD9: =IF(AND(E9>$AV$1, D9<$AW$1),(MIN(E9,$AW$1)-MAX(D9,$AV$1))*24,0) -> 0 | BE9: =IF(E9>$AW$1,(E9-MAX(D9,$AW$1))*24,0) -> 0 | BF9: =IF(ISBLANK(G9),0,(H9-G9)*24) -> 0 | BG9: =IF(BF9>$AY$1,1,IF(BF9>=$AX$1,0.5,0)) -> 0 | BH9: =BF9-BG9-BI9-BJ9 -> 0 | BI9: =IF(AND(H9>$AV$1,G9<$AW$1),(MIN(H9,$AW$1)-MAX(G9,$AV$1))*24,0) -> 0 | BJ9: =IF(H9>$AW$1,(H9-MAX(G9,$AW$1))*24,0) -> 0 | BK9: =IF(ISBLANK(J9),0,(K9-J9)*24) -> 0 | BL9: =IF(BK9>$AY$1,1,IF(BK9>=$AX$1,0.5,0)) -> 0 | BM9: =BK9-BL9-BN9-BO9 -> 0 | BN9: =IF(AND(K9>$AV$1, J9<$AW$1),(MIN(K9,$AW$1)-MAX(J9,$AV$1))*24,0) -> 0 | BO9: =IF(K9>$AW$1,(K9-MAX(J9,$AW$1))*24,0) -> 0 | BP9: =IF(ISBLANK(M9),0,(N9-M9)*24) -> 0 | BQ9: =IF(BP9>$AY$1,1,IF(BP9>=$AX$1,0.5,0)) -> 0 | BR9: =BP9-BQ9-BS9-BT9 -> 0 | BS9: =IF(AND(N9>$AV$1, M9<$AW$1),(MIN(N9,$AW$1)-MAX(M9,$AV$1))*24,0) -> 0 | BT9: =IF(N9>$AW$1,(N9-MAX(M9,$AW$1))*24,0) -> 0 | BU9: =IF(ISBLANK(P9),0,(Q9-P9)*24) -> 0 | BV9: =IF(BU9>$AY$1,1,IF(BU9>=$AX$1,0.5,0)) -> 0 | BW9: =BU9-BV9-BX9-BY9 -> 0 | BX9: =IF(AND(Q9>$AV$1, P9<$AW$1),(MIN(Q9,$AW$1)-MAX(P9,$AV$1))*24,0) -> 0 | BY9: =IF(Q9>$AW$1,(Q9-MAX(P9,$AW$1))*24,0) -> 0 | BZ9: =IF(ISBLANK(S9),0,(T9-S9)*24) -> 0 | CA9: =IF(BZ9>$AY$1,1,IF(BZ9>=$AX$1,0.5,0)) -> 0 | CB9: =BZ9-CA9-CC9-CD9 -> 0 | CC9: =IF(AND(T9>$AV$1, S9<$AW$1),(MIN(T9,$AW$1)-MAX(S9,$AV$1))*24,0) -> 0 | CD9: =IF(T9>$AW$1,(T9-MAX(S9,$AW$1))*24,0) -> 0 | CE9: =IF(ISBLANK(V9),0,(W9-V9)*24) -> 0 | CF9: =IF(CE9>$AY$1,1,IF(CE9>=$AX$1,0.5,0)) -> 0 | CG9: =CE9-CF9-CH9-CI9 -> 0 | CH9: =IF(AND(W9>$AV$1, V9<$AW$1),(MIN(W9,$AW$1)-MAX(V9,$AV$1))*24,0) -> 0 | CI9: =IF(W9>$AW$1,(W9-MAX(V9,$AW$1))*24,0) -> 0 | CK9: =SUM(IF(F9>0,1,0),IF(I9>0,1,0),IF(L9>0,1,0),IF(O9>0,1,0),IF(R9>0,1,0),IF(U9>0,1,0),IF(X9>0,1,0)) -> 0
A10: =IF(ISNA(AZ10),"",AZ10) | F10: =BA10-BB10 -> 0 | I10: =BF10-BG10 -> 0 | L10: =BK10-BL10 -> 0 | O10: =BP10-BQ10 -> 0 | R10: =BU10-BV10 -> 0 | U10: =BZ10-CA10 -> 0 | X10: =CE10-CF10 -> 0 | AB10: =SUM(F10,I10,L10,O10,R10,U10,X10) -> 0 | AE10: =SUMIF($BC$1:$CI$1,AE$1,$BC10:$CI10)+AD10 -> 0 | AG10: =SUMIF($BC$1:$CI$1,AG$1,$BC10:$CI10)+AF10 -> 0 | AI10: =SUMIF($BC$1:$CI$1,AI$1,$BC10:$CI10)+AH10 -> 0 | AK10: =SUMIF($BC$1:$CI$1,AK$1,$BC10:$CI10)+AJ10 -> 0 | AM10: =SUMIF($BC$1:$CI$1,AM$1,$BC10:$CI10)+AL10 -> 0 | AO10: =SUMIF($BC$1:$CI$1,AO$1,$BC10:$CI10)+AN10 -> 0 | AP10: =CK10 -> 0 | AT10: =AE10+AG10+AI10+AK10+AM10+AO10+SUM(AQ10:AS10) -> 0 | AZ10: =VLOOKUP(C10,Employees!D:I,6,FALSE) -> #N/A | BA10: =IF(ISBLANK(D10),0,(E10-D10)*24) -> 0 | BB10: =IF(BA10>$AY$1,1,IF(BA10>=$AX$1,0.5,0)) -> 0 | BC10: =BA10-BB10-BD10-BE10 -> 0 | BD10: =IF(AND(E10>$AV$1, D10<$AW$1),(MIN(E10,$AW$1)-MAX(D10,$AV$1))*24,0) -> 0 | BE10: =IF(E10>$AW$1,(E10-MAX(D10,$AW$1))*24,0) -> 0 | BF10: =IF(ISBLANK(G10),0,(H10-G10)*24) -> 0 | BG10: =IF(BF10>$AY$1,1,IF(BF10>=$AX$1,0.5,0)) -> 0 | BH10: =BF10-BG10-BI10-BJ10 -> 0 | BI10: =IF(AND(H10>$AV$1,G10<$AW$1),(MIN(H10,$AW$1)-MAX(G10,$AV$1))*24,0) -> 0 | BJ10: =IF(H10>$AW$1,(H10-MAX(G10,$AW$1))*24,0) -> 0 | BK10: =IF(ISBLANK(J10),0,(K10-J10)*24) -> 0 | BL10: =IF(BK10>$AY$1,1,IF(BK10>=$AX$1,0.5,0)) -> 0 | BM10: =BK10-BL10-BN10-BO10 -> 0 | BN10: =IF(AND(K10>$AV$1, J10<$AW$1),(MIN(K10,$AW$1)-MAX(J10,$AV$1))*24,0) -> 0 | BO10: =IF(K10>$AW$1,(K10-MAX(J10,$AW$1))*24,0) -> 0 | BP10: =IF(ISBLANK(M10),0,(N10-M10)*24) -> 0 | BQ10: =IF(BP10>$AY$1,1,IF(BP10>=$AX$1,0.5,0)) -> 0 | BR10: =BP10-BQ10-BS10-BT10 -> 0 | BS10: =IF(AND(N10>$AV$1, M10<$AW$1),(MIN(N10,$AW$1)-MAX(M10,$AV$1))*24,0) -> 0 | BT10: =IF(N10>$AW$1,(N10-MAX(M10,$AW$1))*24,0) -> 0 | BU10: =IF(ISBLANK(P10),0,(Q10-P10)*24) -> 0 | BV10: =IF(BU10>$AY$1,1,IF(BU10>=$AX$1,0.5,0)) -> 0 | BW10: =BU10-BV10-BX10-BY10 -> 0 | BX10: =IF(AND(Q10>$AV$1, P10<$AW$1),(MIN(Q10,$AW$1)-MAX(P10,$AV$1))*24,0) -> 0 | BY10: =IF(Q10>$AW$1,(Q10-MAX(P10,$AW$1))*24,0) -> 0 | BZ10: =IF(ISBLANK(S10),0,(T10-S10)*24) -> 0 | CA10: =IF(BZ10>$AY$1,1,IF(BZ10>=$AX$1,0.5,0)) -> 0 | CB10: =BZ10-CA10-CC10-CD10 -> 0 | CC10: =IF(AND(T10>$AV$1, S10<$AW$1),(MIN(T10,$AW$1)-MAX(S10,$AV$1))*24,0) -> 0 | CD10: =IF(T10>$AW$1,(T10-MAX(S10,$AW$1))*24,0) -> 0 | CE10: =IF(ISBLANK(V10),0,(W10-V10)*24) -> 0 | CF10: =IF(CE10>$AY$1,1,IF(CE10>=$AX$1,0.5,0)) -> 0 | CG10: =CE10-CF10-CH10-CI10 -> 0 | CH10: =IF(AND(W10>$AV$1, V10<$AW$1),(MIN(W10,$AW$1)-MAX(V10,$AV$1))*24,0) -> 0 | CI10: =IF(W10>$AW$1,(W10-MAX(V10,$AW$1))*24,0) -> 0 | CK10: =SUM(IF(F10>0,1,0),IF(I10>0,1,0),IF(L10>0,1,0),IF(O10>0,1,0),IF(R10>0,1,0),IF(U10>0,1,0),IF(X10>0,1,0)) -> 0
A11: =IF(ISNA(AZ11),"",AZ11) | F11: =BA11-BB11 -> 0 | I11: =BF11-BG11 -> 0 | L11: =BK11-BL11 -> 0 | O11: =BP11-BQ11 -> 0 | R11: =BU11-BV11 -> 0 | U11: =BZ11-CA11 -> 0 | X11: =CE11-CF11 -> 0 | AB11: =SUM(F11,I11,L11,O11,R11,U11,X11) -> 0 | AE11: =SUMIF($BC$1:$CI$1,AE$1,$BC11:$CI11)+AD11 -> 0 | AG11: =SUMIF($BC$1:$CI$1,AG$1,$BC11:$CI11)+AF11 -> 0 | AI11: =SUMIF($BC$1:$CI$1,AI$1,$BC11:$CI11)+AH11 -> 0 | AK11: =SUMIF($BC$1:$CI$1,AK$1,$BC11:$CI11)+AJ11 -> 0 | AM11: =SUMIF($BC$1:$CI$1,AM$1,$BC11:$CI11)+AL11 -> 0 | AO11: =SUMIF($BC$1:$CI$1,AO$1,$BC11:$CI11)+AN11 -> 0 | AP11: =CK11 -> 0 | AT11: =AE11+AG11+AI11+AK11+AM11+AO11+SUM(AQ11:AS11) -> 0 | AZ11: =VLOOKUP(C11,Employees!D:I,6,FALSE) -> #N/A | BA11: =IF(ISBLANK(D11),0,(E11-D11)*24) -> 0 | BB11: =IF(BA11>$AY$1,1,IF(BA11>=$AX$1,0.5,0)) -> 0 | BC11: =BA11-BB11-BD11-BE11 -> 0 | BD11: =IF(AND(E11>$AV$1, D11<$AW$1),(MIN(E11,$AW$1)-MAX(D11,$AV$1))*24,0) -> 0 | BE11: =IF(E11>$AW$1,(E11-MAX(D11,$AW$1))*24,0) -> 0 | BF11: =IF(ISBLANK(G11),0,(H11-G11)*24) -> 0 | BG11: =IF(BF11>$AY$1,1,IF(BF11>=$AX$1,0.5,0)) -> 0 | BH11: =BF11-BG11-BI11-BJ11 -> 0 | BI11: =IF(AND(H11>$AV$1,G11<$AW$1),(MIN(H11,$AW$1)-MAX(G11,$AV$1))*24,0) -> 0 | BJ11: =IF(H11>$AW$1,(H11-MAX(G11,$AW$1))*24,0) -> 0 | BK11: =IF(ISBLANK(J11),0,(K11-J11)*24) -> 0 | BL11: =IF(BK11>$AY$1,1,IF(BK11>=$AX$1,0.5,0)) -> 0 | BM11: =BK11-BL11-BN11-BO11 -> 0 | BN11: =IF(AND(K11>$AV$1, J11<$AW$1),(MIN(K11,$AW$1)-MAX(J11,$AV$1))*24,0) -> 0 | BO11: =IF(K11>$AW$1,(K11-MAX(J11,$AW$1))*24,0) -> 0 | BP11: =IF(ISBLANK(M11),0,(N11-M11)*24) -> 0 | BQ11: =IF(BP11>$AY$1,1,IF(BP11>=$AX$1,0.5,0)) -> 0 | BR11: =BP11-BQ11-BS11-BT11 -> 0 | BS11: =IF(AND(N11>$AV$1, M11<$AW$1),(MIN(N11,$AW$1)-MAX(M11,$AV$1))*24,0) -> 0 | BT11: =IF(N11>$AW$1,(N11-MAX(M11,$AW$1))*24,0) -> 0 | BU11: =IF(ISBLANK(P11),0,(Q11-P11)*24) -> 0 | BV11: =IF(BU11>$AY$1,1,IF(BU11>=$AX$1,0.5,0)) -> 0 | BW11: =BU11-BV11-BX11-BY11 -> 0 | BX11: =IF(AND(Q11>$AV$1, P11<$AW$1),(MIN(Q11,$AW$1)-MAX(P11,$AV$1))*24,0) -> 0 | BY11: =IF(Q11>$AW$1,(Q11-MAX(P11,$AW$1))*24,0) -> 0 | BZ11: =IF(ISBLANK(S11),0,(T11-S11)*24) -> 0 | CA11: =IF(BZ11>$AY$1,1,IF(BZ11>=$AX$1,0.5,0)) -> 0 | CB11: =BZ11-CA11-CC11-CD11 -> 0 | CC11: =IF(AND(T11>$AV$1, S11<$AW$1),(MIN(T11,$AW$1)-MAX(S11,$AV$1))*24,0) -> 0 | CD11: =IF(T11>$AW$1,(T11-MAX(S11,$AW$1))*24,0) -> 0 | CE11: =IF(ISBLANK(V11),0,(W11-V11)*24) -> 0 | CF11: =IF(CE11>$AY$1,1,IF(CE11>=$AX$1,0.5,0)) -> 0 | CG11: =CE11-CF11-CH11-CI11 -> 0 | CH11: =IF(AND(W11>$AV$1, V11<$AW$1),(MIN(W11,$AW$1)-MAX(V11,$AV$1))*24,0) -> 0 | CI11: =IF(W11>$AW$1,(W11-MAX(V11,$AW$1))*24,0) -> 0 | CK11: =SUM(IF(F11>0,1,0),IF(I11>0,1,0),IF(L11>0,1,0),IF(O11>0,1,0),IF(R11>0,1,0),IF(U11>0,1,0),IF(X11>0,1,0)) -> 0
A12: =IF(ISNA(AZ12),"",AZ12) | F12: =BA12-BB12 -> 0 | I12: =BF12-BG12 -> 0 | L12: =BK12-BL12 -> 0 | O12: =BP12-BQ12 -> 0 | R12: =BU12-BV12 -> 0 | U12: =BZ12-CA12 -> 0 | X12: =CE12-CF12 -> 0 | AB12: =SUM(F12,I12,L12,O12,R12,U12,X12) -> 0 | AE12: =SUMIF($BC$1:$CI$1,AE$1,$BC12:$CI12)+AD12 -> 0 | AG12: =SUMIF($BC$1:$CI$1,AG$1,$BC12:$CI12)+AF12 -> 0 | AI12: =SUMIF($BC$1:$CI$1,AI$1,$BC12:$CI12)+AH12 -> 0 | AK12: =SUMIF($BC$1:$CI$1,AK$1,$BC12:$CI12)+AJ12 -> 0 | AM12: =SUMIF($BC$1:$CI$1,AM$1,$BC12:$CI12)+AL12 -> 0 | AO12: =SUMIF($BC$1:$CI$1,AO$1,$BC12:$CI12)+AN12 -> 0 | AP12: =CK12 -> 0 | AT12: =AE12+AG12+AI12+AK12+AM12+AO12+SUM(AQ12:AS12) -> 0 | AZ12: =VLOOKUP(C12,Employees!D:I,6,FALSE) -> #N/A | BA12: =IF(ISBLANK(D12),0,(E12-D12)*24) -> 0 | BB12: =IF(BA12>$AY$1,1,IF(BA12>=$AX$1,0.5,0)) -> 0 | BC12: =BA12-BB12-BD12-BE12 -> 0 | BD12: =IF(AND(E12>$AV$1, D12<$AW$1),(MIN(E12,$AW$1)-MAX(D12,$AV$1))*24,0) -> 0 | BE12: =IF(E12>$AW$1,(E12-MAX(D12,$AW$1))*24,0) -> 0 | BF12: =IF(ISBLANK(G12),0,(H12-G12)*24) -> 0 | BG12: =IF(BF12>$AY$1,1,IF(BF12>=$AX$1,0.5,0)) -> 0 | BH12: =BF12-BG12-BI12-BJ12 -> 0 | BI12: =IF(AND(H12>$AV$1,G12<$AW$1),(MIN(H12,$AW$1)-MAX(G12,$AV$1))*24,0) -> 0 | BJ12: =IF(H12>$AW$1,(H12-MAX(G12,$AW$1))*24,0) -> 0 | BK12: =IF(ISBLANK(J12),0,(K12-J12)*24) -> 0 | BL12: =IF(BK12>$AY$1,1,IF(BK12>=$AX$1,0.5,0)) -> 0 | BM12: =BK12-BL12-BN12-BO12 -> 0 | BN12: =IF(AND(K12>$AV$1, J12<$AW$1),(MIN(K12,$AW$1)-MAX(J12,$AV$1))*24,0) -> 0 | BO12: =IF(K12>$AW$1,(K12-MAX(J12,$AW$1))*24,0) -> 0 | BP12: =IF(ISBLANK(M12),0,(N12-M12)*24) -> 0 | BQ12: =IF(BP12>$AY$1,1,IF(BP12>=$AX$1,0.5,0)) -> 0 | BR12: =BP12-BQ12-BS12-BT12 -> 0 | BS12: =IF(AND(N12>$AV$1, M12<$AW$1),(MIN(N12,$AW$1)-MAX(M12,$AV$1))*24,0) -> 0 | BT12: =IF(N12>$AW$1,(N12-MAX(M12,$AW$1))*24,0) -> 0 | BU12: =IF(ISBLANK(P12),0,(Q12-P12)*24) -> 0 | BV12: =IF(BU12>$AY$1,1,IF(BU12>=$AX$1,0.5,0)) -> 0 | BW12: =BU12-BV12-BX12-BY12 -> 0 | BX12: =IF(AND(Q12>$AV$1, P12<$AW$1),(MIN(Q12,$AW$1)-MAX(P12,$AV$1))*24,0) -> 0 | BY12: =IF(Q12>$AW$1,(Q12-MAX(P12,$AW$1))*24,0) -> 0 | BZ12: =IF(ISBLANK(S12),0,(T12-S12)*24) -> 0 | CA12: =IF(BZ12>$AY$1,1,IF(BZ12>=$AX$1,0.5,0)) -> 0 | CB12: =BZ12-CA12-CC12-CD12 -> 0 | CC12: =IF(AND(T12>$AV$1, S12<$AW$1),(MIN(T12,$AW$1)-MAX(S12,$AV$1))*24,0) -> 0 | CD12: =IF(T12>$AW$1,(T12-MAX(S12,$AW$1))*24,0) -> 0 | CE12: =IF(ISBLANK(V12),0,(W12-V12)*24) -> 0 | CF12: =IF(CE12>$AY$1,1,IF(CE12>=$AX$1,0.5,0)) -> 0 | CG12: =CE12-CF12-CH12-CI12 -> 0 | CH12: =IF(AND(W12>$AV$1, V12<$AW$1),(MIN(W12,$AW$1)-MAX(V12,$AV$1))*24,0) -> 0 | CI12: =IF(W12>$AW$1,(W12-MAX(V12,$AW$1))*24,0) -> 0 | CK12: =SUM(IF(F12>0,1,0),IF(I12>0,1,0),IF(L12>0,1,0),IF(O12>0,1,0),IF(R12>0,1,0),IF(U12>0,1,0),IF(X12>0,1,0)) -> 0
A13: =IF(ISNA(AZ13),"",AZ13) | F13: =BA13-BB13 -> 0 | I13: =BF13-BG13 -> 0 | L13: =BK13-BL13 -> 0 | O13: =BP13-BQ13 -> 0 | R13: =BU13-BV13 -> 0 | U13: =BZ13-CA13 -> 0 | X13: =CE13-CF13 -> 0 | AB13: =SUM(F13,I13,L13,O13,R13,U13,X13) -> 0 | AE13: =SUMIF($BC$1:$CI$1,AE$1,$BC13:$CI13)+AD13 -> 0 | AG13: =SUMIF($BC$1:$CI$1,AG$1,$BC13:$CI13)+AF13 -> 0 | AI13: =SUMIF($BC$1:$CI$1,AI$1,$BC13:$CI13)+AH13 -> 0 | AK13: =SUMIF($BC$1:$CI$1,AK$1,$BC13:$CI13)+AJ13 -> 0 | AM13: =SUMIF($BC$1:$CI$1,AM$1,$BC13:$CI13)+AL13 -> 0 | AO13: =SUMIF($BC$1:$CI$1,AO$1,$BC13:$CI13)+AN13 -> 0 | AP13: =CK13 -> 0 | AT13: =AE13+AG13+AI13+AK13+AM13+AO13+SUM(AQ13:AS13) -> 0 | AZ13: =VLOOKUP(C13,Employees!D:I,6,FALSE) -> #N/A | BA13: =IF(ISBLANK(D13),0,(E13-D13)*24) -> 0 | BB13: =IF(BA13>$AY$1,1,IF(BA13>=$AX$1,0.5,0)) -> 0 | BC13: =BA13-BB13-BD13-BE13 -> 0 | BD13: =IF(AND(E13>$AV$1, D13<$AW$1),(MIN(E13,$AW$1)-MAX(D13,$AV$1))*24,0) -> 0 | BE13: =IF(E13>$AW$1,(E13-MAX(D13,$AW$1))*24,0) -> 0 | BF13: =IF(ISBLANK(G13),0,(H13-G13)*24) -> 0 | BG13: =IF(BF13>$AY$1,1,IF(BF13>=$AX$1,0.5,0)) -> 0 | BH13: =BF13-BG13-BI13-BJ13 -> 0 | BI13: =IF(AND(H13>$AV$1,G13<$AW$1),(MIN(H13,$AW$1)-MAX(G13,$AV$1))*24,0) -> 0 | BJ13: =IF(H13>$AW$1,(H13-MAX(G13,$AW$1))*24,0) -> 0 | BK13: =IF(ISBLANK(J13),0,(K13-J13)*24) -> 0 | BL13: =IF(BK13>$AY$1,1,IF(BK13>=$AX$1,0.5,0)) -> 0 | BM13: =BK13-BL13-BN13-BO13 -> 0 | BN13: =IF(AND(K13>$AV$1, J13<$AW$1),(MIN(K13,$AW$1)-MAX(J13,$AV$1))*24,0) -> 0 | BO13: =IF(K13>$AW$1,(K13-MAX(J13,$AW$1))*24,0) -> 0 | BP13: =IF(ISBLANK(M13),0,(N13-M13)*24) -> 0 | BQ13: =IF(BP13>$AY$1,1,IF(BP13>=$AX$1,0.5,0)) -> 0 | BR13: =BP13-BQ13-BS13-BT13 -> 0 | BS13: =IF(AND(N13>$AV$1, M13<$AW$1),(MIN(N13,$AW$1)-MAX(M13,$AV$1))*24,0) -> 0 | BT13: =IF(N13>$AW$1,(N13-MAX(M13,$AW$1))*24,0) -> 0 | BU13: =IF(ISBLANK(P13),0,(Q13-P13)*24) -> 0 | BV13: =IF(BU13>$AY$1,1,IF(BU13>=$AX$1,0.5,0)) -> 0 | BW13: =BU13-BV13-BX13-BY13 -> 0 | BX13: =IF(AND(Q13>$AV$1, P13<$AW$1),(MIN(Q13,$AW$1)-MAX(P13,$AV$1))*24,0) -> 0 | BY13: =IF(Q13>$AW$1,(Q13-MAX(P13,$AW$1))*24,0) -> 0 | BZ13: =IF(ISBLANK(S13),0,(T13-S13)*24) -> 0 | CA13: =IF(BZ13>$AY$1,1,IF(BZ13>=$AX$1,0.5,0)) -> 0 | CB13: =BZ13-CA13-CC13-CD13 -> 0 | CC13: =IF(AND(T13>$AV$1, S13<$AW$1),(MIN(T13,$AW$1)-MAX(S13,$AV$1))*24,0) -> 0 | CD13: =IF(T13>$AW$1,(T13-MAX(S13,$AW$1))*24,0) -> 0 | CE13: =IF(ISBLANK(V13),0,(W13-V13)*24) -> 0 | CF13: =IF(CE13>$AY$1,1,IF(CE13>=$AX$1,0.5,0)) -> 0 | CG13: =CE13-CF13-CH13-CI13 -> 0 | CH13: =IF(AND(W13>$AV$1, V13<$AW$1),(MIN(W13,$AW$1)-MAX(V13,$AV$1))*24,0) -> 0 | CI13: =IF(W13>$AW$1,(W13-MAX(V13,$AW$1))*24,0) -> 0 | CK13: =SUM(IF(F13>0,1,0),IF(I13>0,1,0),IF(L13>0,1,0),IF(O13>0,1,0),IF(R13>0,1,0),IF(U13>0,1,0),IF(X13>0,1,0)) -> 0
A14: =IF(ISNA(AZ14),"",AZ14) | F14: =BA14-BB14 -> 0 | I14: =BF14-BG14 -> 0 | L14: =BK14-BL14 -> 0 | O14: =BP14-BQ14 -> 0 | R14: =BU14-BV14 -> 0 | U14: =BZ14-CA14 -> 0 | X14: =CE14-CF14 -> 0 | AB14: =SUM(F14,I14,L14,O14,R14,U14,X14) -> 0 | AE14: =SUMIF($BC$1:$CI$1,AE$1,$BC14:$CI14)+AD14 -> 0 | AG14: =SUMIF($BC$1:$CI$1,AG$1,$BC14:$CI14)+AF14 -> 0 | AI14: =SUMIF($BC$1:$CI$1,AI$1,$BC14:$CI14)+AH14 -> 0 | AK14: =SUMIF($BC$1:$CI$1,AK$1,$BC14:$CI14)+AJ14 -> 0 | AM14: =SUMIF($BC$1:$CI$1,AM$1,$BC14:$CI14)+AL14 -> 0 | AO14: =SUMIF($BC$1:$CI$1,AO$1,$BC14:$CI14)+AN14 -> 0 | AP14: =CK14 -> 0 | AT14: =AE14+AG14+AI14+AK14+AM14+AO14+SUM(AQ14:AS14) -> 0 | AZ14: =VLOOKUP(C14,Employees!D:I,6,FALSE) -> #N/A | BA14: =IF(ISBLANK(D14),0,(E14-D14)*24) -> 0 | BB14: =IF(BA14>$AY$1,1,IF(BA14>=$AX$1,0.5,0)) -> 0 | BC14: =BA14-BB14-BD14-BE14 -> 0 | BD14: =IF(AND(E14>$AV$1, D14<$AW$1),(MIN(E14,$AW$1)-MAX(D14,$AV$1))*24,0) -> 0 | BE14: =IF(E14>$AW$1,(E14-MAX(D14,$AW$1))*24,0) -> 0 | BF14: =IF(ISBLANK(G14),0,(H14-G14)*24) -> 0 | BG14: =IF(BF14>$AY$1,1,IF(BF14>=$AX$1,0.5,0)) -> 0 | BH14: =BF14-BG14-BI14-BJ14 -> 0 | BI14: =IF(AND(H14>$AV$1,G14<$AW$1),(MIN(H14,$AW$1)-MAX(G14,$AV$1))*24,0) -> 0 | BJ14: =IF(H14>$AW$1,(H14-MAX(G14,$AW$1))*24,0) -> 0 | BK14: =IF(ISBLANK(J14),0,(K14-J14)*24) -> 0 | BL14: =IF(BK14>$AY$1,1,IF(BK14>=$AX$1,0.5,0)) -> 0 | BM14: =BK14-BL14-BN14-BO14 -> 0 | BN14: =IF(AND(K14>$AV$1, J14<$AW$1),(MIN(K14,$AW$1)-MAX(J14,$AV$1))*24,0) -> 0 | BO14: =IF(K14>$AW$1,(K14-MAX(J14,$AW$1))*24,0) -> 0 | BP14: =IF(ISBLANK(M14),0,(N14-M14)*24) -> 0 | BQ14: =IF(BP14>$AY$1,1,IF(BP14>=$AX$1,0.5,0)) -> 0 | BR14: =BP14-BQ14-BS14-BT14 -> 0 | BS14: =IF(AND(N14>$AV$1, M14<$AW$1),(MIN(N14,$AW$1)-MAX(M14,$AV$1))*24,0) -> 0 | BT14: =IF(N14>$AW$1,(N14-MAX(M14,$AW$1))*24,0) -> 0 | BU14: =IF(ISBLANK(P14),0,(Q14-P14)*24) -> 0 | BV14: =IF(BU14>$AY$1,1,IF(BU14>=$AX$1,0.5,0)) -> 0 | BW14: =BU14-BV14-BX14-BY14 -> 0 | BX14: =IF(AND(Q14>$AV$1, P14<$AW$1),(MIN(Q14,$AW$1)-MAX(P14,$AV$1))*24,0) -> 0 | BY14: =IF(Q14>$AW$1,(Q14-MAX(P14,$AW$1))*24,0) -> 0 | BZ14: =IF(ISBLANK(S14),0,(T14-S14)*24) -> 0 | CA14: =IF(BZ14>$AY$1,1,IF(BZ14>=$AX$1,0.5,0)) -> 0 | CB14: =BZ14-CA14-CC14-CD14 -> 0 | CC14: =IF(AND(T14>$AV$1, S14<$AW$1),(MIN(T14,$AW$1)-MAX(S14,$AV$1))*24,0) -> 0 | CD14: =IF(T14>$AW$1,(T14-MAX(S14,$AW$1))*24,0) -> 0 | CE14: =IF(ISBLANK(V14),0,(W14-V14)*24) -> 0 | CF14: =IF(CE14>$AY$1,1,IF(CE14>=$AX$1,0.5,0)) -> 0 | CG14: =CE14-CF14-CH14-CI14 -> 0 | CH14: =IF(AND(W14>$AV$1, V14<$AW$1),(MIN(W14,$AW$1)-MAX(V14,$AV$1))*24,0) -> 0 | CI14: =IF(W14>$AW$1,(W14-MAX(V14,$AW$1))*24,0) -> 0 | CK14: =SUM(IF(F14>0,1,0),IF(I14>0,1,0),IF(L14>0,1,0),IF(O14>0,1,0),IF(R14>0,1,0),IF(U14>0,1,0),IF(X14>0,1,0)) -> 0
A15: =IF(ISNA(AZ15),"",AZ15) | F15: =BA15-BB15 -> 0 | I15: =BF15-BG15 -> 0 | L15: =BK15-BL15 -> 0 | O15: =BP15-BQ15 -> 0 | R15: =BU15-BV15 -> 0 | U15: =BZ15-CA15 -> 0 | X15: =CE15-CF15 -> 0 | AB15: =SUM(F15,I15,L15,O15,R15,U15,X15) -> 0 | AE15: =SUMIF($BC$1:$CI$1,AE$1,$BC15:$CI15)+AD15 -> 0 | AG15: =SUMIF($BC$1:$CI$1,AG$1,$BC15:$CI15)+AF15 -> 0 | AI15: =SUMIF($BC$1:$CI$1,AI$1,$BC15:$CI15)+AH15 -> 0 | AK15: =SUMIF($BC$1:$CI$1,AK$1,$BC15:$CI15)+AJ15 -> 0 | AM15: =SUMIF($BC$1:$CI$1,AM$1,$BC15:$CI15)+AL15 -> 0 | AO15: =SUMIF($BC$1:$CI$1,AO$1,$BC15:$CI15)+AN15 -> 0 | AP15: =CK15 -> 0 | AT15: =AE15+AG15+AI15+AK15+AM15+AO15+SUM(AQ15:AS15) -> 0 | AZ15: =VLOOKUP(C15,Employees!D:I,6,FALSE) -> #N/A | BA15: =IF(ISBLANK(D15),0,(E15-D15)*24) -> 0 | BB15: =IF(BA15>$AY$1,1,IF(BA15>=$AX$1,0.5,0)) -> 0 | BC15: =BA15-BB15-BD15-BE15 -> 0 | BD15: =IF(AND(E15>$AV$1, D15<$AW$1),(MIN(E15,$AW$1)-MAX(D15,$AV$1))*24,0) -> 0 | BE15: =IF(E15>$AW$1,(E15-MAX(D15,$AW$1))*24,0) -> 0 | BF15: =IF(ISBLANK(G15),0,(H15-G15)*24) -> 0 | BG15: =IF(BF15>$AY$1,1,IF(BF15>=$AX$1,0.5,0)) -> 0 | BH15: =BF15-BG15-BI15-BJ15 -> 0 | BI15: =IF(AND(H15>$AV$1,G15<$AW$1),(MIN(H15,$AW$1)-MAX(G15,$AV$1))*24,0) -> 0 | BJ15: =IF(H15>$AW$1,(H15-MAX(G15,$AW$1))*24,0) -> 0 | BK15: =IF(ISBLANK(J15),0,(K15-J15)*24) -> 0 | BL15: =IF(BK15>$AY$1,1,IF(BK15>=$AX$1,0.5,0)) -> 0 | BM15: =BK15-BL15-BN15-BO15 -> 0 | BN15: =IF(AND(K15>$AV$1, J15<$AW$1),(MIN(K15,$AW$1)-MAX(J15,$AV$1))*24,0) -> 0 | BO15: =IF(K15>$AW$1,(K15-MAX(J15,$AW$1))*24,0) -> 0 | BP15: =IF(ISBLANK(M15),0,(N15-M15)*24) -> 0 | BQ15: =IF(BP15>$AY$1,1,IF(BP15>=$AX$1,0.5,0)) -> 0 | BR15: =BP15-BQ15-BS15-BT15 -> 0 | BS15: =IF(AND(N15>$AV$1, M15<$AW$1),(MIN(N15,$AW$1)-MAX(M15,$AV$1))*24,0) -> 0 | BT15: =IF(N15>$AW$1,(N15-MAX(M15,$AW$1))*24,0) -> 0 | BU15: =IF(ISBLANK(P15),0,(Q15-P15)*24) -> 0 | BV15: =IF(BU15>$AY$1,1,IF(BU15>=$AX$1,0.5,0)) -> 0 | BW15: =BU15-BV15-BX15-BY15 -> 0 | BX15: =IF(AND(Q15>$AV$1, P15<$AW$1),(MIN(Q15,$AW$1)-MAX(P15,$AV$1))*24,0) -> 0 | BY15: =IF(Q15>$AW$1,(Q15-MAX(P15,$AW$1))*24,0) -> 0 | BZ15: =IF(ISBLANK(S15),0,(T15-S15)*24) -> 0 | CA15: =IF(BZ15>$AY$1,1,IF(BZ15>=$AX$1,0.5,0)) -> 0 | CB15: =BZ15-CA15-CC15-CD15 -> 0 | CC15: =IF(AND(T15>$AV$1, S15<$AW$1),(MIN(T15,$AW$1)-MAX(S15,$AV$1))*24,0) -> 0 | CD15: =IF(T15>$AW$1,(T15-MAX(S15,$AW$1))*24,0) -> 0 | CE15: =IF(ISBLANK(V15),0,(W15-V15)*24) -> 0 | CF15: =IF(CE15>$AY$1,1,IF(CE15>=$AX$1,0.5,0)) -> 0 | CG15: =CE15-CF15-CH15-CI15 -> 0 | CH15: =IF(AND(W15>$AV$1, V15<$AW$1),(MIN(W15,$AW$1)-MAX(V15,$AV$1))*24,0) -> 0 | CI15: =IF(W15>$AW$1,(W15-MAX(V15,$AW$1))*24,0) -> 0 | CK15: =SUM(IF(F15>0,1,0),IF(I15>0,1,0),IF(L15>0,1,0),IF(O15>0,1,0),IF(R15>0,1,0),IF(U15>0,1,0),IF(X15>0,1,0)) -> 0
A16: =IF(ISNA(AZ16),"",AZ16) | F16: =BA16-BB16 -> 0 | I16: =BF16-BG16 -> 0 | L16: =BK16-BL16 -> 0 | O16: =BP16-BQ16 -> 0 | R16: =BU16-BV16 -> 0 | U16: =BZ16-CA16 -> 0 | X16: =CE16-CF16 -> 0 | AB16: =SUM(F16,I16,L16,O16,R16,U16,X16) -> 0 | AE16: =SUMIF($BC$1:$CI$1,AE$1,$BC16:$CI16)+AD16 -> 0 | AG16: =SUMIF($BC$1:$CI$1,AG$1,$BC16:$CI16)+AF16 -> 0 | AI16: =SUMIF($BC$1:$CI$1,AI$1,$BC16:$CI16)+AH16 -> 0 | AK16: =SUMIF($BC$1:$CI$1,AK$1,$BC16:$CI16)+AJ16 -> 0 | AM16: =SUMIF($BC$1:$CI$1,AM$1,$BC16:$CI16)+AL16 -> 0 | AO16: =SUMIF($BC$1:$CI$1,AO$1,$BC16:$CI16)+AN16 -> 0 | AP16: =CK16 -> 0 | AT16: =AE16+AG16+AI16+AK16+AM16+AO16+SUM(AQ16:AS16) -> 0 | AZ16: =VLOOKUP(C16,Employees!D:I,6,FALSE) -> #N/A | BA16: =IF(ISBLANK(D16),0,(E16-D16)*24) -> 0 | BB16: =IF(BA16>$AY$1,1,IF(BA16>=$AX$1,0.5,0)) -> 0 | BC16: =BA16-BB16-BD16-BE16 -> 0 | BD16: =IF(AND(E16>$AV$1, D16<$AW$1),(MIN(E16,$AW$1)-MAX(D16,$AV$1))*24,0) -> 0 | BE16: =IF(E16>$AW$1,(E16-MAX(D16,$AW$1))*24,0) -> 0 | BF16: =IF(ISBLANK(G16),0,(H16-G16)*24) -> 0 | BG16: =IF(BF16>$AY$1,1,IF(BF16>=$AX$1,0.5,0)) -> 0 | BH16: =BF16-BG16-BI16-BJ16 -> 0 | BI16: =IF(AND(H16>$AV$1,G16<$AW$1),(MIN(H16,$AW$1)-MAX(G16,$AV$1))*24,0) -> 0 | BJ16: =IF(H16>$AW$1,(H16-MAX(G16,$AW$1))*24,0) -> 0 | BK16: =IF(ISBLANK(J16),0,(K16-J16)*24) -> 0 | BL16: =IF(BK16>$AY$1,1,IF(BK16>=$AX$1,0.5,0)) -> 0 | BM16: =BK16-BL16-BN16-BO16 -> 0 | BN16: =IF(AND(K16>$AV$1, J16<$AW$1),(MIN(K16,$AW$1)-MAX(J16,$AV$1))*24,0) -> 0 | BO16: =IF(K16>$AW$1,(K16-MAX(J16,$AW$1))*24,0) -> 0 | BP16: =IF(ISBLANK(M16),0,(N16-M16)*24) -> 0 | BQ16: =IF(BP16>$AY$1,1,IF(BP16>=$AX$1,0.5,0)) -> 0 | BR16: =BP16-BQ16-BS16-BT16 -> 0 | BS16: =IF(AND(N16>$AV$1, M16<$AW$1),(MIN(N16,$AW$1)-MAX(M16,$AV$1))*24,0) -> 0 | BT16: =IF(N16>$AW$1,(N16-MAX(M16,$AW$1))*24,0) -> 0 | BU16: =IF(ISBLANK(P16),0,(Q16-P16)*24) -> 0 | BV16: =IF(BU16>$AY$1,1,IF(BU16>=$AX$1,0.5,0)) -> 0 | BW16: =BU16-BV16-BX16-BY16 -> 0 | BX16: =IF(AND(Q16>$AV$1, P16<$AW$1),(MIN(Q16,$AW$1)-MAX(P16,$AV$1))*24,0) -> 0 | BY16: =IF(Q16>$AW$1,(Q16-MAX(P16,$AW$1))*24,0) -> 0 | BZ16: =IF(ISBLANK(S16),0,(T16-S16)*24) -> 0 | CA16: =IF(BZ16>$AY$1,1,IF(BZ16>=$AX$1,0.5,0)) -> 0 | CB16: =BZ16-CA16-CC16-CD16 -> 0 | CC16: =IF(AND(T16>$AV$1, S16<$AW$1),(MIN(T16,$AW$1)-MAX(S16,$AV$1))*24,0) -> 0 | CD16: =IF(T16>$AW$1,(T16-MAX(S16,$AW$1))*24,0) -> 0 | CE16: =IF(ISBLANK(V16),0,(W16-V16)*24) -> 0 | CF16: =IF(CE16>$AY$1,1,IF(CE16>=$AX$1,0.5,0)) -> 0 | CG16: =CE16-CF16-CH16-CI16 -> 0 | CH16: =IF(AND(W16>$AV$1, V16<$AW$1),(MIN(W16,$AW$1)-MAX(V16,$AV$1))*24,0) -> 0 | CI16: =IF(W16>$AW$1,(W16-MAX(V16,$AW$1))*24,0) -> 0 | CK16: =SUM(IF(F16>0,1,0),IF(I16>0,1,0),IF(L16>0,1,0),IF(O16>0,1,0),IF(R16>0,1,0),IF(U16>0,1,0),IF(X16>0,1,0)) -> 0
A17: =IF(ISNA(AZ17),"",AZ17) | F17: =BA17-BB17 -> 0 | I17: =BF17-BG17 -> 0 | L17: =BK17-BL17 -> 0 | O17: =BP17-BQ17 -> 0 | R17: =BU17-BV17 -> 0 | U17: =BZ17-CA17 -> 0 | X17: =CE17-CF17 -> 0 | AB17: =SUM(F17,I17,L17,O17,R17,U17,X17) -> 0 | AE17: =SUMIF($BC$1:$CI$1,AE$1,$BC17:$CI17)+AD17 -> 0 | AG17: =SUMIF($BC$1:$CI$1,AG$1,$BC17:$CI17)+AF17 -> 0 | AI17: =SUMIF($BC$1:$CI$1,AI$1,$BC17:$CI17)+AH17 -> 0 | AK17: =SUMIF($BC$1:$CI$1,AK$1,$BC17:$CI17)+AJ17 -> 0 | AM17: =SUMIF($BC$1:$CI$1,AM$1,$BC17:$CI17)+AL17 -> 0 | AO17: =SUMIF($BC$1:$CI$1,AO$1,$BC17:$CI17)+AN17 -> 0 | AP17: =CK17 -> 0 | AT17: =AE17+AG17+AI17+AK17+AM17+AO17+SUM(AQ17:AS17) -> 0 | AZ17: =VLOOKUP(C17,Employees!D:I,6,FALSE) -> #N/A | BA17: =IF(ISBLANK(D17),0,(E17-D17)*24) -> 0 | BB17: =IF(BA17>$AY$1,1,IF(BA17>=$AX$1,0.5,0)) -> 0 | BC17: =BA17-BB17-BD17-BE17 -> 0 | BD17: =IF(AND(E17>$AV$1, D17<$AW$1),(MIN(E17,$AW$1)-MAX(D17,$AV$1))*24,0) -> 0 | BE17: =IF(E17>$AW$1,(E17-MAX(D17,$AW$1))*24,0) -> 0 | BF17: =IF(ISBLANK(G17),0,(H17-G17)*24) -> 0 | BG17: =IF(BF17>$AY$1,1,IF(BF17>=$AX$1,0.5,0)) -> 0 | BH17: =BF17-BG17-BI17-BJ17 -> 0 | BI17: =IF(AND(H17>$AV$1,G17<$AW$1),(MIN(H17,$AW$1)-MAX(G17,$AV$1))*24,0) -> 0 | BJ17: =IF(H17>$AW$1,(H17-MAX(G17,$AW$1))*24,0) -> 0 | BK17: =IF(ISBLANK(J17),0,(K17-J17)*24) -> 0 | BL17: =IF(BK17>$AY$1,1,IF(BK17>=$AX$1,0.5,0)) -> 0 | BM17: =BK17-BL17-BN17-BO17 -> 0 | BN17: =IF(AND(K17>$AV$1, J17<$AW$1),(MIN(K17,$AW$1)-MAX(J17,$AV$1))*24,0) -> 0 | BO17: =IF(K17>$AW$1,(K17-MAX(J17,$AW$1))*24,0) -> 0 | BP17: =IF(ISBLANK(M17),0,(N17-M17)*24) -> 0 | BQ17: =IF(BP17>$AY$1,1,IF(BP17>=$AX$1,0.5,0)) -> 0 | BR17: =BP17-BQ17-BS17-BT17 -> 0 | BS17: =IF(AND(N17>$AV$1, M17<$AW$1),(MIN(N17,$AW$1)-MAX(M17,$AV$1))*24,0) -> 0 | BT17: =IF(N17>$AW$1,(N17-MAX(M17,$AW$1))*24,0) -> 0 | BU17: =IF(ISBLANK(P17),0,(Q17-P17)*24) -> 0 | BV17: =IF(BU17>$AY$1,1,IF(BU17>=$AX$1,0.5,0)) -> 0 | BW17: =BU17-BV17-BX17-BY17 -> 0 | BX17: =IF(AND(Q17>$AV$1, P17<$AW$1),(MIN(Q17,$AW$1)-MAX(P17,$AV$1))*24,0) -> 0 | BY17: =IF(Q17>$AW$1,(Q17-MAX(P17,$AW$1))*24,0) -> 0 | BZ17: =IF(ISBLANK(S17),0,(T17-S17)*24) -> 0 | CA17: =IF(BZ17>$AY$1,1,IF(BZ17>=$AX$1,0.5,0)) -> 0 | CB17: =BZ17-CA17-CC17-CD17 -> 0 | CC17: =IF(AND(T17>$AV$1, S17<$AW$1),(MIN(T17,$AW$1)-MAX(S17,$AV$1))*24,0) -> 0 | CD17: =IF(T17>$AW$1,(T17-MAX(S17,$AW$1))*24,0) -> 0 | CE17: =IF(ISBLANK(V17),0,(W17-V17)*24) -> 0 | CF17: =IF(CE17>$AY$1,1,IF(CE17>=$AX$1,0.5,0)) -> 0 | CG17: =CE17-CF17-CH17-CI17 -> 0 | CH17: =IF(AND(W17>$AV$1, V17<$AW$1),(MIN(W17,$AW$1)-MAX(V17,$AV$1))*24,0) -> 0 | CI17: =IF(W17>$AW$1,(W17-MAX(V17,$AW$1))*24,0) -> 0 | CK17: =SUM(IF(F17>0,1,0),IF(I17>0,1,0),IF(L17>0,1,0),IF(O17>0,1,0),IF(R17>0,1,0),IF(U17>0,1,0),IF(X17>0,1,0)) -> 0
A18: =IF(ISNA(AZ18),"",AZ18) | F18: =BA18-BB18 -> 0 | I18: =BF18-BG18 -> 0 | L18: =BK18-BL18 -> 0 | O18: =BP18-BQ18 -> 0 | R18: =BU18-BV18 -> 0 | U18: =BZ18-CA18 -> 0 | X18: =CE18-CF18 -> 0 | AB18: =SUM(F18,I18,L18,O18,R18,U18,X18) -> 0 | AE18: =SUMIF($BC$1:$CI$1,AE$1,$BC18:$CI18)+AD18 -> 0 | AG18: =SUMIF($BC$1:$CI$1,AG$1,$BC18:$CI18)+AF18 -> 0 | AI18: =SUMIF($BC$1:$CI$1,AI$1,$BC18:$CI18)+AH18 -> 0 | AK18: =SUMIF($BC$1:$CI$1,AK$1,$BC18:$CI18)+AJ18 -> 0 | AM18: =SUMIF($BC$1:$CI$1,AM$1,$BC18:$CI18)+AL18 -> 0 | AO18: =SUMIF($BC$1:$CI$1,AO$1,$BC18:$CI18)+AN18 -> 0 | AP18: =CK18 -> 0 | AT18: =AE18+AG18+AI18+AK18+AM18+AO18+SUM(AQ18:AS18) -> 0 | AZ18: =VLOOKUP(C18,Employees!D:I,6,FALSE) -> #N/A | BA18: =IF(ISBLANK(D18),0,(E18-D18)*24) -> 0 | BB18: =IF(BA18>$AY$1,1,IF(BA18>=$AX$1,0.5,0)) -> 0 | BC18: =BA18-BB18-BD18-BE18 -> 0 | BD18: =IF(AND(E18>$AV$1, D18<$AW$1),(MIN(E18,$AW$1)-MAX(D18,$AV$1))*24,0) -> 0 | BE18: =IF(E18>$AW$1,(E18-MAX(D18,$AW$1))*24,0) -> 0 | BF18: =IF(ISBLANK(G18),0,(H18-G18)*24) -> 0 | BG18: =IF(BF18>$AY$1,1,IF(BF18>=$AX$1,0.5,0)) -> 0 | BH18: =BF18-BG18-BI18-BJ18 -> 0 | BI18: =IF(AND(H18>$AV$1,G18<$AW$1),(MIN(H18,$AW$1)-MAX(G18,$AV$1))*24,0) -> 0 | BJ18: =IF(H18>$AW$1,(H18-MAX(G18,$AW$1))*24,0) -> 0 | BK18: =IF(ISBLANK(J18),0,(K18-J18)*24) -> 0 | BL18: =IF(BK18>$AY$1,1,IF(BK18>=$AX$1,0.5,0)) -> 0 | BM18: =BK18-BL18-BN18-BO18 -> 0 | BN18: =IF(AND(K18>$AV$1, J18<$AW$1),(MIN(K18,$AW$1)-MAX(J18,$AV$1))*24,0) -> 0 | BO18: =IF(K18>$AW$1,(K18-MAX(J18,$AW$1))*24,0) -> 0 | BP18: =IF(ISBLANK(M18),0,(N18-M18)*24) -> 0 | BQ18: =IF(BP18>$AY$1,1,IF(BP18>=$AX$1,0.5,0)) -> 0 | BR18: =BP18-BQ18-BS18-BT18 -> 0 | BS18: =IF(AND(N18>$AV$1, M18<$AW$1),(MIN(N18,$AW$1)-MAX(M18,$AV$1))*24,0) -> 0 | BT18: =IF(N18>$AW$1,(N18-MAX(M18,$AW$1))*24,0) -> 0 | BU18: =IF(ISBLANK(P18),0,(Q18-P18)*24) -> 0 | BV18: =IF(BU18>$AY$1,1,IF(BU18>=$AX$1,0.5,0)) -> 0 | BW18: =BU18-BV18-BX18-BY18 -> 0 | BX18: =IF(AND(Q18>$AV$1, P18<$AW$1),(MIN(Q18,$AW$1)-MAX(P18,$AV$1))*24,0) -> 0 | BY18: =IF(Q18>$AW$1,(Q18-MAX(P18,$AW$1))*24,0) -> 0 | BZ18: =IF(ISBLANK(S18),0,(T18-S18)*24) -> 0 | CA18: =IF(BZ18>$AY$1,1,IF(BZ18>=$AX$1,0.5,0)) -> 0 | CB18: =BZ18-CA18-CC18-CD18 -> 0 | CC18: =IF(AND(T18>$AV$1, S18<$AW$1),(MIN(T18,$AW$1)-MAX(S18,$AV$1))*24,0) -> 0 | CD18: =IF(T18>$AW$1,(T18-MAX(S18,$AW$1))*24,0) -> 0 | CE18: =IF(ISBLANK(V18),0,(W18-V18)*24) -> 0 | CF18: =IF(CE18>$AY$1,1,IF(CE18>=$AX$1,0.5,0)) -> 0 | CG18: =CE18-CF18-CH18-CI18 -> 0 | CH18: =IF(AND(W18>$AV$1, V18<$AW$1),(MIN(W18,$AW$1)-MAX(V18,$AV$1))*24,0) -> 0 | CI18: =IF(W18>$AW$1,(W18-MAX(V18,$AW$1))*24,0) -> 0 | CK18: =SUM(IF(F18>0,1,0),IF(I18>0,1,0),IF(L18>0,1,0),IF(O18>0,1,0),IF(R18>0,1,0),IF(U18>0,1,0),IF(X18>0,1,0)) -> 0
... A100: =IF(ISNA(AZ100),"",AZ100) | F100: =BA100-BB100 -> 0 | I100: =BF100-BG100 -> 0 | L100: =BK100-BL100 -> 0 | O100: =BP100-BQ100 -> 0 | R100: =BU100-BV100 -> 0 | U100: =BZ100-CA100 -> 0 | X100: =CE100-CF100 -> 0 | AB100: =SUM(F100,I100,L100,O100,R100,U100,X100) -> 0 | AE100: =SUMIF($BC$1:$CI$1,AE$1,$BC100:$CI100)+AD100 -> 0 | AG100: =SUMIF($BC$1:$CI$1,AG$1,$BC100:$CI100)+AF100 -> 0 | AI100: =SUMIF($BC$1:$CI$1,AI$1,$BC100:$CI100)+AH100 -> 0 | AK100: =SUMIF($BC$1:$CI$1,AK$1,$BC100:$CI100)+AJ100 -> 0 | AM100: =SUMIF($BC$1:$CI$1,AM$1,$BC100:$CI100)+AL100 -> 0 | AO100: =SUMIF($BC$1:$CI$1,AO$1,$BC100:$CI100)+AN100 -> 0 | AP100: =CK100 -> 0 | AT100: =AE100+AG100+AI100+AK100+AM100+AO100+SUM(AQ100:AS100) -> 0 | AZ100: =VLOOKUP(C100,Employees!D:I,6,FALSE) -> #N/A | BA100: =IF(ISBLANK(D100),0,(E100-D100)*24) -> 0 | BB100: =IF(BA100>$AY$1,1,IF(BA100>=$AX$1,0.5,0)) -> 0 | BC100: =BA100-BB100-BD100-BE100 -> 0 | BD100: =IF(AND(E100>$AV$1, D100<$AW$1),(MIN(E100,$AW$1)-MAX(D100,$AV$1))*24,0) -> 0 | BE100: =IF(E100>$AW$1,(E100-MAX(D100,$AW$1))*24,0) -> 0 | BF100: =IF(ISBLANK(G100),0,(H100-G100)*24) -> 0 | BG100: =IF(BF100>$AY$1,1,IF(BF100>=$AX$1,0.5,0)) -> 0 | BH100: =BF100-BG100-BI100-BJ100 -> 0 | BI100: =IF(AND(H100>$AV$1,G100<$AW$1),(MIN(H100,$AW$1)-MAX(G100,$AV$1))*24,0) -> 0 | BJ100: =IF(H100>$AW$1,(H100-MAX(G100,$AW$1))*24,0) -> 0 | BK100: =IF(ISBLANK(J100),0,(K100-J100)*24) -> 0 | BL100: =IF(BK100>$AY$1,1,IF(BK100>=$AX$1,0.5,0)) -> 0 | BM100: =BK100-BL100-BN100-BO100 -> 0 | BN100: =IF(AND(K100>$AV$1, J100<$AW$1),(MIN(K100,$AW$1)-MAX(J100,$AV$1))*24,0) -> 0 | BO100: =IF(K100>$AW$1,(K100-MAX(J100,$AW$1))*24,0) -> 0 | BP100: =IF(ISBLANK(M100),0,(N100-M100)*24) -> 0 | BQ100: =IF(BP100>$AY$1,1,IF(BP100>=$AX$1,0.5,0)) -> 0 | BR100: =BP100-BQ100-BS100-BT100 -> 0 | BS100: =IF(AND(N100>$AV$1, M100<$AW$1),(MIN(N100,$AW$1)-MAX(M100,$AV$1))*24,0) -> 0 | BT100: =IF(N100>$AW$1,(N100-MAX(M100,$AW$1))*24,0) -> 0 | BU100: =IF(ISBLANK(P100),0,(Q100-P100)*24) -> 0 | BV100: =IF(BU100>$AY$1,1,IF(BU100>=$AX$1,0.5,0)) -> 0 | BW100: =BU100-BV100-BX100-BY100 -> 0 | BX100: =IF(AND(Q100>$AV$1, P100<$AW$1),(MIN(Q100,$AW$1)-MAX(P100,$AV$1))*24,0) -> 0 | BY100: =IF(Q100>$AW$1,(Q100-MAX(P100,$AW$1))*24,0) -> 0 | BZ100: =IF(ISBLANK(S100),0,(T100-S100)*24) -> 0 | CA100: =IF(BZ100>$AY$1,1,IF(BZ100>=$AX$1,0.5,0)) -> 0 | CB100: =BZ100-CA100-CC100-CD100 -> 0 | CC100: =IF(AND(T100>$AV$1, S100<$AW$1),(MIN(T100,$AW$1)-MAX(S100,$AV$1))*24,0) -> 0 | CD100: =IF(T100>$AW$1,(T100-MAX(S100,$AW$1))*24,0) -> 0 | CE100: =IF(ISBLANK(V100),0,(W100-V100)*24) -> 0 | CF100: =IF(CE100>$AY$1,1,IF(CE100>=$AX$1,0.5,0)) -> 0 | CG100: =CE100-CF100-CH100-CI100 -> 0 | CH100: =IF(AND(W100>$AV$1, V100<$AW$1),(MIN(W100,$AW$1)-MAX(V100,$AV$1))*24,0) -> 0 | CI100: =IF(W100>$AW$1,(W100-MAX(V100,$AW$1))*24,0) -> 0 | CK100: =SUM(IF(F100>0,1,0),IF(I100>0,1,0),IF(L100>0,1,0),IF(O100>0,1,0),IF(R100>0,1,0),IF(U100>0,1,0),IF(X100>0,1,0)) -> 0

Sheet Timesheet
B1: Employee ID | C1: First Name | D1: Last Name | E1: Date of Birth | F1: =_xlfn.CONCAT("Age on ",TEXT( 'Week 1 Roster'!$D$1-1,"dd/mm/yy")) -> Age on 18/01/26 | G1: =_xlfn.CONCAT("Age on ",TEXT( 'Week 1 Roster'!$D$1+14,"dd/mm/yy")) -> Age on 02/02/26 | H1: Update Wage | I1: Hour Threshold | J1: Labour Hire | K1: Store | L1: Operator | M1: Ord | N1: Sat | O1: Sun | P1: Pub | Q1: Eve 1 | R1: Eve 2 | S1: No. of Shifts | T1: Personal Leave | U1: Annual Leave | V1: Unpaid Leave | W1: Total | Y1: Ord | Z1: Sat | AA1: Sun | AB1: Pub | AC1: Eve 1 | AD1: Eve 2 | AE1: No. of Shifts | AF1: Personal Leave | AG1: Annual Leave | AH1: Unpaid Leave | AI1: Week1 Total | AK1: Ord | AL1: Sat | AM1: Sun | AN1: Pub | AO1: Eve 1 | AP1: Eve 2 | AQ1: No. of Shifts | AR1: Personal Leave | AS1: Annual Leave | AT1: Unpaid Leave | AU1: Week 2 Total | AW1: ='Week 1 Roster'!AZ1 -> Employee ID | AX1: ='Week 2 Roster'!AZ1 -> Employee ID
A2: {=_xlfn.NUMBERVALUE(INDIRECT(TEXT(MIN(IF(($AW$2:$AX$300<>"")*(COUNTIF($B$1:B1,$AW$2:$AX$300)=0),ROW($2:$300)*100+COLUMN($AW:$AX),7^8)),"R0C00"),)&"")} -> 10306 | B2: =IF(A2=0,"",_xlfn.NUMBERVALUE(A2)) -> 10306 | C2: =IF($A2=0,"",VLOOKUP($B2,Employees!$A:$G,2,FALSE)) -> Thuy An | D2: =IF($A2=0,"",VLOOKUP($B2,Employees!$A:$G,3,FALSE)) -> Pham | E2: =IF($A2=0,"",VLOOKUP($B2,Employees!$A:$G,5,FALSE)) -> 37927 | F2: =IF($E2="","",ROUNDDOWN(YEARFRAC($E2, 'Week 1 Roster'!$D$1-1, 1), 0)) -> 22 | G2: =IF($E2="","",ROUNDDOWN(YEARFRAC($E2, 'Week 1 Roster'!$D$1+14, 1), 0)) -> 22 | H2: =IF($E2="","",IF(AND(F2<21,F2<>G2),TRUE,FALSE)) -> FALSE | I2: =IF($A2=0,"",VLOOKUP($B2,Employees!$A:$G,6,FALSE)) -> 76 | J2: =IF($A2=0,"",VLOOKUP($B2,Employees!$A:$G,7,FALSE)) -> GCM | K2: =IF($A2=0,"",IF(ISNA(VLOOKUP(A2,'Week 1 Roster'!A:C,2,0)),VLOOKUP(A2,'Week 2 Roster'!A:C,2,0),VLOOKUP(A2,'Week 1 Roster'!A:C,2,0))) -> The Star | L2: =IF($A2=0,"",VLOOKUP(K2,Stores!A:B,2,0)) -> Winlada | M2: =Y2+AK2 -> 23.85 | N2: =Z2+AL2 -> 18.166667 | O2: =AA2+AM2 -> 0 | P2: =AB2+AN2 -> 4.0166667 | Q2: =AC2+AO2 -> 3.6 | R2: =AD2+AP2 -> 0 | S2: =AE2+AQ2 -> 7 | T2: =AF2+AR2 -> 0 | ... V2: =AH2+AT2 -> 0 | W2: =SUM(M2:R2,T2:V2) -> 49.633333 | Y2: =IF($A2=0,0,SUMIF('Week 1 Roster'!$AZ:$AZ,$B2,'Week 1 Roster'!$AE:$AE)) -> 15.283333 | Z2: =IF($A2=0,0,SUMIF('Week 1 Roster'!$AZ:$AZ,$B2,'Week 1 Roster'!$AG:$AG)) -> 8.8 | AA2: =IF($A2=0,0,SUMIF('Week 1 Roster'!$AZ:$AZ,$B2,'Week 1 Roster'!$AI:$AI)) -> 0 | AB2: =IF($A2=0,0,SUMIF('Week 1 Roster'!$AZ:$AZ,$B2,'Week 1 Roster'!$AK:$AK)) -> 0 | AC2: =IF($A2=0,0,SUMIF('Week 1 Roster'!$AZ:$AZ,$B2,'Week 1 Roster'!$AM:$AM)) -> 1.4 | AD2: =IF($A2=0,0,SUMIF('Week 1 Roster'!$AZ:$AZ,$B2,'Week 1 Roster'!$AO:$AO)) -> 0 | AE2: =IF($A2=0,0,SUMIF('Week 1 Roster'!$AZ:$AZ,$B2,'Week 1 Roster'!$AP:$AP)) -> 3 | AF2: =IF($A2=0,0,SUMIF('Week 1 Roster'!$AZ:$AZ,$B2,'Week 1 Roster'!$AQ:$AQ)) -> 0 | AG2: =IF($A2=0,0,SUMIF('Week 1 Roster'!$AZ:$AZ,$B2,'Week 1 Roster'!$AR:$AR)) -> 0 | AH2: =IF($A2=0,0,SUMIF('Week 1 Roster'!$AZ:$AZ,$B2,'Week 1 Roster'!$AS:$AS)) -> 0 | AI2: =SUM(Y2:AD2,AF2:AH2) -> 25.483333 | AK2: =IF($A2=0,0,SUMIF('Week 2 Roster'!$AZ:$AZ,$B2,'Week 2 Roster'!$AE:$AE)) -> 8.5666667 | AL2: =IF($A2=0,0,SUMIF('Week 2 Roster'!$AZ:$AZ,$B2,'Week 2 Roster'!$AG:$AG)) -> 9.3666667 | AM2: =IF($A2=0,0,SUMIF('Week 2 Roster'!$AZ:$AZ,$B2,'Week 2 Roster'!$AI:$AI)) -> 0 | AN2: =IF($A2=0,0,SUMIF('Week 2 Roster'!$AZ:$AZ,$B2,'Week 2 Roster'!$AK:$AK)) -> 4.0166667 | AO2: =IF($A2=0,0,SUMIF('Week 2 Roster'!$AZ:$AZ,$B2,'Week 2 Roster'!$AM:$AM)) -> 2.2 | AP2: =IF($A2=0,0,SUMIF('Week 2 Roster'!$AZ:$AZ,$B2,'Week 2 Roster'!$AO:$AO)) -> 0 | AQ2: =IF($A2=0,0,SUMIF('Week 2 Roster'!$AZ:$AZ,$B2,'Week 2 Roster'!$AP:$AP)) -> 4 | AR2: =IF($A2=0,0,SUMIF('Week 2 Roster'!$AZ:$AZ,$B2,'Week 2 Roster'!$AQ:$AQ)) -> 0 | AS2: =IF($A2=0,0,SUMIF('Week 2 Roster'!$AZ:$AZ,$B2,'Week 2 Roster'!$AR:$AR)) -> 0 | AT2: =IF($A2=0,0,SUMIF('Week 2 Roster'!$AZ:$AZ,$B2,'Week 2 Roster'!$AS:$AS)) -> 0 | AU2: =SUM(AK2:AP2,AR2:AT2) -> 24.15 | AW2: ='Week 1 Roster'!A2 -> 10306 | AX2: ='Week 2 Roster'!A2 -> 10306
A3: {=_xlfn.NUMBERVALUE(INDIRECT(TEXT(MIN(IF(($AW$2:$AX$300<>"")*(COUNTIF($B$1:B2,$AW$2:$AX$300)=0),ROW($2:$300)*100+COLUMN($AW:$AX),7^8)),"R0C00"),)&"")} -> 10386 | B3: =IF(A3=0,"",_xlfn.NUMBERVALUE(A3)) -> 10386 | C3: =IF($A3=0,"",VLOOKUP($B3,Employees!$A:$G,2,FALSE)) -> Thesya | D3: =IF($A3=0,"",VLOOKUP($B3,Employees!$A:$G,3,FALSE)) -> Handoko | E3: =IF($A3=0,"",VLOOKUP($B3,Employees!$A:$G,5,FALSE)) -> 35963 | F3: =IF($E3="","",ROUNDDOWN(YEARFRAC($E3, 'Week 1 Roster'!$D$1-1, 1), 0)) -> 27 | G3: =IF($E3="","",ROUNDDOWN(YEARFRAC($E3, 'Week 1 Roster'!$D$1+14, 1), 0)) -> 27 | H3: =IF($E3="","",IF(AND(F3<21,F3<>G3),TRUE,FALSE)) -> FALSE | I3: =IF($A3=0,"",VLOOKUP($B3,Employees!$A:$G,6,FALSE)) -> 76 | J3: =IF($A3=0,"",VLOOKUP($B3,Employees!$A:$G,7,FALSE)) -> SS | K3: =IF($A3=0,"",IF(ISNA(VLOOKUP(A3,'Week 1 Roster'!A:C,2,0)),VLOOKUP(A3,'Week 2 Roster'!A:C,2,0),VLOOKUP(A3,'Week 1 Roster'!A:C,2,0))) -> The Star | L3: =IF($A3=0,"",VLOOKUP(K3,Stores!A:B,2,0)) -> Winlada | M3: =Y3+AK3 -> 42.416667 | N3: =Z3+AL3 -> 14.6 | O3: =AA3+AM3 -> 8.25 | P3: =AB3+AN3 -> 4.5333333 | Q3: =AC3+AO3 -> 0 | R3: =AD3+AP3 -> 0 | S3: =AE3+AQ3 -> 10 | T3: =AF3+AR3 -> 0 | ... V3: =AH3+AT3 -> 0 | W3: =SUM(M3:R3,T3:V3) -> 69.8 | Y3: =IF($A3=0,0,SUMIF('Week 1 Roster'!$AZ:$AZ,$B3,'Week 1 Roster'!$AE:$AE)) -> 18.283333 | Z3: =IF($A3=0,0,SUMIF('Week 1 Roster'!$AZ:$AZ,$B3,'Week 1 Roster'!$AG:$AG)) -> 8.5 | AA3: =IF($A3=0,0,SUMIF('Week 1 Roster'!$AZ:$AZ,$B3,'Week 1 Roster'!$AI:$AI)) -> 0 | AB3: =IF($A3=0,0,SUMIF('Week 1 Roster'!$AZ:$AZ,$B3,'Week 1 Roster'!$AK:$AK)) -> 0 | AC3: =IF($A3=0,0,SUMIF('Week 1 Roster'!$AZ:$AZ,$B3,'Week 1 Roster'!$AM:$AM)) -> 0 | AD3: =IF($A3=0,0,SUMIF('Week 1 Roster'!$AZ:$AZ,$B3,'Week 1 Roster'!$AO:$AO)) -> 0 | AE3: =IF($A3=0,0,SUMIF('Week 1 Roster'!$AZ:$AZ,$B3,'Week 1 Roster'!$AP:$AP)) -> 4 | AF3: =IF($A3=0,0,SUMIF('Week 1 Roster'!$AZ:$AZ,$B3,'Week 1 Roster'!$AQ:$AQ)) -> 0 | AG3: =IF($A3=0,0,SUMIF('Week 1 Roster'!$AZ:$AZ,$B3,'Week 1 Roster'!$AR:$AR)) -> 0 | AH3: =IF($A3=0,0,SUMIF('Week 1 Roster'!$AZ:$AZ,$B3,'Week 1 Roster'!$AS:$AS)) -> 0 | AI3: =SUM(Y3:AD3,AF3:AH3) -> 26.783333 | AK3: =IF($A3=0,0,SUMIF('Week 2 Roster'!$AZ:$AZ,$B3,'Week 2 Roster'!$AE:$AE)) -> 24.133333 | AL3: =IF($A3=0,0,SUMIF('Week 2 Roster'!$AZ:$AZ,$B3,'Week 2 Roster'!$AG:$AG)) -> 6.1 | AM3: =IF($A3=0,0,SUMIF('Week 2 Roster'!$AZ:$AZ,$B3,'Week 2 Roster'!$AI:$AI)) -> 8.25 | AN3: =IF($A3=0,0,SUMIF('Week 2 Roster'!$AZ:$AZ,$B3,'Week 2 Roster'!$AK:$AK)) -> 4.5333333 | AO3: =IF($A3=0,0,SUMIF('Week 2 Roster'!$AZ:$AZ,$B3,'Week 2 Roster'!$AM:$AM)) -> 0 | AP3: =IF($A3=0,0,SUMIF('Week 2 Roster'!$AZ:$AZ,$B3,'Week 2 Roster'!$AO:$AO)) -> 0 | AQ3: =IF($A3=0,0,SUMIF('Week 2 Roster'!$AZ:$AZ,$B3,'Week 2 Roster'!$AP:$AP)) -> 6 | AR3: =IF($A3=0,0,SUMIF('Week 2 Roster'!$AZ:$AZ,$B3,'Week 2 Roster'!$AQ:$AQ)) -> 0 | AS3: =IF($A3=0,0,SUMIF('Week 2 Roster'!$AZ:$AZ,$B3,'Week 2 Roster'!$AR:$AR)) -> 0 | AT3: =IF($A3=0,0,SUMIF('Week 2 Roster'!$AZ:$AZ,$B3,'Week 2 Roster'!$AS:$AS)) -> 0 | AU3: =SUM(AK3:AP3,AR3:AT3) -> 43.016667 | AW3: ='Week 1 Roster'!A3 -> 10386 | AX3: ='Week 2 Roster'!A3 -> 10386
A4: {=_xlfn.NUMBERVALUE(INDIRECT(TEXT(MIN(IF(($AW$2:$AX$300<>"")*(COUNTIF($B$1:B3,$AW$2:$AX$300)=0),ROW($2:$300)*100+COLUMN($AW:$AX),7^8)),"R0C00"),)&"")} -> 10376 | B4: =IF(A4=0,"",_xlfn.NUMBERVALUE(A4)) -> 10376 | C4: =IF($A4=0,"",VLOOKUP($B4,Employees!$A:$G,2,FALSE)) -> Cong Hieu | D4: =IF($A4=0,"",VLOOKUP($B4,Employees!$A:$G,3,FALSE)) -> Le | E4: =IF($A4=0,"",VLOOKUP($B4,Employees!$A:$G,5,FALSE)) -> 38021 | F4: =IF($E4="","",ROUNDDOWN(YEARFRAC($E4, 'Week 1 Roster'!$D$1-1, 1), 0)) -> 21 | G4: =IF($E4="","",ROUNDDOWN(YEARFRAC($E4, 'Week 1 Roster'!$D$1+14, 1), 0)) -> 21 | H4: =IF($E4="","",IF(AND(F4<21,F4<>G4),TRUE,FALSE)) -> FALSE | I4: =IF($A4=0,"",VLOOKUP($B4,Employees!$A:$G,6,FALSE)) -> 48 | J4: =IF($A4=0,"",VLOOKUP($B4,Employees!$A:$G,7,FALSE)) -> SS | K4: =IF($A4=0,"",IF(ISNA(VLOOKUP(A4,'Week 1 Roster'!A:C,2,0)),VLOOKUP(A4,'Week 2 Roster'!A:C,2,0),VLOOKUP(A4,'Week 1 Roster'!A:C,2,0))) -> The Star | L4: =IF($A4=0,"",VLOOKUP(K4,Stores!A:B,2,0)) -> Winlada | M4: =Y4+AK4 -> 16.95 | N4: =Z4+AL4 -> 0 | O4: =AA4+AM4 -> 12.45 | P4: =AB4+AN4 -> 4.4833333 | Q4: =AC4+AO4 -> 2.5166667 | R4: =AD4+AP4 -> 0 | S4: =AE4+AQ4 -> 5 | T4: =AF4+AR4 -> 0 | ... V4: =AH4+AT4 -> 0 | W4: =SUM(M4:R4,T4:V4) -> 36.4 | Y4: =IF($A4=0,0,SUMIF('Week 1 Roster'!$AZ:$AZ,$B4,'Week 1 Roster'!$AE:$AE)) -> 9.9166667 | Z4: =IF($A4=0,0,SUMIF('Week 1 Roster'!$AZ:$AZ,$B4,'Week 1 Roster'!$AG:$AG)) -> 0 | AA4: =IF($A4=0,0,SUMIF('Week 1 Roster'!$AZ:$AZ,$B4,'Week 1 Roster'!$AI:$AI)) -> 12.45 | AB4: =IF($A4=0,0,SUMIF('Week 1 Roster'!$AZ:$AZ,$B4,'Week 1 Roster'!$AK:$AK)) -> 0 | AC4: =IF($A4=0,0,SUMIF('Week 1 Roster'!$AZ:$AZ,$B4,'Week 1 Roster'!$AM:$AM)) -> 2.5166667 | AD4: =IF($A4=0,0,SUMIF('Week 1 Roster'!$AZ:$AZ,$B4,'Week 1 Roster'!$AO:$AO)) -> 0 | AE4: =IF($A4=0,0,SUMIF('Week 1 Roster'!$AZ:$AZ,$B4,'Week 1 Roster'!$AP:$AP)) -> 3 | AF4: =IF($A4=0,0,SUMIF('Week 1 Roster'!$AZ:$AZ,$B4,'Week 1 Roster'!$AQ:$AQ)) -> 0 | AG4: =IF($A4=0,0,SUMIF('Week 1 Roster'!$AZ:$AZ,$B4,'Week 1 Roster'!$AR:$AR)) -> 0 | AH4: =IF($A4=0,0,SUMIF('Week 1 Roster'!$AZ:$AZ,$B4,'Week 1 Roster'!$AS:$AS)) -> 0 | AI4: =SUM(Y4:AD4,AF4:AH4) -> 24.883333 | AK4: =IF($A4=0,0,SUMIF('Week 2 Roster'!$AZ:$AZ,$B4,'Week 2 Roster'!$AE:$AE)) -> 7.0333333 | AL4: =IF($A4=0,0,SUMIF('Week 2 Roster'!$AZ:$AZ,$B4,'Week 2 Roster'!$AG:$AG)) -> 0 | AM4: =IF($A4=0,0,SUMIF('Week 2 Roster'!$AZ:$AZ,$B4,'Week 2 Roster'!$AI:$AI)) -> 0 | AN4: =IF($A4=0,0,SUMIF('Week 2 Roster'!$AZ:$AZ,$B4,'Week 2 Roster'!$AK:$AK)) -> 4.4833333 | AO4: =IF($A4=0,0,SUMIF('Week 2 Roster'!$AZ:$AZ,$B4,'Week 2 Roster'!$AM:$AM)) -> 0 | AP4: =IF($A4=0,0,SUMIF('Week 2 Roster'!$AZ:$AZ,$B4,'Week 2 Roster'!$AO:$AO)) -> 0 | AQ4: =IF($A4=0,0,SUMIF('Week 2 Roster'!$AZ:$AZ,$B4,'Week 2 Roster'!$AP:$AP)) -> 2 | AR4: =IF($A4=0,0,SUMIF('Week 2 Roster'!$AZ:$AZ,$B4,'Week 2 Roster'!$AQ:$AQ)) -> 0 | AS4: =IF($A4=0,0,SUMIF('Week 2 Roster'!$AZ:$AZ,$B4,'Week 2 Roster'!$AR:$AR)) -> 0 | AT4: =IF($A4=0,0,SUMIF('Week 2 Roster'!$AZ:$AZ,$B4,'Week 2 Roster'!$AS:$AS)) -> 0 | AU4: =SUM(AK4:AP4,AR4:AT4) -> 11.516667 | AW4: ='Week 1 Roster'!A4 -> 10376 | AX4: ='Week 2 Roster'!A4 -> 10376
A5: {=_xlfn.NUMBERVALUE(INDIRECT(TEXT(MIN(IF(($AW$2:$AX$300<>"")*(COUNTIF($B$1:B4,$AW$2:$AX$300)=0),ROW($2:$300)*100+COLUMN($AW:$AX),7^8)),"R0C00"),)&"")} -> 210432 | B5: =IF(A5=0,"",_xlfn.NUMBERVALUE(A5)) -> 210432 | C5: =IF($A5=0,"",VLOOKUP($B5,Employees!$A:$G,2,FALSE)) -> Mya | D5: =IF($A5=0,"",VLOOKUP($B5,Employees!$A:$G,3,FALSE)) -> Hmue | E5: =IF($A5=0,"",VLOOKUP($B5,Employees!$A:$G,5,FALSE)) -> 38106 | F5: =IF($E5="","",ROUNDDOWN(YEARFRAC($E5, 'Week 1 Roster'!$D$1-1, 1), 0)) -> 21 | G5: =IF($E5="","",ROUNDDOWN(YEARFRAC($E5, 'Week 1 Roster'!$D$1+14, 1), 0)) -> 21 | H5: =IF($E5="","",IF(AND(F5<21,F5<>G5),TRUE,FALSE)) -> FALSE | I5: =IF($A5=0,"",VLOOKUP($B5,Employees!$A:$G,6,FALSE)) -> 76 | J5: =IF($A5=0,"",VLOOKUP($B5,Employees!$A:$G,7,FALSE)) -> SS | K5: =IF($A5=0,"",IF(ISNA(VLOOKUP(A5,'Week 1 Roster'!A:C,2,0)),VLOOKUP(A5,'Week 2 Roster'!A:C,2,0),VLOOKUP(A5,'Week 1 Roster'!A:C,2,0))) -> The Star | L5: =IF($A5=0,"",VLOOKUP(K5,Stores!A:B,2,0)) -> Winlada | M5: =Y5+AK5 -> 14.2 | N5: =Z5+AL5 -> 0 | O5: =AA5+AM5 -> 14.35 | P5: =AB5+AN5 -> 0 | Q5: =AC5+AO5 -> 3.5666667 | R5: =AD5+AP5 -> 0 | S5: =AE5+AQ5 -> 5 | T5: =AF5+AR5 -> 0 | ... V5: =AH5+AT5 -> 0 | W5: =SUM(M5:R5,T5:V5) -> 32.116667 | Y5: =IF($A5=0,0,SUMIF('Week 1 Roster'!$AZ:$AZ,$B5,'Week 1 Roster'!$AE:$AE)) -> 6.5 | Z5: =IF($A5=0,0,SUMIF('Week 1 Roster'!$AZ:$AZ,$B5,'Week 1 Roster'!$AG:$AG)) -> 0 | AA5: =IF($A5=0,0,SUMIF('Week 1 Roster'!$AZ:$AZ,$B5,'Week 1 Roster'!$AI:$AI)) -> 6.0166667 | AB5: =IF($A5=0,0,SUMIF('Week 1 Roster'!$AZ:$AZ,$B5,'Week 1 Roster'!$AK:$AK)) -> 0 | AC5: =IF($A5=0,0,SUMIF('Week 1 Roster'!$AZ:$AZ,$B5,'Week 1 Roster'!$AM:$AM)) -> 1.1666667 | AD5: =IF($A5=0,0,SUMIF('Week 1 Roster'!$AZ:$AZ,$B5,'Week 1 Roster'!$AO:$AO)) -> 0 | AE5: =IF($A5=0,0,SUMIF('Week 1 Roster'!$AZ:$AZ,$B5,'Week 1 Roster'!$AP:$AP)) -> 2 | AF5: =IF($A5=0,0,SUMIF('Week 1 Roster'!$AZ:$AZ,$B5,'Week 1 Roster'!$AQ:$AQ)) -> 0 | AG5: =IF($A5=0,0,SUMIF('Week 1 Roster'!$AZ:$AZ,$B5,'Week 1 Roster'!$AR:$AR)) -> 0 | AH5: =IF($A5=0,0,SUMIF('Week 1 Roster'!$AZ:$AZ,$B5,'Week 1 Roster'!$AS:$AS)) -> 0 | AI5: =SUM(Y5:AD5,AF5:AH5) -> 13.683333 | AK5: =IF($A5=0,0,SUMIF('Week 2 Roster'!$AZ:$AZ,$B5,'Week 2 Roster'!$AE:$AE)) -> 7.7 | AL5: =IF($A5=0,0,SUMIF('Week 2 Roster'!$AZ:$AZ,$B5,'Week 2 Roster'!$AG:$AG)) -> 0 | AM5: =IF($A5=0,0,SUMIF('Week 2 Roster'!$AZ:$AZ,$B5,'Week 2 Roster'!$AI:$AI)) -> 8.3333333 | AN5: =IF($A5=0,0,SUMIF('Week 2 Roster'!$AZ:$AZ,$B5,'Week 2 Roster'!$AK:$AK)) -> 0 | AO5: =IF($A5=0,0,SUMIF('Week 2 Roster'!$AZ:$AZ,$B5,'Week 2 Roster'!$AM:$AM)) -> 2.4 | AP5: =IF($A5=0,0,SUMIF('Week 2 Roster'!$AZ:$AZ,$B5,'Week 2 Roster'!$AO:$AO)) -> 0 | AQ5: =IF($A5=0,0,SUMIF('Week 2 Roster'!$AZ:$AZ,$B5,'Week 2 Roster'!$AP:$AP)) -> 3 | AR5: =IF($A5=0,0,SUMIF('Week 2 Roster'!$AZ:$AZ,$B5,'Week 2 Roster'!$AQ:$AQ)) -> 0 | AS5: =IF($A5=0,0,SUMIF('Week 2 Roster'!$AZ:$AZ,$B5,'Week 2 Roster'!$AR:$AR)) -> 0 | AT5: =IF($A5=0,0,SUMIF('Week 2 Roster'!$AZ:$AZ,$B5,'Week 2 Roster'!$AS:$AS)) -> 0 | AU5: =SUM(AK5:AP5,AR5:AT5) -> 18.433333 | AW5: ='Week 1 Roster'!A5 -> 210432 | AX5: ='Week 2 Roster'!A5 -> 210432
A6: {=_xlfn.NUMBERVALUE(INDIRECT(TEXT(MIN(IF(($AW$2:$AX$300<>"")*(COUNTIF($B$1:B5,$AW$2:$AX$300)=0),ROW($2:$300)*100+COLUMN($AW:$AX),7^8)),"R0C00"),)&"")} -> 210553 | B6: =IF(A6=0,"",_xlfn.NUMBERVALUE(A6)) -> 210553 | C6: =IF($A6=0,"",VLOOKUP($B6,Employees!$A:$G,2,FALSE)) -> Yunji | D6: =IF($A6=0,"",VLOOKUP($B6,Employees!$A:$G,3,FALSE)) -> Kang | E6: =IF($A6=0,"",VLOOKUP($B6,Employees!$A:$G,5,FALSE)) -> 36234 | F6: =IF($E6="","",ROUNDDOWN(YEARFRAC($E6, 'Week 1 Roster'!$D$1-1, 1), 0)) -> 26 | G6: =IF($E6="","",ROUNDDOWN(YEARFRAC($E6, 'Week 1 Roster'!$D$1+14, 1), 0)) -> 26 | H6: =IF($E6="","",IF(AND(F6<21,F6<>G6),TRUE,FALSE)) -> FALSE | I6: =IF($A6=0,"",VLOOKUP($B6,Employees!$A:$G,6,FALSE)) -> 76 | J6: =IF($A6=0,"",VLOOKUP($B6,Employees!$A:$G,7,FALSE)) -> Win | K6: =IF($A6=0,"",IF(ISNA(VLOOKUP(A6,'Week 1 Roster'!A:C,2,0)),VLOOKUP(A6,'Week 2 Roster'!A:C,2,0),VLOOKUP(A6,'Week 1 Roster'!A:C,2,0))) -> The Star | L6: =IF($A6=0,"",VLOOKUP(K6,Stores!A:B,2,0)) -> Winlada | M6: =Y6+AK6 -> 18.516667 | N6: =Z6+AL6 -> 0 | O6: =AA6+AM6 -> 0 | P6: =AB6+AN6 -> 0 | Q6: =AC6+AO6 -> 2.3666667 | R6: =AD6+AP6 -> 0 | S6: =AE6+AQ6 -> 4 | T6: =AF6+AR6 -> 0 | ... V6: =AH6+AT6 -> 0 | W6: =SUM(M6:R6,T6:V6) -> 20.883333 | Y6: =IF($A6=0,0,SUMIF('Week 1 Roster'!$AZ:$AZ,$B6,'Week 1 Roster'!$AE:$AE)) -> 9.5 | Z6: =IF($A6=0,0,SUMIF('Week 1 Roster'!$AZ:$AZ,$B6,'Week 1 Roster'!$AG:$AG)) -> 0 | AA6: =IF($A6=0,0,SUMIF('Week 1 Roster'!$AZ:$AZ,$B6,'Week 1 Roster'!$AI:$AI)) -> 0 | AB6: =IF($A6=0,0,SUMIF('Week 1 Roster'!$AZ:$AZ,$B6,'Week 1 Roster'!$AK:$AK)) -> 0 | AC6: =IF($A6=0,0,SUMIF('Week 1 Roster'!$AZ:$AZ,$B6,'Week 1 Roster'!$AM:$AM)) -> 1.1666667 | AD6: =IF($A6=0,0,SUMIF('Week 1 Roster'!$AZ:$AZ,$B6,'Week 1 Roster'!$AO:$AO)) -> 0 | AE6: =IF($A6=0,0,SUMIF('Week 1 Roster'!$AZ:$AZ,$B6,'Week 1 Roster'!$AP:$AP)) -> 2 | AF6: =IF($A6=0,0,SUMIF('Week 1 Roster'!$AZ:$AZ,$B6,'Week 1 Roster'!$AQ:$AQ)) -> 0 | AG6: =IF($A6=0,0,SUMIF('Week 1 Roster'!$AZ:$AZ,$B6,'Week 1 Roster'!$AR:$AR)) -> 0 | AH6: =IF($A6=0,0,SUMIF('Week 1 Roster'!$AZ:$AZ,$B6,'Week 1 Roster'!$AS:$AS)) -> 0 | AI6: =SUM(Y6:AD6,AF6:AH6) -> 10.666667 | AK6: =IF($A6=0,0,SUMIF('Week 2 Roster'!$AZ:$AZ,$B6,'Week 2 Roster'!$AE:$AE)) -> 9.0166667 | AL6: =IF($A6=0,0,SUMIF('Week 2 Roster'!$AZ:$AZ,$B6,'Week 2 Roster'!$AG:$AG)) -> 0 | AM6: =IF($A6=0,0,SUMIF('Week 2 Roster'!$AZ:$AZ,$B6,'Week 2 Roster'!$AI:$AI)) -> 0 | AN6: =IF($A6=0,0,SUMIF('Week 2 Roster'!$AZ:$AZ,$B6,'Week 2 Roster'!$AK:$AK)) -> 0 | AO6: =IF($A6=0,0,SUMIF('Week 2 Roster'!$AZ:$AZ,$B6,'Week 2 Roster'!$AM:$AM)) -> 1.2 | AP6: =IF($A6=0,0,SUMIF('Week 2 Roster'!$AZ:$AZ,$B6,'Week 2 Roster'!$AO:$AO)) -> 0 | AQ6: =IF($A6=0,0,SUMIF('Week 2 Roster'!$AZ:$AZ,$B6,'Week 2 Roster'!$AP:$AP)) -> 2 | AR6: =IF($A6=0,0,SUMIF('Week 2 Roster'!$AZ:$AZ,$B6,'Week 2 Roster'!$AQ:$AQ)) -> 0 | AS6: =IF($A6=0,0,SUMIF('Week 2 Roster'!$AZ:$AZ,$B6,'Week 2 Roster'!$AR:$AR)) -> 0 | AT6: =IF($A6=0,0,SUMIF('Week 2 Roster'!$AZ:$AZ,$B6,'Week 2 Roster'!$AS:$AS)) -> 0 | AU6: =SUM(AK6:AP6,AR6:AT6) -> 10.216667 | AW6: ='Week 1 Roster'!A6 -> 210553 | AX6: ='Week 2 Roster'!A6 -> 210553
A7: {=_xlfn.NUMBERVALUE(INDIRECT(TEXT(MIN(IF(($AW$2:$AX$300<>"")*(COUNTIF($B$1:B6,$AW$2:$AX$300)=0),ROW($2:$300)*100+COLUMN($AW:$AX),7^8)),"R0C00"),)&"")} -> 10431 | B7: =IF(A7=0,"",_xlfn.NUMBERVALUE(A7)) -> 10431 | C7: =IF($A7=0,"",VLOOKUP($B7,Employees!$A:$G,2,FALSE)) -> Victoria | D7: =IF($A7=0,"",VLOOKUP($B7,Employees!$A:$G,3,FALSE)) -> Handoko | E7: =IF($A7=0,"",VLOOKUP($B7,Employees!$A:$G,5,FALSE)) -> 36829 | F7: =IF($E7="","",ROUNDDOWN(YEARFRAC($E7, 'Week 1 Roster'!$D$1-1, 1), 0)) -> 25 | G7: =IF($E7="","",ROUNDDOWN(YEARFRAC($E7, 'Week 1 Roster'!$D$1+14, 1), 0)) -> 25 | H7: =IF($E7="","",IF(AND(F7<21,F7<>G7),TRUE,FALSE)) -> FALSE | I7: =IF($A7=0,"",VLOOKUP($B7,Employees!$A:$G,6,FALSE)) -> 62 | J7: =IF($A7=0,"",VLOOKUP($B7,Employees!$A:$G,7,FALSE)) -> Win | K7: =IF($A7=0,"",IF(ISNA(VLOOKUP(A7,'Week 1 Roster'!A:C,2,0)),VLOOKUP(A7,'Week 2 Roster'!A:C,2,0),VLOOKUP(A7,'Week 1 Roster'!A:C,2,0))) -> The Star | L7: =IF($A7=0,"",VLOOKUP(K7,Stores!A:B,2,0)) -> Winlada | M7: =Y7+AK7 -> 7.75 | N7: =Z7+AL7 -> 0 | O7: =AA7+AM7 -> 0 | P7: =AB7+AN7 -> 0 | Q7: =AC7+AO7 -> 0 | R7: =AD7+AP7 -> 0 | S7: =AE7+AQ7 -> 1 | T7: =AF7+AR7 -> 0 | ... V7: =AH7+AT7 -> 0 | W7: =SUM(M7:R7,T7:V7) -> 7.75 | Y7: =IF($A7=0,0,SUMIF('Week 1 Roster'!$AZ:$AZ,$B7,'Week 1 Roster'!$AE:$AE)) -> 7.75 | Z7: =IF($A7=0,0,SUMIF('Week 1 Roster'!$AZ:$AZ,$B7,'Week 1 Roster'!$AG:$AG)) -> 0 | AA7: =IF($A7=0,0,SUMIF('Week 1 Roster'!$AZ:$AZ,$B7,'Week 1 Roster'!$AI:$AI)) -> 0 | AB7: =IF($A7=0,0,SUMIF('Week 1 Roster'!$AZ:$AZ,$B7,'Week 1 Roster'!$AK:$AK)) -> 0 | AC7: =IF($A7=0,0,SUMIF('Week 1 Roster'!$AZ:$AZ,$B7,'Week 1 Roster'!$AM:$AM)) -> 0 | AD7: =IF($A7=0,0,SUMIF('Week 1 Roster'!$AZ:$AZ,$B7,'Week 1 Roster'!$AO:$AO)) -> 0 | AE7: =IF($A7=0,0,SUMIF('Week 1 Roster'!$AZ:$AZ,$B7,'Week 1 Roster'!$AP:$AP)) -> 1 | AF7: =IF($A7=0,0,SUMIF('Week 1 Roster'!$AZ:$AZ,$B7,'Week 1 Roster'!$AQ:$AQ)) -> 0 | AG7: =IF($A7=0,0,SUMIF('Week 1 Roster'!$AZ:$AZ,$B7,'Week 1 Roster'!$AR:$AR)) -> 0 | AH7: =IF($A7=0,0,SUMIF('Week 1 Roster'!$AZ:$AZ,$B7,'Week 1 Roster'!$AS:$AS)) -> 0 | AI7: =SUM(Y7:AD7,AF7:AH7) -> 7.75 | AK7: =IF($A7=0,0,SUMIF('Week 2 Roster'!$AZ:$AZ,$B7,'Week 2 Roster'!$AE:$AE)) -> 0 | AL7: =IF($A7=0,0,SUMIF('Week 2 Roster'!$AZ:$AZ,$B7,'Week 2 Roster'!$AG:$AG)) -> 0 | AM7: =IF($A7=0,0,SUMIF('Week 2 Roster'!$AZ:$AZ,$B7,'Week 2 Roster'!$AI:$AI)) -> 0 | AN7: =IF($A7=0,0,SUMIF('Week 2 Roster'!$AZ:$AZ,$B7,'Week 2 Roster'!$AK:$AK)) -> 0 | AO7: =IF($A7=0,0,SUMIF('Week 2 Roster'!$AZ:$AZ,$B7,'Week 2 Roster'!$AM:$AM)) -> 0 | AP7: =IF($A7=0,0,SUMIF('Week 2 Roster'!$AZ:$AZ,$B7,'Week 2 Roster'!$AO:$AO)) -> 0 | AQ7: =IF($A7=0,0,SUMIF('Week 2 Roster'!$AZ:$AZ,$B7,'Week 2 Roster'!$AP:$AP)) -> 0 | AR7: =IF($A7=0,0,SUMIF('Week 2 Roster'!$AZ:$AZ,$B7,'Week 2 Roster'!$AQ:$AQ)) -> 0 | AS7: =IF($A7=0,0,SUMIF('Week 2 Roster'!$AZ:$AZ,$B7,'Week 2 Roster'!$AR:$AR)) -> 0 | AT7: =IF($A7=0,0,SUMIF('Week 2 Roster'!$AZ:$AZ,$B7,'Week 2 Roster'!$AS:$AS)) -> 0 | AU7: =SUM(AK7:AP7,AR7:AT7) -> 0 | AW7: ='Week 1 Roster'!A7 -> 10431 | AX7: ='Week 2 Roster'!A7
A8: {=_xlfn.NUMBERVALUE(INDIRECT(TEXT(MIN(IF(($AW$2:$AX$300<>"")*(COUNTIF($B$1:B7,$AW$2:$AX$300)=0),ROW($2:$300)*100+COLUMN($AW:$AX),7^8)),"R0C00"),)&"")} -> 10090 | B8: =IF(A8=0,"",_xlfn.NUMBERVALUE(A8)) -> 10090 | C8: =IF($A8=0,"",VLOOKUP($B8,Employees!$A:$G,2,FALSE)) -> Hsin-Yi | D8: =IF($A8=0,"",VLOOKUP($B8,Employees!$A:$G,3,FALSE)) -> CHIANG | E8: =IF($A8=0,"",VLOOKUP($B8,Employees!$A:$G,5,FALSE)) -> 33945 | F8: =IF($E8="","",ROUNDDOWN(YEARFRAC($E8, 'Week 1 Roster'!$D$1-1, 1), 0)) -> 33 | G8: =IF($E8="","",ROUNDDOWN(YEARFRAC($E8, 'Week 1 Roster'!$D$1+14, 1), 0)) -> 33 | H8: =IF($E8="","",IF(AND(F8<21,F8<>G8),TRUE,FALSE)) -> FALSE | I8: =IF($A8=0,"",VLOOKUP($B8,Employees!$A:$G,6,FALSE)) -> 76 | J8: =IF($A8=0,"",VLOOKUP($B8,Employees!$A:$G,7,FALSE)) -> HL | K8: =IF($A8=0,"",IF(ISNA(VLOOKUP(A8,'Week 1 Roster'!A:C,2,0)),VLOOKUP(A8,'Week 2 Roster'!A:C,2,0),VLOOKUP(A8,'Week 1 Roster'!A:C,2,0))) -> The Star | L8: =IF($A8=0,"",VLOOKUP(K8,Stores!A:B,2,0)) -> Winlada | M8: =Y8+AK8 -> 4.25 | N8: =Z8+AL8 -> 0 | O8: =AA8+AM8 -> 0 | P8: =AB8+AN8 -> 0 | Q8: =AC8+AO8 -> 1.1666667 | R8: =AD8+AP8 -> 0 | S8: =AE8+AQ8 -> 1 | T8: =AF8+AR8 -> 0 | ... V8: =AH8+AT8 -> 0 | W8: =SUM(M8:R8,T8:V8) -> 5.4166667 | Y8: =IF($A8=0,0,SUMIF('Week 1 Roster'!$AZ:$AZ,$B8,'Week 1 Roster'!$AE:$AE)) -> 4.25 | Z8: =IF($A8=0,0,SUMIF('Week 1 Roster'!$AZ:$AZ,$B8,'Week 1 Roster'!$AG:$AG)) -> 0 | AA8: =IF($A8=0,0,SUMIF('Week 1 Roster'!$AZ:$AZ,$B8,'Week 1 Roster'!$AI:$AI)) -> 0 | AB8: =IF($A8=0,0,SUMIF('Week 1 Roster'!$AZ:$AZ,$B8,'Week 1 Roster'!$AK:$AK)) -> 0 | AC8: =IF($A8=0,0,SUMIF('Week 1 Roster'!$AZ:$AZ,$B8,'Week 1 Roster'!$AM:$AM)) -> 1.1666667 | AD8: =IF($A8=0,0,SUMIF('Week 1 Roster'!$AZ:$AZ,$B8,'Week 1 Roster'!$AO:$AO)) -> 0 | AE8: =IF($A8=0,0,SUMIF('Week 1 Roster'!$AZ:$AZ,$B8,'Week 1 Roster'!$AP:$AP)) -> 1 | AF8: =IF($A8=0,0,SUMIF('Week 1 Roster'!$AZ:$AZ,$B8,'Week 1 Roster'!$AQ:$AQ)) -> 0 | AG8: =IF($A8=0,0,SUMIF('Week 1 Roster'!$AZ:$AZ,$B8,'Week 1 Roster'!$AR:$AR)) -> 0 | AH8: =IF($A8=0,0,SUMIF('Week 1 Roster'!$AZ:$AZ,$B8,'Week 1 Roster'!$AS:$AS)) -> 0 | AI8: =SUM(Y8:AD8,AF8:AH8) -> 5.4166667 | AK8: =IF($A8=0,0,SUMIF('Week 2 Roster'!$AZ:$AZ,$B8,'Week 2 Roster'!$AE:$AE)) -> 0 | AL8: =IF($A8=0,0,SUMIF('Week 2 Roster'!$AZ:$AZ,$B8,'Week 2 Roster'!$AG:$AG)) -> 0 | AM8: =IF($A8=0,0,SUMIF('Week 2 Roster'!$AZ:$AZ,$B8,'Week 2 Roster'!$AI:$AI)) -> 0 | AN8: =IF($A8=0,0,SUMIF('Week 2 Roster'!$AZ:$AZ,$B8,'Week 2 Roster'!$AK:$AK)) -> 0 | AO8: =IF($A8=0,0,SUMIF('Week 2 Roster'!$AZ:$AZ,$B8,'Week 2 Roster'!$AM:$AM)) -> 0 | AP8: =IF($A8=0,0,SUMIF('Week 2 Roster'!$AZ:$AZ,$B8,'Week 2 Roster'!$AO:$AO)) -> 0 | AQ8: =IF($A8=0,0,SUMIF('Week 2 Roster'!$AZ:$AZ,$B8,'Week 2 Roster'!$AP:$AP)) -> 0 | AR8: =IF($A8=0,0,SUMIF('Week 2 Roster'!$AZ:$AZ,$B8,'Week 2 Roster'!$AQ:$AQ)) -> 0 | AS8: =IF($A8=0,0,SUMIF('Week 2 Roster'!$AZ:$AZ,$B8,'Week 2 Roster'!$AR:$AR)) -> 0 | AT8: =IF($A8=0,0,SUMIF('Week 2 Roster'!$AZ:$AZ,$B8,'Week 2 Roster'!$AS:$AS)) -> 0 | AU8: =SUM(AK8:AP8,AR8:AT8) -> 0 | AW8: ='Week 1 Roster'!A8 -> 10090 | AX8: ='Week 2 Roster'!A8
A9: {=_xlfn.NUMBERVALUE(INDIRECT(TEXT(MIN(IF(($AW$2:$AX$300<>"")*(COUNTIF($B$1:B8,$AW$2:$AX$300)=0),ROW($2:$300)*100+COLUMN($AW:$AX),7^8)),"R0C00"),)&"")} -> 0 | B9: =IF(A9=0,"",_xlfn.NUMBERVALUE(A9)) | C9: =IF($A9=0,"",VLOOKUP($B9,Employees!$A:$G,2,FALSE)) | D9: =IF($A9=0,"",VLOOKUP($B9,Employees!$A:$G,3,FALSE)) | E9: =IF($A9=0,"",VLOOKUP($B9,Employees!$A:$G,5,FALSE)) | F9: =IF($E9="","",ROUNDDOWN(YEARFRAC($E9, 'Week 1 Roster'!$D$1-1, 1), 0)) | G9: =IF($E9="","",ROUNDDOWN(YEARFRAC($E9, 'Week 1 Roster'!$D$1+14, 1), 0)) | H9: =IF($E9="","",IF(AND(F9<21,F9<>G9),TRUE,FALSE)) | I9: =IF($A9=0,"",VLOOKUP($B9,Employees!$A:$G,6,FALSE)) | J9: =IF($A9=0,"",VLOOKUP($B9,Employees!$A:$G,7,FALSE)) | K9: =IF($A9=0,"",IF(ISNA(VLOOKUP(A9,'Week 1 Roster'!A:C,2,0)),VLOOKUP(A9,'Week 2 Roster'!A:C,2,0),VLOOKUP(A9,'Week 1 Roster'!A:C,2,0))) | L9: =IF($A9=0,"",VLOOKUP(K9,Stores!A:B,2,0)) | M9: =Y9+AK9 -> 0 | N9: =Z9+AL9 -> 0 | O9: =AA9+AM9 -> 0 | P9: =AB9+AN9 -> 0 | Q9: =AC9+AO9 -> 0 | R9: =AD9+AP9 -> 0 | S9: =AE9+AQ9 -> 0 | T9: =AF9+AR9 -> 0 | ... V9: =AH9+AT9 -> 0 | W9: =SUM(M9:R9,T9:V9) -> 0 | Y9: =IF($A9=0,0,SUMIF('Week 1 Roster'!$AZ:$AZ,$B9,'Week 1 Roster'!$AE:$AE)) -> 0 | Z9: =IF($A9=0,0,SUMIF('Week 1 Roster'!$AZ:$AZ,$B9,'Week 1 Roster'!$AG:$AG)) -> 0 | AA9: =IF($A9=0,0,SUMIF('Week 1 Roster'!$AZ:$AZ,$B9,'Week 1 Roster'!$AI:$AI)) -> 0 | AB9: =IF($A9=0,0,SUMIF('Week 1 Roster'!$AZ:$AZ,$B9,'Week 1 Roster'!$AK:$AK)) -> 0 | AC9: =IF($A9=0,0,SUMIF('Week 1 Roster'!$AZ:$AZ,$B9,'Week 1 Roster'!$AM:$AM)) -> 0 | AD9: =IF($A9=0,0,SUMIF('Week 1 Roster'!$AZ:$AZ,$B9,'Week 1 Roster'!$AO:$AO)) -> 0 | AE9: =IF($A9=0,0,SUMIF('Week 1 Roster'!$AZ:$AZ,$B9,'Week 1 Roster'!$AP:$AP)) -> 0 | AF9: =IF($A9=0,0,SUMIF('Week 1 Roster'!$AZ:$AZ,$B9,'Week 1 Roster'!$AQ:$AQ)) -> 0 | AG9: =IF($A9=0,0,SUMIF('Week 1 Roster'!$AZ:$AZ,$B9,'Week 1 Roster'!$AR:$AR)) -> 0 | AH9: =IF($A9=0,0,SUMIF('Week 1 Roster'!$AZ:$AZ,$B9,'Week 1 Roster'!$AS:$AS)) -> 0 | AI9: =SUM(Y9:AD9,AF9:AH9) -> 0 | AK9: =IF($A9=0,0,SUMIF('Week 2 Roster'!$AZ:$AZ,$B9,'Week 2 Roster'!$AE:$AE)) -> 0 | AL9: =IF($A9=0,0,SUMIF('Week 2 Roster'!$AZ:$AZ,$B9,'Week 2 Roster'!$AG:$AG)) -> 0 | AM9: =IF($A9=0,0,SUMIF('Week 2 Roster'!$AZ:$AZ,$B9,'Week 2 Roster'!$AI:$AI)) -> 0 | AN9: =IF($A9=0,0,SUMIF('Week 2 Roster'!$AZ:$AZ,$B9,'Week 2 Roster'!$AK:$AK)) -> 0 | AO9: =IF($A9=0,0,SUMIF('Week 2 Roster'!$AZ:$AZ,$B9,'Week 2 Roster'!$AM:$AM)) -> 0 | AP9: =IF($A9=0,0,SUMIF('Week 2 Roster'!$AZ:$AZ,$B9,'Week 2 Roster'!$AO:$AO)) -> 0 | AQ9: =IF($A9=0,0,SUMIF('Week 2 Roster'!$AZ:$AZ,$B9,'Week 2 Roster'!$AP:$AP)) -> 0 | AR9: =IF($A9=0,0,SUMIF('Week 2 Roster'!$AZ:$AZ,$B9,'Week 2 Roster'!$AQ:$AQ)) -> 0 | AS9: =IF($A9=0,0,SUMIF('Week 2 Roster'!$AZ:$AZ,$B9,'Week 2 Roster'!$AR:$AR)) -> 0 | AT9: =IF($A9=0,0,SUMIF('Week 2 Roster'!$AZ:$AZ,$B9,'Week 2 Roster'!$AS:$AS)) -> 0 | AU9: =SUM(AK9:AP9,AR9:AT9) -> 0 | AW9: ='Week 1 Roster'!A9 | AX9: ='Week 2 Roster'!A9
A10: {=_xlfn.NUMBERVALUE(INDIRECT(TEXT(MIN(IF(($AW$2:$AX$300<>"")*(COUNTIF($B$1:B9,$AW$2:$AX$300)=0),ROW($2:$300)*100+COLUMN($AW:$AX),7^8)),"R0C00"),)&"")} -> 0 | B10: =IF(A10=0,"",_xlfn.NUMBERVALUE(A10)) | C10: =IF($A10=0,"",VLOOKUP($B10,Employees!$A:$G,2,FALSE)) | D10: =IF($A10=0,"",VLOOKUP($B10,Employees!$A:$G,3,FALSE)) | E10: =IF($A10=0,"",VLOOKUP($B10,Employees!$A:$G,5,FALSE)) | F10: =IF($E10="","",ROUNDDOWN(YEARFRAC($E10, 'Week 1 Roster'!$D$1-1, 1), 0)) | G10: =IF($E10="","",ROUNDDOWN(YEARFRAC($E10, 'Week 1 Roster'!$D$1+14, 1), 0)) | H10: =IF($E10="","",IF(AND(F10<21,F10<>G10),TRUE,FALSE)) | I10: =IF($A10=0,"",VLOOKUP($B10,Employees!$A:$G,6,FALSE)) | J10: =IF($A10=0,"",VLOOKUP($B10,Employees!$A:$G,7,FALSE)) | K10: =IF($A10=0,"",IF(ISNA(VLOOKUP(A10,'Week 1 Roster'!A:C,2,0)),VLOOKUP(A10,'Week 2 Roster'!A:C,2,0),VLOOKUP(A10,'Week 1 Roster'!A:C,2,0))) | L10: =IF($A10=0,"",VLOOKUP(K10,Stores!A:B,2,0)) | M10: =Y10+AK10 -> 0 | N10: =Z10+AL10 -> 0 | O10: =AA10+AM10 -> 0 | P10: =AB10+AN10 -> 0 | Q10: =AC10+AO10 -> 0 | R10: =AD10+AP10 -> 0 | S10: =AE10+AQ10 -> 0 | T10: =AF10+AR10 -> 0 | ... V10: =AH10+AT10 -> 0 | W10: =SUM(M10:R10,T10:V10) -> 0 | Y10: =IF($A10=0,0,SUMIF('Week 1 Roster'!$AZ:$AZ,$B10,'Week 1 Roster'!$AE:$AE)) -> 0 | Z10: =IF($A10=0,0,SUMIF('Week 1 Roster'!$AZ:$AZ,$B10,'Week 1 Roster'!$AG:$AG)) -> 0 | AA10: =IF($A10=0,0,SUMIF('Week 1 Roster'!$AZ:$AZ,$B10,'Week 1 Roster'!$AI:$AI)) -> 0 | AB10: =IF($A10=0,0,SUMIF('Week 1 Roster'!$AZ:$AZ,$B10,'Week 1 Roster'!$AK:$AK)) -> 0 | AC10: =IF($A10=0,0,SUMIF('Week 1 Roster'!$AZ:$AZ,$B10,'Week 1 Roster'!$AM:$AM)) -> 0 | AD10: =IF($A10=0,0,SUMIF('Week 1 Roster'!$AZ:$AZ,$B10,'Week 1 Roster'!$AO:$AO)) -> 0 | AE10: =IF($A10=0,0,SUMIF('Week 1 Roster'!$AZ:$AZ,$B10,'Week 1 Roster'!$AP:$AP)) -> 0 | AF10: =IF($A10=0,0,SUMIF('Week 1 Roster'!$AZ:$AZ,$B10,'Week 1 Roster'!$AQ:$AQ)) -> 0 | AG10: =IF($A10=0,0,SUMIF('Week 1 Roster'!$AZ:$AZ,$B10,'Week 1 Roster'!$AR:$AR)) -> 0 | AH10: =IF($A10=0,0,SUMIF('Week 1 Roster'!$AZ:$AZ,$B10,'Week 1 Roster'!$AS:$AS)) -> 0 | AI10: =SUM(Y10:AD10,AF10:AH10) -> 0 | AK10: =IF($A10=0,0,SUMIF('Week 2 Roster'!$AZ:$AZ,$B10,'Week 2 Roster'!$AE:$AE)) -> 0 | AL10: =IF($A10=0,0,SUMIF('Week 2 Roster'!$AZ:$AZ,$B10,'Week 2 Roster'!$AG:$AG)) -> 0 | AM10: =IF($A10=0,0,SUMIF('Week 2 Roster'!$AZ:$AZ,$B10,'Week 2 Roster'!$AI:$AI)) -> 0 | AN10: =IF($A10=0,0,SUMIF('Week 2 Roster'!$AZ:$AZ,$B10,'Week 2 Roster'!$AK:$AK)) -> 0 | AO10: =IF($A10=0,0,SUMIF('Week 2 Roster'!$AZ:$AZ,$B10,'Week 2 Roster'!$AM:$AM)) -> 0 | AP10: =IF($A10=0,0,SUMIF('Week 2 Roster'!$AZ:$AZ,$B10,'Week 2 Roster'!$AO:$AO)) -> 0 | AQ10: =IF($A10=0,0,SUMIF('Week 2 Roster'!$AZ:$AZ,$B10,'Week 2 Roster'!$AP:$AP)) -> 0 | AR10: =IF($A10=0,0,SUMIF('Week 2 Roster'!$AZ:$AZ,$B10,'Week 2 Roster'!$AQ:$AQ)) -> 0 | AS10: =IF($A10=0,0,SUMIF('Week 2 Roster'!$AZ:$AZ,$B10,'Week 2 Roster'!$AR:$AR)) -> 0 | AT10: =IF($A10=0,0,SUMIF('Week 2 Roster'!$AZ:$AZ,$B10,'Week 2 Roster'!$AS:$AS)) -> 0 | AU10: =SUM(AK10:AP10,AR10:AT10) -> 0 | AW10: ='Week 1 Roster'!A10 | AX10: ='Week 2 Roster'!A10
A11: {=_xlfn.NUMBERVALUE(INDIRECT(TEXT(MIN(IF(($AW$2:$AX$300<>"")*(COUNTIF($B$1:B10,$AW$2:$AX$300)=0),ROW($2:$300)*100+COLUMN($AW:$AX),7^8)),"R0C00"),)&"")} -> 0 | B11: =IF(A11=0,"",_xlfn.NUMBERVALUE(A11)) | C11: =IF($A11=0,"",VLOOKUP($B11,Employees!$A:$G,2,FALSE)) | D11: =IF($A11=0,"",VLOOKUP($B11,Employees!$A:$G,3,FALSE)) | E11: =IF($A11=0,"",VLOOKUP($B11,Employees!$A:$G,5,FALSE)) | F11: =IF($E11="","",ROUNDDOWN(YEARFRAC($E11, 'Week 1 Roster'!$D$1-1, 1), 0)) | G11: =IF($E11="","",ROUNDDOWN(YEARFRAC($E11, 'Week 1 Roster'!$D$1+14, 1), 0)) | H11: =IF($E11="","",IF(AND(F11<21,F11<>G11),TRUE,FALSE)) | I11: =IF($A11=0,"",VLOOKUP($B11,Employees!$A:$G,6,FALSE)) | J11: =IF($A11=0,"",VLOOKUP($B11,Employees!$A:$G,7,FALSE)) | K11: =IF($A11=0,"",IF(ISNA(VLOOKUP(A11,'Week 1 Roster'!A:C,2,0)),VLOOKUP(A11,'Week 2 Roster'!A:C,2,0),VLOOKUP(A11,'Week 1 Roster'!A:C,2,0))) | L11: =IF($A11=0,"",VLOOKUP(K11,Stores!A:B,2,0)) | M11: =Y11+AK11 -> 0 | N11: =Z11+AL11 -> 0 | O11: =AA11+AM11 -> 0 | P11: =AB11+AN11 -> 0 | Q11: =AC11+AO11 -> 0 | R11: =AD11+AP11 -> 0 | S11: =AE11+AQ11 -> 0 | T11: =AF11+AR11 -> 0 | ... V11: =AH11+AT11 -> 0 | W11: =SUM(M11:R11,T11:V11) -> 0 | Y11: =IF($A11=0,0,SUMIF('Week 1 Roster'!$AZ:$AZ,$B11,'Week 1 Roster'!$AE:$AE)) -> 0 | Z11: =IF($A11=0,0,SUMIF('Week 1 Roster'!$AZ:$AZ,$B11,'Week 1 Roster'!$AG:$AG)) -> 0 | AA11: =IF($A11=0,0,SUMIF('Week 1 Roster'!$AZ:$AZ,$B11,'Week 1 Roster'!$AI:$AI)) -> 0 | AB11: =IF($A11=0,0,SUMIF('Week 1 Roster'!$AZ:$AZ,$B11,'Week 1 Roster'!$AK:$AK)) -> 0 | AC11: =IF($A11=0,0,SUMIF('Week 1 Roster'!$AZ:$AZ,$B11,'Week 1 Roster'!$AM:$AM)) -> 0 | AD11: =IF($A11=0,0,SUMIF('Week 1 Roster'!$AZ:$AZ,$B11,'Week 1 Roster'!$AO:$AO)) -> 0 | AE11: =IF($A11=0,0,SUMIF('Week 1 Roster'!$AZ:$AZ,$B11,'Week 1 Roster'!$AP:$AP)) -> 0 | AF11: =IF($A11=0,0,SUMIF('Week 1 Roster'!$AZ:$AZ,$B11,'Week 1 Roster'!$AQ:$AQ)) -> 0 | AG11: =IF($A11=0,0,SUMIF('Week 1 Roster'!$AZ:$AZ,$B11,'Week 1 Roster'!$AR:$AR)) -> 0 | AH11: =IF($A11=0,0,SUMIF('Week 1 Roster'!$AZ:$AZ,$B11,'Week 1 Roster'!$AS:$AS)) -> 0 | AI11: =SUM(Y11:AD11,AF11:AH11) -> 0 | AK11: =IF($A11=0,0,SUMIF('Week 2 Roster'!$AZ:$AZ,$B11,'Week 2 Roster'!$AE:$AE)) -> 0 | AL11: =IF($A11=0,0,SUMIF('Week 2 Roster'!$AZ:$AZ,$B11,'Week 2 Roster'!$AG:$AG)) -> 0 | AM11: =IF($A11=0,0,SUMIF('Week 2 Roster'!$AZ:$AZ,$B11,'Week 2 Roster'!$AI:$AI)) -> 0 | AN11: =IF($A11=0,0,SUMIF('Week 2 Roster'!$AZ:$AZ,$B11,'Week 2 Roster'!$AK:$AK)) -> 0 | AO11: =IF($A11=0,0,SUMIF('Week 2 Roster'!$AZ:$AZ,$B11,'Week 2 Roster'!$AM:$AM)) -> 0 | AP11: =IF($A11=0,0,SUMIF('Week 2 Roster'!$AZ:$AZ,$B11,'Week 2 Roster'!$AO:$AO)) -> 0 | AQ11: =IF($A11=0,0,SUMIF('Week 2 Roster'!$AZ:$AZ,$B11,'Week 2 Roster'!$AP:$AP)) -> 0 | AR11: =IF($A11=0,0,SUMIF('Week 2 Roster'!$AZ:$AZ,$B11,'Week 2 Roster'!$AQ:$AQ)) -> 0 | AS11: =IF($A11=0,0,SUMIF('Week 2 Roster'!$AZ:$AZ,$B11,'Week 2 Roster'!$AR:$AR)) -> 0 | AT11: =IF($A11=0,0,SUMIF('Week 2 Roster'!$AZ:$AZ,$B11,'Week 2 Roster'!$AS:$AS)) -> 0 | AU11: =SUM(AK11:AP11,AR11:AT11) -> 0 | AW11: ='Week 1 Roster'!A11 | AX11: ='Week 2 Roster'!A11
A12: {=_xlfn.NUMBERVALUE(INDIRECT(TEXT(MIN(IF(($AW$2:$AX$300<>"")*(COUNTIF($B$1:B11,$AW$2:$AX$300)=0),ROW($2:$300)*100+COLUMN($AW:$AX),7^8)),"R0C00"),)&"")} -> 0 | B12: =IF(A12=0,"",_xlfn.NUMBERVALUE(A12)) | C12: =IF($A12=0,"",VLOOKUP($B12,Employees!$A:$G,2,FALSE)) | D12: =IF($A12=0,"",VLOOKUP($B12,Employees!$A:$G,3,FALSE)) | E12: =IF($A12=0,"",VLOOKUP($B12,Employees!$A:$G,5,FALSE)) | F12: =IF($E12="","",ROUNDDOWN(YEARFRAC($E12, 'Week 1 Roster'!$D$1-1, 1), 0)) | G12: =IF($E12="","",ROUNDDOWN(YEARFRAC($E12, 'Week 1 Roster'!$D$1+14, 1), 0)) | H12: =IF($E12="","",IF(AND(F12<21,F12<>G12),TRUE,FALSE)) | I12: =IF($A12=0,"",VLOOKUP($B12,Employees!$A:$G,6,FALSE)) | J12: =IF($A12=0,"",VLOOKUP($B12,Employees!$A:$G,7,FALSE)) | K12: =IF($A12=0,"",IF(ISNA(VLOOKUP(A12,'Week 1 Roster'!A:C,2,0)),VLOOKUP(A12,'Week 2 Roster'!A:C,2,0),VLOOKUP(A12,'Week 1 Roster'!A:C,2,0))) | L12: =IF($A12=0,"",VLOOKUP(K12,Stores!A:B,2,0)) | M12: =Y12+AK12 -> 0 | N12: =Z12+AL12 -> 0 | O12: =AA12+AM12 -> 0 | P12: =AB12+AN12 -> 0 | Q12: =AC12+AO12 -> 0 | R12: =AD12+AP12 -> 0 | S12: =AE12+AQ12 -> 0 | T12: =AF12+AR12 -> 0 | ... V12: =AH12+AT12 -> 0 | W12: =SUM(M12:R12,T12:V12) -> 0 | Y12: =IF($A12=0,0,SUMIF('Week 1 Roster'!$AZ:$AZ,$B12,'Week 1 Roster'!$AE:$AE)) -> 0 | Z12: =IF($A12=0,0,SUMIF('Week 1 Roster'!$AZ:$AZ,$B12,'Week 1 Roster'!$AG:$AG)) -> 0 | AA12: =IF($A12=0,0,SUMIF('Week 1 Roster'!$AZ:$AZ,$B12,'Week 1 Roster'!$AI:$AI)) -> 0 | AB12: =IF($A12=0,0,SUMIF('Week 1 Roster'!$AZ:$AZ,$B12,'Week 1 Roster'!$AK:$AK)) -> 0 | AC12: =IF($A12=0,0,SUMIF('Week 1 Roster'!$AZ:$AZ,$B12,'Week 1 Roster'!$AM:$AM)) -> 0 | AD12: =IF($A12=0,0,SUMIF('Week 1 Roster'!$AZ:$AZ,$B12,'Week 1 Roster'!$AO:$AO)) -> 0 | AE12: =IF($A12=0,0,SUMIF('Week 1 Roster'!$AZ:$AZ,$B12,'Week 1 Roster'!$AP:$AP)) -> 0 | AF12: =IF($A12=0,0,SUMIF('Week 1 Roster'!$AZ:$AZ,$B12,'Week 1 Roster'!$AQ:$AQ)) -> 0 | AG12: =IF($A12=0,0,SUMIF('Week 1 Roster'!$AZ:$AZ,$B12,'Week 1 Roster'!$AR:$AR)) -> 0 | AH12: =IF($A12=0,0,SUMIF('Week 1 Roster'!$AZ:$AZ,$B12,'Week 1 Roster'!$AS:$AS)) -> 0 | AI12: =SUM(Y12:AD12,AF12:AH12) -> 0 | AK12: =IF($A12=0,0,SUMIF('Week 2 Roster'!$AZ:$AZ,$B12,'Week 2 Roster'!$AE:$AE)) -> 0 | AL12: =IF($A12=0,0,SUMIF('Week 2 Roster'!$AZ:$AZ,$B12,'Week 2 Roster'!$AG:$AG)) -> 0 | AM12: =IF($A12=0,0,SUMIF('Week 2 Roster'!$AZ:$AZ,$B12,'Week 2 Roster'!$AI:$AI)) -> 0 | AN12: =IF($A12=0,0,SUMIF('Week 2 Roster'!$AZ:$AZ,$B12,'Week 2 Roster'!$AK:$AK)) -> 0 | AO12: =IF($A12=0,0,SUMIF('Week 2 Roster'!$AZ:$AZ,$B12,'Week 2 Roster'!$AM:$AM)) -> 0 | AP12: =IF($A12=0,0,SUMIF('Week 2 Roster'!$AZ:$AZ,$B12,'Week 2 Roster'!$AO:$AO)) -> 0 | AQ12: =IF($A12=0,0,SUMIF('Week 2 Roster'!$AZ:$AZ,$B12,'Week 2 Roster'!$AP:$AP)) -> 0 | AR12: =IF($A12=0,0,SUMIF('Week 2 Roster'!$AZ:$AZ,$B12,'Week 2 Roster'!$AQ:$AQ)) -> 0 | AS12: =IF($A12=0,0,SUMIF('Week 2 Roster'!$AZ:$AZ,$B12,'Week 2 Roster'!$AR:$AR)) -> 0 | AT12: =IF($A12=0,0,SUMIF('Week 2 Roster'!$AZ:$AZ,$B12,'Week 2 Roster'!$AS:$AS)) -> 0 | AU12: =SUM(AK12:AP12,AR12:AT12) -> 0 | AW12: ='Week 1 Roster'!A12 | AX12: ='Week 2 Roster'!A12
A13: {=_xlfn.NUMBERVALUE(INDIRECT(TEXT(MIN(IF(($AW$2:$AX$300<>"")*(COUNTIF($B$1:B12,$AW$2:$AX$300)=0),ROW($2:$300)*100+COLUMN($AW:$AX),7^8)),"R0C00"),)&"")} -> 0 | B13: =IF(A13=0,"",_xlfn.NUMBERVALUE(A13)) | C13: =IF($A13=0,"",VLOOKUP($B13,Employees!$A:$G,2,FALSE)) | D13: =IF($A13=0,"",VLOOKUP($B13,Employees!$A:$G,3,FALSE)) | E13: =IF($A13=0,"",VLOOKUP($B13,Employees!$A:$G,5,FALSE)) | F13: =IF($E13="","",ROUNDDOWN(YEARFRAC($E13, 'Week 1 Roster'!$D$1-1, 1), 0)) | G13: =IF($E13="","",ROUNDDOWN(YEARFRAC($E13, 'Week 1 Roster'!$D$1+14, 1), 0)) | H13: =IF($E13="","",IF(AND(F13<21,F13<>G13),TRUE,FALSE)) | I13: =IF($A13=0,"",VLOOKUP($B13,Employees!$A:$G,6,FALSE)) | J13: =IF($A13=0,"",VLOOKUP($B13,Employees!$A:$G,7,FALSE)) | K13: =IF($A13=0,"",IF(ISNA(VLOOKUP(A13,'Week 1 Roster'!A:C,2,0)),VLOOKUP(A13,'Week 2 Roster'!A:C,2,0),VLOOKUP(A13,'Week 1 Roster'!A:C,2,0))) | L13: =IF($A13=0,"",VLOOKUP(K13,Stores!A:B,2,0)) | M13: =Y13+AK13 -> 0 | N13: =Z13+AL13 -> 0 | O13: =AA13+AM13 -> 0 | P13: =AB13+AN13 -> 0 | Q13: =AC13+AO13 -> 0 | R13: =AD13+AP13 -> 0 | S13: =AE13+AQ13 -> 0 | T13: =AF13+AR13 -> 0 | ... V13: =AH13+AT13 -> 0 | W13: =SUM(M13:R13,T13:V13) -> 0 | Y13: =IF($A13=0,0,SUMIF('Week 1 Roster'!$AZ:$AZ,$B13,'Week 1 Roster'!$AE:$AE)) -> 0 | Z13: =IF($A13=0,0,SUMIF('Week 1 Roster'!$AZ:$AZ,$B13,'Week 1 Roster'!$AG:$AG)) -> 0 | AA13: =IF($A13=0,0,SUMIF('Week 1 Roster'!$AZ:$AZ,$B13,'Week 1 Roster'!$AI:$AI)) -> 0 | AB13: =IF($A13=0,0,SUMIF('Week 1 Roster'!$AZ:$AZ,$B13,'Week 1 Roster'!$AK:$AK)) -> 0 | AC13: =IF($A13=0,0,SUMIF('Week 1 Roster'!$AZ:$AZ,$B13,'Week 1 Roster'!$AM:$AM)) -> 0 | AD13: =IF($A13=0,0,SUMIF('Week 1 Roster'!$AZ:$AZ,$B13,'Week 1 Roster'!$AO:$AO)) -> 0 | AE13: =IF($A13=0,0,SUMIF('Week 1 Roster'!$AZ:$AZ,$B13,'Week 1 Roster'!$AP:$AP)) -> 0 | AF13: =IF($A13=0,0,SUMIF('Week 1 Roster'!$AZ:$AZ,$B13,'Week 1 Roster'!$AQ:$AQ)) -> 0 | AG13: =IF($A13=0,0,SUMIF('Week 1 Roster'!$AZ:$AZ,$B13,'Week 1 Roster'!$AR:$AR)) -> 0 | AH13: =IF($A13=0,0,SUMIF('Week 1 Roster'!$AZ:$AZ,$B13,'Week 1 Roster'!$AS:$AS)) -> 0 | AI13: =SUM(Y13:AD13,AF13:AH13) -> 0 | AK13: =IF($A13=0,0,SUMIF('Week 2 Roster'!$AZ:$AZ,$B13,'Week 2 Roster'!$AE:$AE)) -> 0 | AL13: =IF($A13=0,0,SUMIF('Week 2 Roster'!$AZ:$AZ,$B13,'Week 2 Roster'!$AG:$AG)) -> 0 | AM13: =IF($A13=0,0,SUMIF('Week 2 Roster'!$AZ:$AZ,$B13,'Week 2 Roster'!$AI:$AI)) -> 0 | AN13: =IF($A13=0,0,SUMIF('Week 2 Roster'!$AZ:$AZ,$B13,'Week 2 Roster'!$AK:$AK)) -> 0 | AO13: =IF($A13=0,0,SUMIF('Week 2 Roster'!$AZ:$AZ,$B13,'Week 2 Roster'!$AM:$AM)) -> 0 | AP13: =IF($A13=0,0,SUMIF('Week 2 Roster'!$AZ:$AZ,$B13,'Week 2 Roster'!$AO:$AO)) -> 0 | AQ13: =IF($A13=0,0,SUMIF('Week 2 Roster'!$AZ:$AZ,$B13,'Week 2 Roster'!$AP:$AP)) -> 0 | AR13: =IF($A13=0,0,SUMIF('Week 2 Roster'!$AZ:$AZ,$B13,'Week 2 Roster'!$AQ:$AQ)) -> 0 | AS13: =IF($A13=0,0,SUMIF('Week 2 Roster'!$AZ:$AZ,$B13,'Week 2 Roster'!$AR:$AR)) -> 0 | AT13: =IF($A13=0,0,SUMIF('Week 2 Roster'!$AZ:$AZ,$B13,'Week 2 Roster'!$AS:$AS)) -> 0 | AU13: =SUM(AK13:AP13,AR13:AT13) -> 0 | AW13: ='Week 1 Roster'!A13 | AX13: ='Week 2 Roster'!A13
... A100: {=_xlfn.NUMBERVALUE(INDIRECT(TEXT(MIN(IF(($AW$2:$AX$300<>"")*(COUNTIF($B$1:B99,$AW$2:$AX$300)=0),ROW($2:$300)*100+COLUMN($AW:$AX),7^8)),"R0C00"),)&"")} -> 0 | B100: =IF(A100=0,"",_xlfn.NUMBERVALUE(A100)) | C100: =IF($A100=0,"",VLOOKUP($B100,Employees!$A:$G,2,FALSE)) | D100: =IF($A100=0,"",VLOOKUP($B100,Employees!$A:$G,3,FALSE)) | E100: =IF($A100=0,"",VLOOKUP($B100,Employees!$A:$G,5,FALSE)) | F100: =IF($E100="","",ROUNDDOWN(YEARFRAC($E100, 'Week 1 Roster'!$D$1-1, 1), 0)) | G100: =IF($E100="","",ROUNDDOWN(YEARFRAC($E100, 'Week 1 Roster'!$D$1+14, 1), 0)) | H100: =IF($E100="","",IF(AND(F100<21,F100<>G100),TRUE,FALSE)) | I100: =IF($A100=0,"",VLOOKUP($B100,Employees!$A:$G,6,FALSE)) | J100: =IF($A100=0,"",VLOOKUP($B100,Employees!$A:$G,7,FALSE)) | K100: =IF($A100=0,"",IF(ISNA(VLOOKUP(A100,'Week 1 Roster'!A:C,2,0)),VLOOKUP(A100,'Week 2 Roster'!A:C,2,0),VLOOKUP(A100,'Week 1 Roster'!A:C,2,0))) | L100: =IF($A100=0,"",VLOOKUP(K100,Stores!A:B,2,0)) | M100: =Y100+AK100 -> 0 | N100: =Z100+AL100 -> 0 | O100: =AA100+AM100 -> 0 | P100: =AB100+AN100 -> 0 | Q100: =AC100+AO100 -> 0 | R100: =AD100+AP100 -> 0 | S100: =AE100+AQ100 -> 0 | T100: =AF100+AR100 -> 0 | ... V100: =AH100+AT100 -> 0 | W100: =SUM(M100:R100,T100:V100) -> 0 | Y100: =IF($A100=0,0,SUMIF('Week 1 Roster'!$AZ:$AZ,$B100,'Week 1 Roster'!$AE:$AE)) -> 0 | Z100: =IF($A100=0,0,SUMIF('Week 1 Roster'!$AZ:$AZ,$B100,'Week 1 Roster'!$AG:$AG)) -> 0 | AA100: =IF($A100=0,0,SUMIF('Week 1 Roster'!$AZ:$AZ,$B100,'Week 1 Roster'!$AI:$AI)) -> 0 | AB100: =IF($A100=0,0,SUMIF('Week 1 Roster'!$AZ:$AZ,$B100,'Week 1 Roster'!$AK:$AK)) -> 0 | AC100: =IF($A100=0,0,SUMIF('Week 1 Roster'!$AZ:$AZ,$B100,'Week 1 Roster'!$AM:$AM)) -> 0 | AD100: =IF($A100=0,0,SUMIF('Week 1 Roster'!$AZ:$AZ,$B100,'Week 1 Roster'!$AO:$AO)) -> 0 | AE100: =IF($A100=0,0,SUMIF('Week 1 Roster'!$AZ:$AZ,$B100,'Week 1 Roster'!$AP:$AP)) -> 0 | AF100: =IF($A100=0,0,SUMIF('Week 1 Roster'!$AZ:$AZ,$B100,'Week 1 Roster'!$AQ:$AQ)) -> 0 | AG100: =IF($A100=0,0,SUMIF('Week 1 Roster'!$AZ:$AZ,$B100,'Week 1 Roster'!$AR:$AR)) -> 0 | AH100: =IF($A100=0,0,SUMIF('Week 1 Roster'!$AZ:$AZ,$B100,'Week 1 Roster'!$AS:$AS)) -> 0 | AI100: =SUM(Y100:AD100,AF100:AH100) -> 0 | AK100: =IF($A100=0,0,SUMIF('Week 2 Roster'!$AZ:$AZ,$B100,'Week 2 Roster'!$AE:$AE)) -> 0 | AL100: =IF($A100=0,0,SUMIF('Week 2 Roster'!$AZ:$AZ,$B100,'Week 2 Roster'!$AG:$AG)) -> 0 | AM100: =IF($A100=0,0,SUMIF('Week 2 Roster'!$AZ:$AZ,$B100,'Week 2 Roster'!$AI:$AI)) -> 0 | AN100: =IF($A100=0,0,SUMIF('Week 2 Roster'!$AZ:$AZ,$B100,'Week 2 Roster'!$AK:$AK)) -> 0 | AO100: =IF($A100=0,0,SUMIF('Week 2 Roster'!$AZ:$AZ,$B100,'Week 2 Roster'!$AM:$AM)) -> 0 | AP100: =IF($A100=0,0,SUMIF('Week 2 Roster'!$AZ:$AZ,$B100,'Week 2 Roster'!$AO:$AO)) -> 0 | AQ100: =IF($A100=0,0,SUMIF('Week 2 Roster'!$AZ:$AZ,$B100,'Week 2 Roster'!$AP:$AP)) -> 0 | AR100: =IF($A100=0,0,SUMIF('Week 2 Roster'!$AZ:$AZ,$B100,'Week 2 Roster'!$AQ:$AQ)) -> 0 | AS100: =IF($A100=0,0,SUMIF('Week 2 Roster'!$AZ:$AZ,$B100,'Week 2 Roster'!$AR:$AR)) -> 0 | AT100: =IF($A100=0,0,SUMIF('Week 2 Roster'!$AZ:$AZ,$B100,'Week 2 Roster'!$AS:$AS)) -> 0 | AU100: =SUM(AK100:AP100,AR100:AT100) -> 0 | AW100: ='Week 1 Roster'!A100 | AX100: ='Week 2 Roster'!A100
A101: {=_xlfn.NUMBERVALUE(INDIRECT(TEXT(MIN(IF(($AW$2:$AX$300<>"")*(COUNTIF($B$1:B100,$AW$2:$AX$300)=0),ROW($2:$300)*100+COLUMN($AW:$AX),7^8)),"R0C00"),)&"")} -> 0 | B101: =IF(A101=0,"",_xlfn.NUMBERVALUE(A101)) | C101: =IF($A101=0,"",VLOOKUP($B101,Employees!$A:$G,2,FALSE)) | D101: =IF($A101=0,"",VLOOKUP($B101,Employees!$A:$G,3,FALSE)) | E101: =IF($A101=0,"",VLOOKUP($B101,Employees!$A:$G,5,FALSE)) | F101: =IF($E101="","",ROUNDDOWN(YEARFRAC($E101, 'Week 1 Roster'!$D$1-1, 1), 0)) | G101: =IF($E101="","",ROUNDDOWN(YEARFRAC($E101, 'Week 1 Roster'!$D$1+14, 1), 0)) | H101: =IF($E101="","",IF(AND(F101<21,F101<>G101),TRUE,FALSE)) | I101: =IF($A101=0,"",VLOOKUP($B101,Employees!$A:$G,6,FALSE)) | J101: =IF($A101=0,"",VLOOKUP($B101,Employees!$A:$G,7,FALSE)) | K101: =IF($A101=0,"",IF(ISNA(VLOOKUP(A101,'Week 1 Roster'!A:C,2,0)),VLOOKUP(A101,'Week 2 Roster'!A:C,2,0),VLOOKUP(A101,'Week 1 Roster'!A:C,2,0))) | L101: =IF($A101=0,"",VLOOKUP(K101,Stores!A:B,2,0)) | M101: =Y101+AK101 -> 0 | N101: =Z101+AL101 -> 0 | O101: =AA101+AM101 -> 0 | P101: =AB101+AN101 -> 0 | Q101: =AC101+AO101 -> 0 | R101: =AD101+AP101 -> 0 | S101: =AE101+AQ101 -> 0 | T101: =AF101+AR101 -> 0 | ... V101: =AH101+AT101 -> 0 | W101: =SUM(M101:R101,T101:V101) -> 0 | Y101: =IF($A101=0,0,SUMIF('Week 1 Roster'!$AZ:$AZ,$B101,'Week 1 Roster'!$AE:$AE)) -> 0 | Z101: =IF($A101=0,0,SUMIF('Week 1 Roster'!$AZ:$AZ,$B101,'Week 1 Roster'!$AG:$AG)) -> 0 | AA101: =IF($A101=0,0,SUMIF('Week 1 Roster'!$AZ:$AZ,$B101,'Week 1 Roster'!$AI:$AI)) -> 0 | AB101: =IF($A101=0,0,SUMIF('Week 1 Roster'!$AZ:$AZ,$B101,'Week 1 Roster'!$AK:$AK)) -> 0 | AC101: =IF($A101=0,0,SUMIF('Week 1 Roster'!$AZ:$AZ,$B101,'Week 1 Roster'!$AM:$AM)) -> 0 | AD101: =IF($A101=0,0,SUMIF('Week 1 Roster'!$AZ:$AZ,$B101,'Week 1 Roster'!$AO:$AO)) -> 0 | AE101: =IF($A101=0,0,SUMIF('Week 1 Roster'!$AZ:$AZ,$B101,'Week 1 Roster'!$AP:$AP)) -> 0 | AF101: =IF($A101=0,0,SUMIF('Week 1 Roster'!$AZ:$AZ,$B101,'Week 1 Roster'!$AQ:$AQ)) -> 0 | AG101: =IF($A101=0,0,SUMIF('Week 1 Roster'!$AZ:$AZ,$B101,'Week 1 Roster'!$AR:$AR)) -> 0 | AH101: =IF($A101=0,0,SUMIF('Week 1 Roster'!$AZ:$AZ,$B101,'Week 1 Roster'!$AS:$AS)) -> 0 | AI101: =SUM(Y101:AD101,AF101:AH101) -> 0 | AK101: =IF($A101=0,0,SUMIF('Week 2 Roster'!$AZ:$AZ,$B101,'Week 2 Roster'!$AE:$AE)) -> 0 | AL101: =IF($A101=0,0,SUMIF('Week 2 Roster'!$AZ:$AZ,$B101,'Week 2 Roster'!$AG:$AG)) -> 0 | AM101: =IF($A101=0,0,SUMIF('Week 2 Roster'!$AZ:$AZ,$B101,'Week 2 Roster'!$AI:$AI)) -> 0 | AN101: =IF($A101=0,0,SUMIF('Week 2 Roster'!$AZ:$AZ,$B101,'Week 2 Roster'!$AK:$AK)) -> 0 | AO101: =IF($A101=0,0,SUMIF('Week 2 Roster'!$AZ:$AZ,$B101,'Week 2 Roster'!$AM:$AM)) -> 0 | AP101: =IF($A101=0,0,SUMIF('Week 2 Roster'!$AZ:$AZ,$B101,'Week 2 Roster'!$AO:$AO)) -> 0 | AQ101: =IF($A101=0,0,SUMIF('Week 2 Roster'!$AZ:$AZ,$B101,'Week 2 Roster'!$AP:$AP)) -> 0 | AR101: =IF($A101=0,0,SUMIF('Week 2 Roster'!$AZ:$AZ,$B101,'Week 2 Roster'!$AQ:$AQ)) -> 0 | AS101: =IF($A101=0,0,SUMIF('Week 2 Roster'!$AZ:$AZ,$B101,'Week 2 Roster'!$AR:$AR)) -> 0 | AT101: =IF($A101=0,0,SUMIF('Week 2 Roster'!$AZ:$AZ,$B101,'Week 2 Roster'!$AS:$AS)) -> 0 | AU101: =SUM(AK101:AP101,AR101:AT101) -> 0
A102: {=_xlfn.NUMBERVALUE(INDIRECT(TEXT(MIN(IF(($AW$2:$AX$300<>"")*(COUNTIF($B$1:B101,$AW$2:$AX$300)=0),ROW($2:$300)*100+COLUMN($AW:$AX),7^8)),"R0C00"),)&"")} -> 0 | B102: =IF(A102=0,"",_xlfn.NUMBERVALUE(A102)) | C102: =IF($A102=0,"",VLOOKUP($B102,Employees!$A:$G,2,FALSE)) | D102: =IF($A102=0,"",VLOOKUP($B102,Employees!$A:$G,3,FALSE)) | E102: =IF($A102=0,"",VLOOKUP($B102,Employees!$A:$G,5,FALSE)) | F102: =IF($E102="","",ROUNDDOWN(YEARFRAC($E102, 'Week 1 Roster'!$D$1-1, 1), 0)) | G102: =IF($E102="","",ROUNDDOWN(YEARFRAC($E102, 'Week 1 Roster'!$D$1+14, 1), 0)) | H102: =IF($E102="","",IF(AND(F102<21,F102<>G102),TRUE,FALSE)) | I102: =IF($A102=0,"",VLOOKUP($B102,Employees!$A:$G,6,FALSE)) | J102: =IF($A102=0,"",VLOOKUP($B102,Employees!$A:$G,7,FALSE)) | K102: =IF($A102=0,"",IF(ISNA(VLOOKUP(A102,'Week 1 Roster'!A:C,2,0)),VLOOKUP(A102,'Week 2 Roster'!A:C,2,0),VLOOKUP(A102,'Week 1 Roster'!A:C,2,0))) | L102: =IF($A102=0,"",VLOOKUP(K102,Stores!A:B,2,0)) | M102: =Y102+AK102 -> 0 | N102: =Z102+AL102 -> 0 | O102: =AA102+AM102 -> 0 | P102: =AB102+AN102 -> 0 | Q102: =AC102+AO102 -> 0 | R102: =AD102+AP102 -> 0 | S102: =AE102+AQ102 -> 0 | T102: =AF102+AR102 -> 0 | ... V102: =AH102+AT102 -> 0 | W102: =SUM(M102:R102,T102:V102) -> 0 | Y102: =IF($A102=0,0,SUMIF('Week 1 Roster'!$AZ:$AZ,$B102,'Week 1 Roster'!$AE:$AE)) -> 0 | Z102: =IF($A102=0,0,SUMIF('Week 1 Roster'!$AZ:$AZ,$B102,'Week 1 Roster'!$AG:$AG)) -> 0 | AA102: =IF($A102=0,0,SUMIF('Week 1 Roster'!$AZ:$AZ,$B102,'Week 1 Roster'!$AI:$AI)) -> 0 | AB102: =IF($A102=0,0,SUMIF('Week 1 Roster'!$AZ:$AZ,$B102,'Week 1 Roster'!$AK:$AK)) -> 0 | AC102: =IF($A102=0,0,SUMIF('Week 1 Roster'!$AZ:$AZ,$B102,'Week 1 Roster'!$AM:$AM)) -> 0 | AD102: =IF($A102=0,0,SUMIF('Week 1 Roster'!$AZ:$AZ,$B102,'Week 1 Roster'!$AO:$AO)) -> 0 | AE102: =IF($A102=0,0,SUMIF('Week 1 Roster'!$AZ:$AZ,$B102,'Week 1 Roster'!$AP:$AP)) -> 0 | AF102: =IF($A102=0,0,SUMIF('Week 1 Roster'!$AZ:$AZ,$B102,'Week 1 Roster'!$AQ:$AQ)) -> 0 | AG102: =IF($A102=0,0,SUMIF('Week 1 Roster'!$AZ:$AZ,$B102,'Week 1 Roster'!$AR:$AR)) -> 0 | AH102: =IF($A102=0,0,SUMIF('Week 1 Roster'!$AZ:$AZ,$B102,'Week 1 Roster'!$AS:$AS)) -> 0 | AI102: =SUM(Y102:AD102,AF102:AH102) -> 0 | AK102: =IF($A102=0,0,SUMIF('Week 2 Roster'!$AZ:$AZ,$B102,'Week 2 Roster'!$AE:$AE)) -> 0 | AL102: =IF($A102=0,0,SUMIF('Week 2 Roster'!$AZ:$AZ,$B102,'Week 2 Roster'!$AG:$AG)) -> 0 | AM102: =IF($A102=0,0,SUMIF('Week 2 Roster'!$AZ:$AZ,$B102,'Week 2 Roster'!$AI:$AI)) -> 0 | AN102: =IF($A102=0,0,SUMIF('Week 2 Roster'!$AZ:$AZ,$B102,'Week 2 Roster'!$AK:$AK)) -> 0 | AO102: =IF($A102=0,0,SUMIF('Week 2 Roster'!$AZ:$AZ,$B102,'Week 2 Roster'!$AM:$AM)) -> 0 | AP102: =IF($A102=0,0,SUMIF('Week 2 Roster'!$AZ:$AZ,$B102,'Week 2 Roster'!$AO:$AO)) -> 0 | AQ102: =IF($A102=0,0,SUMIF('Week 2 Roster'!$AZ:$AZ,$B102,'Week 2 Roster'!$AP:$AP)) -> 0 | AR102: =IF($A102=0,0,SUMIF('Week 2 Roster'!$AZ:$AZ,$B102,'Week 2 Roster'!$AQ:$AQ)) -> 0 | AS102: =IF($A102=0,0,SUMIF('Week 2 Roster'!$AZ:$AZ,$B102,'Week 2 Roster'!$AR:$AR)) -> 0 | AT102: =IF($A102=0,0,SUMIF('Week 2 Roster'!$AZ:$AZ,$B102,'Week 2 Roster'!$AS:$AS)) -> 0 | AU102: =SUM(AK102:AP102,AR102:AT102) -> 0
A103: {=_xlfn.NUMBERVALUE(INDIRECT(TEXT(MIN(IF(($AW$2:$AX$300<>"")*(COUNTIF($B$1:B102,$AW$2:$AX$300)=0),ROW($2:$300)*100+COLUMN($AW:$AX),7^8)),"R0C00"),)&"")} -> 0 | B103: =IF(A103=0,"",_xlfn.NUMBERVALUE(A103)) | C103: =IF($A103=0,"",VLOOKUP($B103,Employees!$A:$G,2,FALSE)) | D103: =IF($A103=0,"",VLOOKUP($B103,Employees!$A:$G,3,FALSE)) | E103: =IF($A103=0,"",VLOOKUP($B103,Employees!$A:$G,5,FALSE)) | F103: =IF($E103="","",ROUNDDOWN(YEARFRAC($E103, 'Week 1 Roster'!$D$1-1, 1), 0)) | G103: =IF($E103="","",ROUNDDOWN(YEARFRAC($E103, 'Week 1 Roster'!$D$1+14, 1), 0)) | H103: =IF($E103="","",IF(AND(F103<21,F103<>G103),TRUE,FALSE)) | I103: =IF($A103=0,"",VLOOKUP($B103,Employees!$A:$G,6,FALSE)) | J103: =IF($A103=0,"",VLOOKUP($B103,Employees!$A:$G,7,FALSE)) | K103: =IF($A103=0,"",IF(ISNA(VLOOKUP(A103,'Week 1 Roster'!A:C,2,0)),VLOOKUP(A103,'Week 2 Roster'!A:C,2,0),VLOOKUP(A103,'Week 1 Roster'!A:C,2,0))) | L103: =IF($A103=0,"",VLOOKUP(K103,Stores!A:B,2,0)) | M103: =Y103+AK103 -> 0 | N103: =Z103+AL103 -> 0 | O103: =AA103+AM103 -> 0 | P103: =AB103+AN103 -> 0 | Q103: =AC103+AO103 -> 0 | R103: =AD103+AP103 -> 0 | S103: =AE103+AQ103 -> 0 | T103: =AF103+AR103 -> 0 | ... V103: =AH103+AT103 -> 0 | W103: =SUM(M103:R103,T103:V103) -> 0 | Y103: =IF($A103=0,0,SUMIF('Week 1 Roster'!$AZ:$AZ,$B103,'Week 1 Roster'!$AE:$AE)) -> 0 | Z103: =IF($A103=0,0,SUMIF('Week 1 Roster'!$AZ:$AZ,$B103,'Week 1 Roster'!$AG:$AG)) -> 0 | AA103: =IF($A103=0,0,SUMIF('Week 1 Roster'!$AZ:$AZ,$B103,'Week 1 Roster'!$AI:$AI)) -> 0 | AB103: =IF($A103=0,0,SUMIF('Week 1 Roster'!$AZ:$AZ,$B103,'Week 1 Roster'!$AK:$AK)) -> 0 | AC103: =IF($A103=0,0,SUMIF('Week 1 Roster'!$AZ:$AZ,$B103,'Week 1 Roster'!$AM:$AM)) -> 0 | AD103: =IF($A103=0,0,SUMIF('Week 1 Roster'!$AZ:$AZ,$B103,'Week 1 Roster'!$AO:$AO)) -> 0 | AE103: =IF($A103=0,0,SUMIF('Week 1 Roster'!$AZ:$AZ,$B103,'Week 1 Roster'!$AP:$AP)) -> 0 | AF103: =IF($A103=0,0,SUMIF('Week 1 Roster'!$AZ:$AZ,$B103,'Week 1 Roster'!$AQ:$AQ)) -> 0 | AG103: =IF($A103=0,0,SUMIF('Week 1 Roster'!$AZ:$AZ,$B103,'Week 1 Roster'!$AR:$AR)) -> 0 | AH103: =IF($A103=0,0,SUMIF('Week 1 Roster'!$AZ:$AZ,$B103,'Week 1 Roster'!$AS:$AS)) -> 0 | AI103: =SUM(Y103:AD103,AF103:AH103) -> 0 | AK103: =IF($A103=0,0,SUMIF('Week 2 Roster'!$AZ:$AZ,$B103,'Week 2 Roster'!$AE:$AE)) -> 0 | AL103: =IF($A103=0,0,SUMIF('Week 2 Roster'!$AZ:$AZ,$B103,'Week 2 Roster'!$AG:$AG)) -> 0 | AM103: =IF($A103=0,0,SUMIF('Week 2 Roster'!$AZ:$AZ,$B103,'Week 2 Roster'!$AI:$AI)) -> 0 | AN103: =IF($A103=0,0,SUMIF('Week 2 Roster'!$AZ:$AZ,$B103,'Week 2 Roster'!$AK:$AK)) -> 0 | AO103: =IF($A103=0,0,SUMIF('Week 2 Roster'!$AZ:$AZ,$B103,'Week 2 Roster'!$AM:$AM)) -> 0 | AP103: =IF($A103=0,0,SUMIF('Week 2 Roster'!$AZ:$AZ,$B103,'Week 2 Roster'!$AO:$AO)) -> 0 | AQ103: =IF($A103=0,0,SUMIF('Week 2 Roster'!$AZ:$AZ,$B103,'Week 2 Roster'!$AP:$AP)) -> 0 | AR103: =IF($A103=0,0,SUMIF('Week 2 Roster'!$AZ:$AZ,$B103,'Week 2 Roster'!$AQ:$AQ)) -> 0 | AS103: =IF($A103=0,0,SUMIF('Week 2 Roster'!$AZ:$AZ,$B103,'Week 2 Roster'!$AR:$AR)) -> 0 | AT103: =IF($A103=0,0,SUMIF('Week 2 Roster'!$AZ:$AZ,$B103,'Week 2 Roster'!$AS:$AS)) -> 0 | AU103: =SUM(AK103:AP103,AR103:AT103) -> 0
A104: {=_xlfn.NUMBERVALUE(INDIRECT(TEXT(MIN(IF(($AW$2:$AX$300<>"")*(COUNTIF($B$1:B103,$AW$2:$AX$300)=0),ROW($2:$300)*100+COLUMN($AW:$AX),7^8)),"R0C00"),)&"")} -> 0 | B104: =IF(A104=0,"",_xlfn.NUMBERVALUE(A104)) | C104: =IF($A104=0,"",VLOOKUP($B104,Employees!$A:$G,2,FALSE)) | D104: =IF($A104=0,"",VLOOKUP($B104,Employees!$A:$G,3,FALSE)) | E104: =IF($A104=0,"",VLOOKUP($B104,Employees!$A:$G,5,FALSE)) | F104: =IF($E104="","",ROUNDDOWN(YEARFRAC($E104, 'Week 1 Roster'!$D$1-1, 1), 0)) | G104: =IF($E104="","",ROUNDDOWN(YEARFRAC($E104, 'Week 1 Roster'!$D$1+14, 1), 0)) | H104: =IF($E104="","",IF(AND(F104<21,F104<>G104),TRUE,FALSE)) | I104: =IF($A104=0,"",VLOOKUP($B104,Employees!$A:$G,6,FALSE)) | J104: =IF($A104=0,"",VLOOKUP($B104,Employees!$A:$G,7,FALSE)) | K104: =IF($A104=0,"",IF(ISNA(VLOOKUP(A104,'Week 1 Roster'!A:C,2,0)),VLOOKUP(A104,'Week 2 Roster'!A:C,2,0),VLOOKUP(A104,'Week 1 Roster'!A:C,2,0))) | L104: =IF($A104=0,"",VLOOKUP(K104,Stores!A:B,2,0)) | M104: =Y104+AK104 -> 0 | N104: =Z104+AL104 -> 0 | O104: =AA104+AM104 -> 0 | P104: =AB104+AN104 -> 0 | Q104: =AC104+AO104 -> 0 | R104: =AD104+AP104 -> 0 | S104: =AE104+AQ104 -> 0 | T104: =AF104+AR104 -> 0 | ... V104: =AH104+AT104 -> 0 | W104: =SUM(M104:R104,T104:V104) -> 0 | Y104: =IF($A104=0,0,SUMIF('Week 1 Roster'!$AZ:$AZ,$B104,'Week 1 Roster'!$AE:$AE)) -> 0 | Z104: =IF($A104=0,0,SUMIF('Week 1 Roster'!$AZ:$AZ,$B104,'Week 1 Roster'!$AG:$AG)) -> 0 | AA104: =IF($A104=0,0,SUMIF('Week 1 Roster'!$AZ:$AZ,$B104,'Week 1 Roster'!$AI:$AI)) -> 0 | AB104: =IF($A104=0,0,SUMIF('Week 1 Roster'!$AZ:$AZ,$B104,'Week 1 Roster'!$AK:$AK)) -> 0 | AC104: =IF($A104=0,0,SUMIF('Week 1 Roster'!$AZ:$AZ,$B104,'Week 1 Roster'!$AM:$AM)) -> 0 | AD104: =IF($A104=0,0,SUMIF('Week 1 Roster'!$AZ:$AZ,$B104,'Week 1 Roster'!$AO:$AO)) -> 0 | AE104: =IF($A104=0,0,SUMIF('Week 1 Roster'!$AZ:$AZ,$B104,'Week 1 Roster'!$AP:$AP)) -> 0 | AF104: =IF($A104=0,0,SUMIF('Week 1 Roster'!$AZ:$AZ,$B104,'Week 1 Roster'!$AQ:$AQ)) -> 0 | AG104: =IF($A104=0,0,SUMIF('Week 1 Roster'!$AZ:$AZ,$B104,'Week 1 Roster'!$AR:$AR)) -> 0 | AH104: =IF($A104=0,0,SUMIF('Week 1 Roster'!$AZ:$AZ,$B104,'Week 1 Roster'!$AS:$AS)) -> 0 | AI104: =SUM(Y104:AD104,AF104:AH104) -> 0 | AK104: =IF($A104=0,0,SUMIF('Week 2 Roster'!$AZ:$AZ,$B104,'Week 2 Roster'!$AE:$AE)) -> 0 | AL104: =IF($A104=0,0,SUMIF('Week 2 Roster'!$AZ:$AZ,$B104,'Week 2 Roster'!$AG:$AG)) -> 0 | AM104: =IF($A104=0,0,SUMIF('Week 2 Roster'!$AZ:$AZ,$B104,'Week 2 Roster'!$AI:$AI)) -> 0 | AN104: =IF($A104=0,0,SUMIF('Week 2 Roster'!$AZ:$AZ,$B104,'Week 2 Roster'!$AK:$AK)) -> 0 | AO104: =IF($A104=0,0,SUMIF('Week 2 Roster'!$AZ:$AZ,$B104,'Week 2 Roster'!$AM:$AM)) -> 0 | AP104: =IF($A104=0,0,SUMIF('Week 2 Roster'!$AZ:$AZ,$B104,'Week 2 Roster'!$AO:$AO)) -> 0 | AQ104: =IF($A104=0,0,SUMIF('Week 2 Roster'!$AZ:$AZ,$B104,'Week 2 Roster'!$AP:$AP)) -> 0 | AR104: =IF($A104=0,0,SUMIF('Week 2 Roster'!$AZ:$AZ,$B104,'Week 2 Roster'!$AQ:$AQ)) -> 0 | AS104: =IF($A104=0,0,SUMIF('Week 2 Roster'!$AZ:$AZ,$B104,'Week 2 Roster'!$AR:$AR)) -> 0 | AT104: =IF($A104=0,0,SUMIF('Week 2 Roster'!$AZ:$AZ,$B104,'Week 2 Roster'!$AS:$AS)) -> 0 | AU104: =SUM(AK104:AP104,AR104:AT104) -> 0
A105: {=_xlfn.NUMBERVALUE(INDIRECT(TEXT(MIN(IF(($AW$2:$AX$300<>"")*(COUNTIF($B$1:B104,$AW$2:$AX$300)=0),ROW($2:$300)*100+COLUMN($AW:$AX),7^8)),"R0C00"),)&"")} -> 0 | B105: =IF(A105=0,"",_xlfn.NUMBERVALUE(A105)) | C105: =IF($A105=0,"",VLOOKUP($B105,Employees!$A:$G,2,FALSE)) | D105: =IF($A105=0,"",VLOOKUP($B105,Employees!$A:$G,3,FALSE)) | E105: =IF($A105=0,"",VLOOKUP($B105,Employees!$A:$G,5,FALSE)) | F105: =IF($E105="","",ROUNDDOWN(YEARFRAC($E105, 'Week 1 Roster'!$D$1-1, 1), 0)) | G105: =IF($E105="","",ROUNDDOWN(YEARFRAC($E105, 'Week 1 Roster'!$D$1+14, 1), 0)) | H105: =IF($E105="","",IF(AND(F105<21,F105<>G105),TRUE,FALSE)) | I105: =IF($A105=0,"",VLOOKUP($B105,Employees!$A:$G,6,FALSE)) | J105: =IF($A105=0,"",VLOOKUP($B105,Employees!$A:$G,7,FALSE)) | K105: =IF($A105=0,"",IF(ISNA(VLOOKUP(A105,'Week 1 Roster'!A:C,2,0)),VLOOKUP(A105,'Week 2 Roster'!A:C,2,0),VLOOKUP(A105,'Week 1 Roster'!A:C,2,0))) | L105: =IF($A105=0,"",VLOOKUP(K105,Stores!A:B,2,0)) | M105: =Y105+AK105 -> 0 | N105: =Z105+AL105 -> 0 | O105: =AA105+AM105 -> 0 | P105: =AB105+AN105 -> 0 | Q105: =AC105+AO105 -> 0 | R105: =AD105+AP105 -> 0 | S105: =AE105+AQ105 -> 0 | T105: =AF105+AR105 -> 0 | ... V105: =AH105+AT105 -> 0 | W105: =SUM(M105:R105,T105:V105) -> 0 | Y105: =IF($A105=0,0,SUMIF('Week 1 Roster'!$AZ:$AZ,$B105,'Week 1 Roster'!$AE:$AE)) -> 0 | Z105: =IF($A105=0,0,SUMIF('Week 1 Roster'!$AZ:$AZ,$B105,'Week 1 Roster'!$AG:$AG)) -> 0 | AA105: =IF($A105=0,0,SUMIF('Week 1 Roster'!$AZ:$AZ,$B105,'Week 1 Roster'!$AI:$AI)) -> 0 | AB105: =IF($A105=0,0,SUMIF('Week 1 Roster'!$AZ:$AZ,$B105,'Week 1 Roster'!$AK:$AK)) -> 0 | AC105: =IF($A105=0,0,SUMIF('Week 1 Roster'!$AZ:$AZ,$B105,'Week 1 Roster'!$AM:$AM)) -> 0 | AD105: =IF($A105=0,0,SUMIF('Week 1 Roster'!$AZ:$AZ,$B105,'Week 1 Roster'!$AO:$AO)) -> 0 | AE105: =IF($A105=0,0,SUMIF('Week 1 Roster'!$AZ:$AZ,$B105,'Week 1 Roster'!$AP:$AP)) -> 0 | AF105: =IF($A105=0,0,SUMIF('Week 1 Roster'!$AZ:$AZ,$B105,'Week 1 Roster'!$AQ:$AQ)) -> 0 | AG105: =IF($A105=0,0,SUMIF('Week 1 Roster'!$AZ:$AZ,$B105,'Week 1 Roster'!$AR:$AR)) -> 0 | AH105: =IF($A105=0,0,SUMIF('Week 1 Roster'!$AZ:$AZ,$B105,'Week 1 Roster'!$AS:$AS)) -> 0 | AI105: =SUM(Y105:AD105,AF105:AH105) -> 0 | AK105: =IF($A105=0,0,SUMIF('Week 2 Roster'!$AZ:$AZ,$B105,'Week 2 Roster'!$AE:$AE)) -> 0 | AL105: =IF($A105=0,0,SUMIF('Week 2 Roster'!$AZ:$AZ,$B105,'Week 2 Roster'!$AG:$AG)) -> 0 | AM105: =IF($A105=0,0,SUMIF('Week 2 Roster'!$AZ:$AZ,$B105,'Week 2 Roster'!$AI:$AI)) -> 0 | AN105: =IF($A105=0,0,SUMIF('Week 2 Roster'!$AZ:$AZ,$B105,'Week 2 Roster'!$AK:$AK)) -> 0 | AO105: =IF($A105=0,0,SUMIF('Week 2 Roster'!$AZ:$AZ,$B105,'Week 2 Roster'!$AM:$AM)) -> 0 | AP105: =IF($A105=0,0,SUMIF('Week 2 Roster'!$AZ:$AZ,$B105,'Week 2 Roster'!$AO:$AO)) -> 0 | AQ105: =IF($A105=0,0,SUMIF('Week 2 Roster'!$AZ:$AZ,$B105,'Week 2 Roster'!$AP:$AP)) -> 0 | AR105: =IF($A105=0,0,SUMIF('Week 2 Roster'!$AZ:$AZ,$B105,'Week 2 Roster'!$AQ:$AQ)) -> 0 | AS105: =IF($A105=0,0,SUMIF('Week 2 Roster'!$AZ:$AZ,$B105,'Week 2 Roster'!$AR:$AR)) -> 0 | AT105: =IF($A105=0,0,SUMIF('Week 2 Roster'!$AZ:$AZ,$B105,'Week 2 Roster'!$AS:$AS)) -> 0 | AU105: =SUM(AK105:AP105,AR105:AT105) -> 0
A106: {=_xlfn.NUMBERVALUE(INDIRECT(TEXT(MIN(IF(($AW$2:$AX$300<>"")*(COUNTIF($B$1:B105,$AW$2:$AX$300)=0),ROW($2:$300)*100+COLUMN($AW:$AX),7^8)),"R0C00"),)&"")} -> 0 | B106: =IF(A106=0,"",_xlfn.NUMBERVALUE(A106)) | C106: =IF($A106=0,"",VLOOKUP($B106,Employees!$A:$G,2,FALSE)) | D106: =IF($A106=0,"",VLOOKUP($B106,Employees!$A:$G,3,FALSE)) | E106: =IF($A106=0,"",VLOOKUP($B106,Employees!$A:$G,5,FALSE)) | F106: =IF($E106="","",ROUNDDOWN(YEARFRAC($E106, 'Week 1 Roster'!$D$1-1, 1), 0)) | G106: =IF($E106="","",ROUNDDOWN(YEARFRAC($E106, 'Week 1 Roster'!$D$1+14, 1), 0)) | H106: =IF($E106="","",IF(AND(F106<21,F106<>G106),TRUE,FALSE)) | I106: =IF($A106=0,"",VLOOKUP($B106,Employees!$A:$G,6,FALSE)) | J106: =IF($A106=0,"",VLOOKUP($B106,Employees!$A:$G,7,FALSE)) | K106: =IF($A106=0,"",IF(ISNA(VLOOKUP(A106,'Week 1 Roster'!A:C,2,0)),VLOOKUP(A106,'Week 2 Roster'!A:C,2,0),VLOOKUP(A106,'Week 1 Roster'!A:C,2,0))) | L106: =IF($A106=0,"",VLOOKUP(K106,Stores!A:B,2,0)) | M106: =Y106+AK106 -> 0 | N106: =Z106+AL106 -> 0 | O106: =AA106+AM106 -> 0 | P106: =AB106+AN106 -> 0 | Q106: =AC106+AO106 -> 0 | R106: =AD106+AP106 -> 0 | S106: =AE106+AQ106 -> 0 | T106: =AF106+AR106 -> 0 | ... V106: =AH106+AT106 -> 0 | W106: =SUM(M106:R106,T106:V106) -> 0 | Y106: =IF($A106=0,0,SUMIF('Week 1 Roster'!$AZ:$AZ,$B106,'Week 1 Roster'!$AE:$AE)) -> 0 | Z106: =IF($A106=0,0,SUMIF('Week 1 Roster'!$AZ:$AZ,$B106,'Week 1 Roster'!$AG:$AG)) -> 0 | AA106: =IF($A106=0,0,SUMIF('Week 1 Roster'!$AZ:$AZ,$B106,'Week 1 Roster'!$AI:$AI)) -> 0 | AB106: =IF($A106=0,0,SUMIF('Week 1 Roster'!$AZ:$AZ,$B106,'Week 1 Roster'!$AK:$AK)) -> 0 | AC106: =IF($A106=0,0,SUMIF('Week 1 Roster'!$AZ:$AZ,$B106,'Week 1 Roster'!$AM:$AM)) -> 0 | AD106: =IF($A106=0,0,SUMIF('Week 1 Roster'!$AZ:$AZ,$B106,'Week 1 Roster'!$AO:$AO)) -> 0 | AE106: =IF($A106=0,0,SUMIF('Week 1 Roster'!$AZ:$AZ,$B106,'Week 1 Roster'!$AP:$AP)) -> 0 | AF106: =IF($A106=0,0,SUMIF('Week 1 Roster'!$AZ:$AZ,$B106,'Week 1 Roster'!$AQ:$AQ)) -> 0 | AG106: =IF($A106=0,0,SUMIF('Week 1 Roster'!$AZ:$AZ,$B106,'Week 1 Roster'!$AR:$AR)) -> 0 | AH106: =IF($A106=0,0,SUMIF('Week 1 Roster'!$AZ:$AZ,$B106,'Week 1 Roster'!$AS:$AS)) -> 0 | AI106: =SUM(Y106:AD106,AF106:AH106) -> 0 | AK106: =IF($A106=0,0,SUMIF('Week 2 Roster'!$AZ:$AZ,$B106,'Week 2 Roster'!$AE:$AE)) -> 0 | AL106: =IF($A106=0,0,SUMIF('Week 2 Roster'!$AZ:$AZ,$B106,'Week 2 Roster'!$AG:$AG)) -> 0 | AM106: =IF($A106=0,0,SUMIF('Week 2 Roster'!$AZ:$AZ,$B106,'Week 2 Roster'!$AI:$AI)) -> 0 | AN106: =IF($A106=0,0,SUMIF('Week 2 Roster'!$AZ:$AZ,$B106,'Week 2 Roster'!$AK:$AK)) -> 0 | AO106: =IF($A106=0,0,SUMIF('Week 2 Roster'!$AZ:$AZ,$B106,'Week 2 Roster'!$AM:$AM)) -> 0 | AP106: =IF($A106=0,0,SUMIF('Week 2 Roster'!$AZ:$AZ,$B106,'Week 2 Roster'!$AO:$AO)) -> 0 | AQ106: =IF($A106=0,0,SUMIF('Week 2 Roster'!$AZ:$AZ,$B106,'Week 2 Roster'!$AP:$AP)) -> 0 | AR106: =IF($A106=0,0,SUMIF('Week 2 Roster'!$AZ:$AZ,$B106,'Week 2 Roster'!$AQ:$AQ)) -> 0 | AS106: =IF($A106=0,0,SUMIF('Week 2 Roster'!$AZ:$AZ,$B106,'Week 2 Roster'!$AR:$AR)) -> 0 | AT106: =IF($A106=0,0,SUMIF('Week 2 Roster'!$AZ:$AZ,$B106,'Week 2 Roster'!$AS:$AS)) -> 0 | AU106: =SUM(AK106:AP106,AR106:AT106) -> 0
A107: {=_xlfn.NUMBERVALUE(INDIRECT(TEXT(MIN(IF(($AW$2:$AX$300<>"")*(COUNTIF($B$1:B106,$AW$2:$AX$300)=0),ROW($2:$300)*100+COLUMN($AW:$AX),7^8)),"R0C00"),)&"")} -> 0 | B107: =IF(A107=0,"",_xlfn.NUMBERVALUE(A107)) | C107: =IF($A107=0,"",VLOOKUP($B107,Employees!$A:$G,2,FALSE)) | D107: =IF($A107=0,"",VLOOKUP($B107,Employees!$A:$G,3,FALSE)) | E107: =IF($A107=0,"",VLOOKUP($B107,Employees!$A:$G,5,FALSE)) | F107: =IF($E107="","",ROUNDDOWN(YEARFRAC($E107, 'Week 1 Roster'!$D$1-1, 1), 0)) | G107: =IF($E107="","",ROUNDDOWN(YEARFRAC($E107, 'Week 1 Roster'!$D$1+14, 1), 0)) | H107: =IF($E107="","",IF(AND(F107<21,F107<>G107),TRUE,FALSE)) | I107: =IF($A107=0,"",VLOOKUP($B107,Employees!$A:$G,6,FALSE)) | J107: =IF($A107=0,"",VLOOKUP($B107,Employees!$A:$G,7,FALSE)) | K107: =IF($A107=0,"",IF(ISNA(VLOOKUP(A107,'Week 1 Roster'!A:C,2,0)),VLOOKUP(A107,'Week 2 Roster'!A:C,2,0),VLOOKUP(A107,'Week 1 Roster'!A:C,2,0))) | L107: =IF($A107=0,"",VLOOKUP(K107,Stores!A:B,2,0)) | M107: =Y107+AK107 -> 0 | N107: =Z107+AL107 -> 0 | O107: =AA107+AM107 -> 0 | P107: =AB107+AN107 -> 0 | Q107: =AC107+AO107 -> 0 | R107: =AD107+AP107 -> 0 | S107: =AE107+AQ107 -> 0 | T107: =AF107+AR107 -> 0 | ... V107: =AH107+AT107 -> 0 | W107: =SUM(M107:R107,T107:V107) -> 0 | Y107: =IF($A107=0,0,SUMIF('Week 1 Roster'!$AZ:$AZ,$B107,'Week 1 Roster'!$AE:$AE)) -> 0 | Z107: =IF($A107=0,0,SUMIF('Week 1 Roster'!$AZ:$AZ,$B107,'Week 1 Roster'!$AG:$AG)) -> 0 | AA107: =IF($A107=0,0,SUMIF('Week 1 Roster'!$AZ:$AZ,$B107,'Week 1 Roster'!$AI:$AI)) -> 0 | AB107: =IF($A107=0,0,SUMIF('Week 1 Roster'!$AZ:$AZ,$B107,'Week 1 Roster'!$AK:$AK)) -> 0 | AC107: =IF($A107=0,0,SUMIF('Week 1 Roster'!$AZ:$AZ,$B107,'Week 1 Roster'!$AM:$AM)) -> 0 | AD107: =IF($A107=0,0,SUMIF('Week 1 Roster'!$AZ:$AZ,$B107,'Week 1 Roster'!$AO:$AO)) -> 0 | AE107: =IF($A107=0,0,SUMIF('Week 1 Roster'!$AZ:$AZ,$B107,'Week 1 Roster'!$AP:$AP)) -> 0 | AF107: =IF($A107=0,0,SUMIF('Week 1 Roster'!$AZ:$AZ,$B107,'Week 1 Roster'!$AQ:$AQ)) -> 0 | AG107: =IF($A107=0,0,SUMIF('Week 1 Roster'!$AZ:$AZ,$B107,'Week 1 Roster'!$AR:$AR)) -> 0 | AH107: =IF($A107=0,0,SUMIF('Week 1 Roster'!$AZ:$AZ,$B107,'Week 1 Roster'!$AS:$AS)) -> 0 | AI107: =SUM(Y107:AD107,AF107:AH107) -> 0 | AK107: =IF($A107=0,0,SUMIF('Week 2 Roster'!$AZ:$AZ,$B107,'Week 2 Roster'!$AE:$AE)) -> 0 | AL107: =IF($A107=0,0,SUMIF('Week 2 Roster'!$AZ:$AZ,$B107,'Week 2 Roster'!$AG:$AG)) -> 0 | AM107: =IF($A107=0,0,SUMIF('Week 2 Roster'!$AZ:$AZ,$B107,'Week 2 Roster'!$AI:$AI)) -> 0 | AN107: =IF($A107=0,0,SUMIF('Week 2 Roster'!$AZ:$AZ,$B107,'Week 2 Roster'!$AK:$AK)) -> 0 | AO107: =IF($A107=0,0,SUMIF('Week 2 Roster'!$AZ:$AZ,$B107,'Week 2 Roster'!$AM:$AM)) -> 0 | AP107: =IF($A107=0,0,SUMIF('Week 2 Roster'!$AZ:$AZ,$B107,'Week 2 Roster'!$AO:$AO)) -> 0 | AQ107: =IF($A107=0,0,SUMIF('Week 2 Roster'!$AZ:$AZ,$B107,'Week 2 Roster'!$AP:$AP)) -> 0 | AR107: =IF($A107=0,0,SUMIF('Week 2 Roster'!$AZ:$AZ,$B107,'Week 2 Roster'!$AQ:$AQ)) -> 0 | AS107: =IF($A107=0,0,SUMIF('Week 2 Roster'!$AZ:$AZ,$B107,'Week 2 Roster'!$AR:$AR)) -> 0 | AT107: =IF($A107=0,0,SUMIF('Week 2 Roster'!$AZ:$AZ,$B107,'Week 2 Roster'!$AS:$AS)) -> 0 | AU107: =SUM(AK107:AP107,AR107:AT107) -> 0
A108: {=_xlfn.NUMBERVALUE(INDIRECT(TEXT(MIN(IF(($AW$2:$AX$300<>"")*(COUNTIF($B$1:B107,$AW$2:$AX$300)=0),ROW($2:$300)*100+COLUMN($AW:$AX),7^8)),"R0C00"),)&"")} -> 0 | B108: =IF(A108=0,"",_xlfn.NUMBERVALUE(A108)) | C108: =IF($A108=0,"",VLOOKUP($B108,Employees!$A:$G,2,FALSE)) | D108: =IF($A108=0,"",VLOOKUP($B108,Employees!$A:$G,3,FALSE)) | E108: =IF($A108=0,"",VLOOKUP($B108,Employees!$A:$G,5,FALSE)) | F108: =IF($E108="","",ROUNDDOWN(YEARFRAC($E108, 'Week 1 Roster'!$D$1-1, 1), 0)) | G108: =IF($E108="","",ROUNDDOWN(YEARFRAC($E108, 'Week 1 Roster'!$D$1+14, 1), 0)) | H108: =IF($E108="","",IF(AND(F108<21,F108<>G108),TRUE,FALSE)) | I108: =IF($A108=0,"",VLOOKUP($B108,Employees!$A:$G,6,FALSE)) | J108: =IF($A108=0,"",VLOOKUP($B108,Employees!$A:$G,7,FALSE)) | K108: =IF($A108=0,"",IF(ISNA(VLOOKUP(A108,'Week 1 Roster'!A:C,2,0)),VLOOKUP(A108,'Week 2 Roster'!A:C,2,0),VLOOKUP(A108,'Week 1 Roster'!A:C,2,0))) | L108: =IF($A108=0,"",VLOOKUP(K108,Stores!A:B,2,0)) | M108: =Y108+AK108 -> 0 | N108: =Z108+AL108 -> 0 | O108: =AA108+AM108 -> 0 | P108: =AB108+AN108 -> 0 | Q108: =AC108+AO108 -> 0 | R108: =AD108+AP108 -> 0 | S108: =AE108+AQ108 -> 0 | T108: =AF108+AR108 -> 0 | ... V108: =AH108+AT108 -> 0 | W108: =SUM(M108:R108,T108:V108) -> 0 | Y108: =IF($A108=0,0,SUMIF('Week 1 Roster'!$AZ:$AZ,$B108,'Week 1 Roster'!$AE:$AE)) -> 0 | Z108: =IF($A108=0,0,SUMIF('Week 1 Roster'!$AZ:$AZ,$B108,'Week 1 Roster'!$AG:$AG)) -> 0 | AA108: =IF($A108=0,0,SUMIF('Week 1 Roster'!$AZ:$AZ,$B108,'Week 1 Roster'!$AI:$AI)) -> 0 | AB108: =IF($A108=0,0,SUMIF('Week 1 Roster'!$AZ:$AZ,$B108,'Week 1 Roster'!$AK:$AK)) -> 0 | AC108: =IF($A108=0,0,SUMIF('Week 1 Roster'!$AZ:$AZ,$B108,'Week 1 Roster'!$AM:$AM)) -> 0 | AD108: =IF($A108=0,0,SUMIF('Week 1 Roster'!$AZ:$AZ,$B108,'Week 1 Roster'!$AO:$AO)) -> 0 | AE108: =IF($A108=0,0,SUMIF('Week 1 Roster'!$AZ:$AZ,$B108,'Week 1 Roster'!$AP:$AP)) -> 0 | AF108: =IF($A108=0,0,SUMIF('Week 1 Roster'!$AZ:$AZ,$B108,'Week 1 Roster'!$AQ:$AQ)) -> 0 | AG108: =IF($A108=0,0,SUMIF('Week 1 Roster'!$AZ:$AZ,$B108,'Week 1 Roster'!$AR:$AR)) -> 0 | AH108: =IF($A108=0,0,SUMIF('Week 1 Roster'!$AZ:$AZ,$B108,'Week 1 Roster'!$AS:$AS)) -> 0 | AI108: =SUM(Y108:AD108,AF108:AH108) -> 0 | AK108: =IF($A108=0,0,SUMIF('Week 2 Roster'!$AZ:$AZ,$B108,'Week 2 Roster'!$AE:$AE)) -> 0 | AL108: =IF($A108=0,0,SUMIF('Week 2 Roster'!$AZ:$AZ,$B108,'Week 2 Roster'!$AG:$AG)) -> 0 | AM108: =IF($A108=0,0,SUMIF('Week 2 Roster'!$AZ:$AZ,$B108,'Week 2 Roster'!$AI:$AI)) -> 0 | AN108: =IF($A108=0,0,SUMIF('Week 2 Roster'!$AZ:$AZ,$B108,'Week 2 Roster'!$AK:$AK)) -> 0 | AO108: =IF($A108=0,0,SUMIF('Week 2 Roster'!$AZ:$AZ,$B108,'Week 2 Roster'!$AM:$AM)) -> 0 | AP108: =IF($A108=0,0,SUMIF('Week 2 Roster'!$AZ:$AZ,$B108,'Week 2 Roster'!$AO:$AO)) -> 0 | AQ108: =IF($A108=0,0,SUMIF('Week 2 Roster'!$AZ:$AZ,$B108,'Week 2 Roster'!$AP:$AP)) -> 0 | AR108: =IF($A108=0,0,SUMIF('Week 2 Roster'!$AZ:$AZ,$B108,'Week 2 Roster'!$AQ:$AQ)) -> 0 | AS108: =IF($A108=0,0,SUMIF('Week 2 Roster'!$AZ:$AZ,$B108,'Week 2 Roster'!$AR:$AR)) -> 0 | AT108: =IF($A108=0,0,SUMIF('Week 2 Roster'!$AZ:$AZ,$B108,'Week 2 Roster'!$AS:$AS)) -> 0 | AU108: =SUM(AK108:AP108,AR108:AT108) -> 0
A109: {=_xlfn.NUMBERVALUE(INDIRECT(TEXT(MIN(IF(($AW$2:$AX$300<>"")*(COUNTIF($B$1:B108,$AW$2:$AX$300)=0),ROW($2:$300)*100+COLUMN($AW:$AX),7^8)),"R0C00"),)&"")} -> 0 | B109: =IF(A109=0,"",_xlfn.NUMBERVALUE(A109)) | C109: =IF($A109=0,"",VLOOKUP($B109,Employees!$A:$G,2,FALSE)) | D109: =IF($A109=0,"",VLOOKUP($B109,Employees!$A:$G,3,FALSE)) | E109: =IF($A109=0,"",VLOOKUP($B109,Employees!$A:$G,5,FALSE)) | F109: =IF($E109="","",ROUNDDOWN(YEARFRAC($E109, 'Week 1 Roster'!$D$1-1, 1), 0)) | G109: =IF($E109="","",ROUNDDOWN(YEARFRAC($E109, 'Week 1 Roster'!$D$1+14, 1), 0)) | H109: =IF($E109="","",IF(AND(F109<21,F109<>G109),TRUE,FALSE)) | I109: =IF($A109=0,"",VLOOKUP($B109,Employees!$A:$G,6,FALSE)) | J109: =IF($A109=0,"",VLOOKUP($B109,Employees!$A:$G,7,FALSE)) | K109: =IF($A109=0,"",IF(ISNA(VLOOKUP(A109,'Week 1 Roster'!A:C,2,0)),VLOOKUP(A109,'Week 2 Roster'!A:C,2,0),VLOOKUP(A109,'Week 1 Roster'!A:C,2,0))) | L109: =IF($A109=0,"",VLOOKUP(K109,Stores!A:B,2,0)) | M109: =Y109+AK109 -> 0 | N109: =Z109+AL109 -> 0 | O109: =AA109+AM109 -> 0 | P109: =AB109+AN109 -> 0 | Q109: =AC109+AO109 -> 0 | R109: =AD109+AP109 -> 0 | S109: =AE109+AQ109 -> 0 | T109: =AF109+AR109 -> 0 | ... V109: =AH109+AT109 -> 0 | W109: =SUM(M109:R109,T109:V109) -> 0 | Y109: =IF($A109=0,0,SUMIF('Week 1 Roster'!$AZ:$AZ,$B109,'Week 1 Roster'!$AE:$AE)) -> 0 | Z109: =IF($A109=0,0,SUMIF('Week 1 Roster'!$AZ:$AZ,$B109,'Week 1 Roster'!$AG:$AG)) -> 0 | AA109: =IF($A109=0,0,SUMIF('Week 1 Roster'!$AZ:$AZ,$B109,'Week 1 Roster'!$AI:$AI)) -> 0 | AB109: =IF($A109=0,0,SUMIF('Week 1 Roster'!$AZ:$AZ,$B109,'Week 1 Roster'!$AK:$AK)) -> 0 | AC109: =IF($A109=0,0,SUMIF('Week 1 Roster'!$AZ:$AZ,$B109,'Week 1 Roster'!$AM:$AM)) -> 0 | AD109: =IF($A109=0,0,SUMIF('Week 1 Roster'!$AZ:$AZ,$B109,'Week 1 Roster'!$AO:$AO)) -> 0 | AE109: =IF($A109=0,0,SUMIF('Week 1 Roster'!$AZ:$AZ,$B109,'Week 1 Roster'!$AP:$AP)) -> 0 | AF109: =IF($A109=0,0,SUMIF('Week 1 Roster'!$AZ:$AZ,$B109,'Week 1 Roster'!$AQ:$AQ)) -> 0 | AG109: =IF($A109=0,0,SUMIF('Week 1 Roster'!$AZ:$AZ,$B109,'Week 1 Roster'!$AR:$AR)) -> 0 | AH109: =IF($A109=0,0,SUMIF('Week 1 Roster'!$AZ:$AZ,$B109,'Week 1 Roster'!$AS:$AS)) -> 0 | AI109: =SUM(Y109:AD109,AF109:AH109) -> 0 | AK109: =IF($A109=0,0,SUMIF('Week 2 Roster'!$AZ:$AZ,$B109,'Week 2 Roster'!$AE:$AE)) -> 0 | AL109: =IF($A109=0,0,SUMIF('Week 2 Roster'!$AZ:$AZ,$B109,'Week 2 Roster'!$AG:$AG)) -> 0 | AM109: =IF($A109=0,0,SUMIF('Week 2 Roster'!$AZ:$AZ,$B109,'Week 2 Roster'!$AI:$AI)) -> 0 | AN109: =IF($A109=0,0,SUMIF('Week 2 Roster'!$AZ:$AZ,$B109,'Week 2 Roster'!$AK:$AK)) -> 0 | AO109: =IF($A109=0,0,SUMIF('Week 2 Roster'!$AZ:$AZ,$B109,'Week 2 Roster'!$AM:$AM)) -> 0 | AP109: =IF($A109=0,0,SUMIF('Week 2 Roster'!$AZ:$AZ,$B109,'Week 2 Roster'!$AO:$AO)) -> 0 | AQ109: =IF($A109=0,0,SUMIF('Week 2 Roster'!$AZ:$AZ,$B109,'Week 2 Roster'!$AP:$AP)) -> 0 | AR109: =IF($A109=0,0,SUMIF('Week 2 Roster'!$AZ:$AZ,$B109,'Week 2 Roster'!$AQ:$AQ)) -> 0 | AS109: =IF($A109=0,0,SUMIF('Week 2 Roster'!$AZ:$AZ,$B109,'Week 2 Roster'!$AR:$AR)) -> 0 | AT109: =IF($A109=0,0,SUMIF('Week 2 Roster'!$AZ:$AZ,$B109,'Week 2 Roster'!$AS:$AS)) -> 0 | AU109: =SUM(AK109:AP109,AR109:AT109) -> 0
A110: {=_xlfn.NUMBERVALUE(INDIRECT(TEXT(MIN(IF(($AW$2:$AX$300<>"")*(COUNTIF($B$1:B109,$AW$2:$AX$300)=0),ROW($2:$300)*100+COLUMN($AW:$AX),7^8)),"R0C00"),)&"")} -> 0 | B110: =IF(A110=0,"",_xlfn.NUMBERVALUE(A110)) | C110: =IF($A110=0,"",VLOOKUP($B110,Employees!$A:$G,2,FALSE)) | D110: =IF($A110=0,"",VLOOKUP($B110,Employees!$A:$G,3,FALSE)) | E110: =IF($A110=0,"",VLOOKUP($B110,Employees!$A:$G,5,FALSE)) | F110: =IF($E110="","",ROUNDDOWN(YEARFRAC($E110, 'Week 1 Roster'!$D$1-1, 1), 0)) | G110: =IF($E110="","",ROUNDDOWN(YEARFRAC($E110, 'Week 1 Roster'!$D$1+14, 1), 0)) | H110: =IF($E110="","",IF(AND(F110<21,F110<>G110),TRUE,FALSE)) | I110: =IF($A110=0,"",VLOOKUP($B110,Employees!$A:$G,6,FALSE)) | J110: =IF($A110=0,"",VLOOKUP($B110,Employees!$A:$G,7,FALSE)) | K110: =IF($A110=0,"",IF(ISNA(VLOOKUP(A110,'Week 1 Roster'!A:C,2,0)),VLOOKUP(A110,'Week 2 Roster'!A:C,2,0),VLOOKUP(A110,'Week 1 Roster'!A:C,2,0))) | L110: =IF($A110=0,"",VLOOKUP(K110,Stores!A:B,2,0)) | M110: =Y110+AK110 -> 0 | N110: =Z110+AL110 -> 0 | O110: =AA110+AM110 -> 0 | P110: =AB110+AN110 -> 0 | Q110: =AC110+AO110 -> 0 | R110: =AD110+AP110 -> 0 | S110: =AE110+AQ110 -> 0 | T110: =AF110+AR110 -> 0 | ... V110: =AH110+AT110 -> 0 | W110: =SUM(M110:R110,T110:V110) -> 0 | Y110: =IF($A110=0,0,SUMIF('Week 1 Roster'!$AZ:$AZ,$B110,'Week 1 Roster'!$AE:$AE)) -> 0 | Z110: =IF($A110=0,0,SUMIF('Week 1 Roster'!$AZ:$AZ,$B110,'Week 1 Roster'!$AG:$AG)) -> 0 | AA110: =IF($A110=0,0,SUMIF('Week 1 Roster'!$AZ:$AZ,$B110,'Week 1 Roster'!$AI:$AI)) -> 0 | AB110: =IF($A110=0,0,SUMIF('Week 1 Roster'!$AZ:$AZ,$B110,'Week 1 Roster'!$AK:$AK)) -> 0 | AC110: =IF($A110=0,0,SUMIF('Week 1 Roster'!$AZ:$AZ,$B110,'Week 1 Roster'!$AM:$AM)) -> 0 | AD110: =IF($A110=0,0,SUMIF('Week 1 Roster'!$AZ:$AZ,$B110,'Week 1 Roster'!$AO:$AO)) -> 0 | AE110: =IF($A110=0,0,SUMIF('Week 1 Roster'!$AZ:$AZ,$B110,'Week 1 Roster'!$AP:$AP)) -> 0 | AF110: =IF($A110=0,0,SUMIF('Week 1 Roster'!$AZ:$AZ,$B110,'Week 1 Roster'!$AQ:$AQ)) -> 0 | AG110: =IF($A110=0,0,SUMIF('Week 1 Roster'!$AZ:$AZ,$B110,'Week 1 Roster'!$AR:$AR)) -> 0 | AH110: =IF($A110=0,0,SUMIF('Week 1 Roster'!$AZ:$AZ,$B110,'Week 1 Roster'!$AS:$AS)) -> 0 | AI110: =SUM(Y110:AD110,AF110:AH110) -> 0 | AK110: =IF($A110=0,0,SUMIF('Week 2 Roster'!$AZ:$AZ,$B110,'Week 2 Roster'!$AE:$AE)) -> 0 | AL110: =IF($A110=0,0,SUMIF('Week 2 Roster'!$AZ:$AZ,$B110,'Week 2 Roster'!$AG:$AG)) -> 0 | AM110: =IF($A110=0,0,SUMIF('Week 2 Roster'!$AZ:$AZ,$B110,'Week 2 Roster'!$AI:$AI)) -> 0 | AN110: =IF($A110=0,0,SUMIF('Week 2 Roster'!$AZ:$AZ,$B110,'Week 2 Roster'!$AK:$AK)) -> 0 | AO110: =IF($A110=0,0,SUMIF('Week 2 Roster'!$AZ:$AZ,$B110,'Week 2 Roster'!$AM:$AM)) -> 0 | AP110: =IF($A110=0,0,SUMIF('Week 2 Roster'!$AZ:$AZ,$B110,'Week 2 Roster'!$AO:$AO)) -> 0 | AQ110: =IF($A110=0,0,SUMIF('Week 2 Roster'!$AZ:$AZ,$B110,'Week 2 Roster'!$AP:$AP)) -> 0 | AR110: =IF($A110=0,0,SUMIF('Week 2 Roster'!$AZ:$AZ,$B110,'Week 2 Roster'!$AQ:$AQ)) -> 0 | AS110: =IF($A110=0,0,SUMIF('Week 2 Roster'!$AZ:$AZ,$B110,'Week 2 Roster'!$AR:$AR)) -> 0 | AT110: =IF($A110=0,0,SUMIF('Week 2 Roster'!$AZ:$AZ,$B110,'Week 2 Roster'!$AS:$AS)) -> 0 | AU110: =SUM(AK110:AP110,AR110:AT110) -> 0
A111: {=_xlfn.NUMBERVALUE(INDIRECT(TEXT(MIN(IF(($AW$2:$AX$300<>"")*(COUNTIF($B$1:B110,$AW$2:$AX$300)=0),ROW($2:$300)*100+COLUMN($AW:$AX),7^8)),"R0C00"),)&"")} -> 0 | B111: =IF(A111=0,"",_xlfn.NUMBERVALUE(A111)) | C111: =IF($A111=0,"",VLOOKUP($B111,Employees!$A:$G,2,FALSE)) | D111: =IF($A111=0,"",VLOOKUP($B111,Employees!$A:$G,3,FALSE)) | E111: =IF($A111=0,"",VLOOKUP($B111,Employees!$A:$G,5,FALSE)) | F111: =IF($E111="","",ROUNDDOWN(YEARFRAC($E111, 'Week 1 Roster'!$D$1-1, 1), 0)) | G111: =IF($E111="","",ROUNDDOWN(YEARFRAC($E111, 'Week 1 Roster'!$D$1+14, 1), 0)) | H111: =IF($E111="","",IF(AND(F111<21,F111<>G111),TRUE,FALSE)) | I111: =IF($A111=0,"",VLOOKUP($B111,Employees!$A:$G,6,FALSE)) | J111: =IF($A111=0,"",VLOOKUP($B111,Employees!$A:$G,7,FALSE)) | K111: =IF($A111=0,"",IF(ISNA(VLOOKUP(A111,'Week 1 Roster'!A:C,2,0)),VLOOKUP(A111,'Week 2 Roster'!A:C,2,0),VLOOKUP(A111,'Week 1 Roster'!A:C,2,0))) | L111: =IF($A111=0,"",VLOOKUP(K111,Stores!A:B,2,0)) | M111: =Y111+AK111 -> 0 | N111: =Z111+AL111 -> 0 | O111: =AA111+AM111 -> 0 | P111: =AB111+AN111 -> 0 | Q111: =AC111+AO111 -> 0 | R111: =AD111+AP111 -> 0 | S111: =AE111+AQ111 -> 0 | T111: =AF111+AR111 -> 0 | ... V111: =AH111+AT111 -> 0 | W111: =SUM(M111:R111,T111:V111) -> 0 | Y111: =IF($A111=0,0,SUMIF('Week 1 Roster'!$AZ:$AZ,$B111,'Week 1 Roster'!$AE:$AE)) -> 0 | Z111: =IF($A111=0,0,SUMIF('Week 1 Roster'!$AZ:$AZ,$B111,'Week 1 Roster'!$AG:$AG)) -> 0 | AA111: =IF($A111=0,0,SUMIF('Week 1 Roster'!$AZ:$AZ,$B111,'Week 1 Roster'!$AI:$AI)) -> 0 | AB111: =IF($A111=0,0,SUMIF('Week 1 Roster'!$AZ:$AZ,$B111,'Week 1 Roster'!$AK:$AK)) -> 0 | AC111: =IF($A111=0,0,SUMIF('Week 1 Roster'!$AZ:$AZ,$B111,'Week 1 Roster'!$AM:$AM)) -> 0 | AD111: =IF($A111=0,0,SUMIF('Week 1 Roster'!$AZ:$AZ,$B111,'Week 1 Roster'!$AO:$AO)) -> 0 | AE111: =IF($A111=0,0,SUMIF('Week 1 Roster'!$AZ:$AZ,$B111,'Week 1 Roster'!$AP:$AP)) -> 0 | AF111: =IF($A111=0,0,SUMIF('Week 1 Roster'!$AZ:$AZ,$B111,'Week 1 Roster'!$AQ:$AQ)) -> 0 | AG111: =IF($A111=0,0,SUMIF('Week 1 Roster'!$AZ:$AZ,$B111,'Week 1 Roster'!$AR:$AR)) -> 0 | AH111: =IF($A111=0,0,SUMIF('Week 1 Roster'!$AZ:$AZ,$B111,'Week 1 Roster'!$AS:$AS)) -> 0 | AI111: =SUM(Y111:AD111,AF111:AH111) -> 0 | AK111: =IF($A111=0,0,SUMIF('Week 2 Roster'!$AZ:$AZ,$B111,'Week 2 Roster'!$AE:$AE)) -> 0 | AL111: =IF($A111=0,0,SUMIF('Week 2 Roster'!$AZ:$AZ,$B111,'Week 2 Roster'!$AG:$AG)) -> 0 | AM111: =IF($A111=0,0,SUMIF('Week 2 Roster'!$AZ:$AZ,$B111,'Week 2 Roster'!$AI:$AI)) -> 0 | AN111: =IF($A111=0,0,SUMIF('Week 2 Roster'!$AZ:$AZ,$B111,'Week 2 Roster'!$AK:$AK)) -> 0 | AO111: =IF($A111=0,0,SUMIF('Week 2 Roster'!$AZ:$AZ,$B111,'Week 2 Roster'!$AM:$AM)) -> 0 | AP111: =IF($A111=0,0,SUMIF('Week 2 Roster'!$AZ:$AZ,$B111,'Week 2 Roster'!$AO:$AO)) -> 0 | AQ111: =IF($A111=0,0,SUMIF('Week 2 Roster'!$AZ:$AZ,$B111,'Week 2 Roster'!$AP:$AP)) -> 0 | AR111: =IF($A111=0,0,SUMIF('Week 2 Roster'!$AZ:$AZ,$B111,'Week 2 Roster'!$AQ:$AQ)) -> 0 | AS111: =IF($A111=0,0,SUMIF('Week 2 Roster'!$AZ:$AZ,$B111,'Week 2 Roster'!$AR:$AR)) -> 0 | AT111: =IF($A111=0,0,SUMIF('Week 2 Roster'!$AZ:$AZ,$B111,'Week 2 Roster'!$AS:$AS)) -> 0 | AU111: =SUM(AK111:AP111,AR111:AT111) -> 0
A112: {=_xlfn.NUMBERVALUE(INDIRECT(TEXT(MIN(IF(($AW$2:$AX$300<>"")*(COUNTIF($B$1:B111,$AW$2:$AX$300)=0),ROW($2:$300)*100+COLUMN($AW:$AX),7^8)),"R0C00"),)&"")} -> 0 | B112: =IF(A112=0,"",_xlfn.NUMBERVALUE(A112)) | C112: =IF($A112=0,"",VLOOKUP($B112,Employees!$A:$G,2,FALSE)) | D112: =IF($A112=0,"",VLOOKUP($B112,Employees!$A:$G,3,FALSE)) | E112: =IF($A112=0,"",VLOOKUP($B112,Employees!$A:$G,5,FALSE)) | F112: =IF($E112="","",ROUNDDOWN(YEARFRAC($E112, 'Week 1 Roster'!$D$1-1, 1), 0)) | G112: =IF($E112="","",ROUNDDOWN(YEARFRAC($E112, 'Week 1 Roster'!$D$1+14, 1), 0)) | H112: =IF($E112="","",IF(AND(F112<21,F112<>G112),TRUE,FALSE)) | I112: =IF($A112=0,"",VLOOKUP($B112,Employees!$A:$G,6,FALSE)) | J112: =IF($A112=0,"",VLOOKUP($B112,Employees!$A:$G,7,FALSE)) | K112: =IF($A112=0,"",IF(ISNA(VLOOKUP(A112,'Week 1 Roster'!A:C,2,0)),VLOOKUP(A112,'Week 2 Roster'!A:C,2,0),VLOOKUP(A112,'Week 1 Roster'!A:C,2,0))) | L112: =IF($A112=0,"",VLOOKUP(K112,Stores!A:B,2,0)) | M112: =Y112+AK112 -> 0 | N112: =Z112+AL112 -> 0 | O112: =AA112+AM112 -> 0 | P112: =AB112+AN112 -> 0 | Q112: =AC112+AO112 -> 0 | R112: =AD112+AP112 -> 0 | S112: =AE112+AQ112 -> 0 | T112: =AF112+AR112 -> 0 | ... V112: =AH112+AT112 -> 0 | W112: =SUM(M112:R112,T112:V112) -> 0 | Y112: =IF($A112=0,0,SUMIF('Week 1 Roster'!$AZ:$AZ,$B112,'Week 1 Roster'!$AE:$AE)) -> 0 | Z112: =IF($A112=0,0,SUMIF('Week 1 Roster'!$AZ:$AZ,$B112,'Week 1 Roster'!$AG:$AG)) -> 0 | AA112: =IF($A112=0,0,SUMIF('Week 1 Roster'!$AZ:$AZ,$B112,'Week 1 Roster'!$AI:$AI)) -> 0 | AB112: =IF($A112=0,0,SUMIF('Week 1 Roster'!$AZ:$AZ,$B112,'Week 1 Roster'!$AK:$AK)) -> 0 | AC112: =IF($A112=0,0,SUMIF('Week 1 Roster'!$AZ:$AZ,$B112,'Week 1 Roster'!$AM:$AM)) -> 0 | AD112: =IF($A112=0,0,SUMIF('Week 1 Roster'!$AZ:$AZ,$B112,'Week 1 Roster'!$AO:$AO)) -> 0 | AE112: =IF($A112=0,0,SUMIF('Week 1 Roster'!$AZ:$AZ,$B112,'Week 1 Roster'!$AP:$AP)) -> 0 | AF112: =IF($A112=0,0,SUMIF('Week 1 Roster'!$AZ:$AZ,$B112,'Week 1 Roster'!$AQ:$AQ)) -> 0 | AG112: =IF($A112=0,0,SUMIF('Week 1 Roster'!$AZ:$AZ,$B112,'Week 1 Roster'!$AR:$AR)) -> 0 | AH112: =IF($A112=0,0,SUMIF('Week 1 Roster'!$AZ:$AZ,$B112,'Week 1 Roster'!$AS:$AS)) -> 0 | AI112: =SUM(Y112:AD112,AF112:AH112) -> 0 | AK112: =IF($A112=0,0,SUMIF('Week 2 Roster'!$AZ:$AZ,$B112,'Week 2 Roster'!$AE:$AE)) -> 0 | AL112: =IF($A112=0,0,SUMIF('Week 2 Roster'!$AZ:$AZ,$B112,'Week 2 Roster'!$AG:$AG)) -> 0 | AM112: =IF($A112=0,0,SUMIF('Week 2 Roster'!$AZ:$AZ,$B112,'Week 2 Roster'!$AI:$AI)) -> 0 | AN112: =IF($A112=0,0,SUMIF('Week 2 Roster'!$AZ:$AZ,$B112,'Week 2 Roster'!$AK:$AK)) -> 0 | AO112: =IF($A112=0,0,SUMIF('Week 2 Roster'!$AZ:$AZ,$B112,'Week 2 Roster'!$AM:$AM)) -> 0 | AP112: =IF($A112=0,0,SUMIF('Week 2 Roster'!$AZ:$AZ,$B112,'Week 2 Roster'!$AO:$AO)) -> 0 | AQ112: =IF($A112=0,0,SUMIF('Week 2 Roster'!$AZ:$AZ,$B112,'Week 2 Roster'!$AP:$AP)) -> 0 | AR112: =IF($A112=0,0,SUMIF('Week 2 Roster'!$AZ:$AZ,$B112,'Week 2 Roster'!$AQ:$AQ)) -> 0 | AS112: =IF($A112=0,0,SUMIF('Week 2 Roster'!$AZ:$AZ,$B112,'Week 2 Roster'!$AR:$AR)) -> 0 | AT112: =IF($A112=0,0,SUMIF('Week 2 Roster'!$AZ:$AZ,$B112,'Week 2 Roster'!$AS:$AS)) -> 0 | AU112: =SUM(AK112:AP112,AR112:AT112) -> 0
... A300: {=_xlfn.NUMBERVALUE(INDIRECT(TEXT(MIN(IF(($AW$2:$AX$300<>"")*(COUNTIF($B$1:B299,$AW$2:$AX$300)=0),ROW($2:$300)*100+COLUMN($AW:$AX),7^8)),"R0C00"),)&"")} -> 0 | B300: =IF(A300=0,"",_xlfn.NUMBERVALUE(A300)) | C300: =IF($A300=0,"",VLOOKUP($B300,Employees!$A:$G,2,FALSE)) | D300: =IF($A300=0,"",VLOOKUP($B300,Employees!$A:$G,3,FALSE)) | E300: =IF($A300=0,"",VLOOKUP($B300,Employees!$A:$G,5,FALSE)) | F300: =IF($E300="","",ROUNDDOWN(YEARFRAC($E300, 'Week 1 Roster'!$D$1-1, 1), 0)) | G300: =IF($E300="","",ROUNDDOWN(YEARFRAC($E300, 'Week 1 Roster'!$D$1+14, 1), 0)) | H300: =IF($E300="","",IF(AND(F300<21,F300<>G300),TRUE,FALSE)) | I300: =IF($A300=0,"",VLOOKUP($B300,Employees!$A:$G,6,FALSE)) | J300: =IF($A300=0,"",VLOOKUP($B300,Employees!$A:$G,7,FALSE)) | K300: =IF($A300=0,"",IF(ISNA(VLOOKUP(A300,'Week 1 Roster'!A:C,2,0)),VLOOKUP(A300,'Week 2 Roster'!A:C,2,0),VLOOKUP(A300,'Week 1 Roster'!A:C,2,0))) | L300: =IF($A300=0,"",VLOOKUP(K300,Stores!A:B,2,0)) | M300: =Y300+AK300 -> 0 | N300: =Z300+AL300 -> 0 | O300: =AA300+AM300 -> 0 | P300: =AB300+AN300 -> 0 | Q300: =AC300+AO300 -> 0 | R300: =AD300+AP300 -> 0 | S300: =AE300+AQ300 -> 0 | T300: =AF300+AR300 -> 0 | ... V300: =AH300+AT300 -> 0 | W300: =SUM(M300:R300,T300:V300) -> 0 | Y300: =IF($A300=0,0,SUMIF('Week 1 Roster'!$AZ:$AZ,$B300,'Week 1 Roster'!$AE:$AE)) -> 0 | Z300: =IF($A300=0,0,SUMIF('Week 1 Roster'!$AZ:$AZ,$B300,'Week 1 Roster'!$AG:$AG)) -> 0 | AA300: =IF($A300=0,0,SUMIF('Week 1 Roster'!$AZ:$AZ,$B300,'Week 1 Roster'!$AI:$AI)) -> 0 | AB300: =IF($A300=0,0,SUMIF('Week 1 Roster'!$AZ:$AZ,$B300,'Week 1 Roster'!$AK:$AK)) -> 0 | AC300: =IF($A300=0,0,SUMIF('Week 1 Roster'!$AZ:$AZ,$B300,'Week 1 Roster'!$AM:$AM)) -> 0 | AD300: =IF($A300=0,0,SUMIF('Week 1 Roster'!$AZ:$AZ,$B300,'Week 1 Roster'!$AO:$AO)) -> 0 | AE300: =IF($A300=0,0,SUMIF('Week 1 Roster'!$AZ:$AZ,$B300,'Week 1 Roster'!$AP:$AP)) -> 0 | AF300: =IF($A300=0,0,SUMIF('Week 1 Roster'!$AZ:$AZ,$B300,'Week 1 Roster'!$AQ:$AQ)) -> 0 | AG300: =IF($A300=0,0,SUMIF('Week 1 Roster'!$AZ:$AZ,$B300,'Week 1 Roster'!$AR:$AR)) -> 0 | AH300: =IF($A300=0,0,SUMIF('Week 1 Roster'!$AZ:$AZ,$B300,'Week 1 Roster'!$AS:$AS)) -> 0 | AI300: =SUM(Y300:AD300,AF300:AH300) -> 0 | AK300: =IF($A300=0,0,SUMIF('Week 2 Roster'!$AZ:$AZ,$B300,'Week 2 Roster'!$AE:$AE)) -> 0 | AL300: =IF($A300=0,0,SUMIF('Week 2 Roster'!$AZ:$AZ,$B300,'Week 2 Roster'!$AG:$AG)) -> 0 | AM300: =IF($A300=0,0,SUMIF('Week 2 Roster'!$AZ:$AZ,$B300,'Week 2 Roster'!$AI:$AI)) -> 0 | AN300: =IF($A300=0,0,SUMIF('Week 2 Roster'!$AZ:$AZ,$B300,'Week 2 Roster'!$AK:$AK)) -> 0 | AO300: =IF($A300=0,0,SUMIF('Week 2 Roster'!$AZ:$AZ,$B300,'Week 2 Roster'!$AM:$AM)) -> 0 | AP300: =IF($A300=0,0,SUMIF('Week 2 Roster'!$AZ:$AZ,$B300,'Week 2 Roster'!$AO:$AO)) -> 0 | AQ300: =IF($A300=0,0,SUMIF('Week 2 Roster'!$AZ:$AZ,$B300,'Week 2 Roster'!$AP:$AP)) -> 0 | AR300: =IF($A300=0,0,SUMIF('Week 2 Roster'!$AZ:$AZ,$B300,'Week 2 Roster'!$AQ:$AQ)) -> 0 | AS300: =IF($A300=0,0,SUMIF('Week 2 Roster'!$AZ:$AZ,$B300,'Week 2 Roster'!$AR:$AR)) -> 0 | AT300: =IF($A300=0,0,SUMIF('Week 2 Roster'!$AZ:$AZ,$B300,'Week 2 Roster'!$AS:$AS)) -> 0 | AU300: =SUM(AK300:AP300,AR300:AT300) -> 0

Sheet Employees
A1: Employee ID | B1: First Name | C1: Last Name | D1: Preferred Name | E1: Date of Birth | F1: Hour Threshold | G1: Company | H1: Level | I1: =A1 -> Employee ID
A2: 10001 | B2: Chien Han | C2: Lee | D2: Ryan Lee | E2: 33178 | F2: 76 | G2: GCM | H2: Level 3 | I2: =A2 -> 10001
A3: 10002 | B3: Chih-Ching | C3: Hsu | D3: Sharon Hsu | E3: 34854 | F3: 76 | G3: GCM | I3: =A3 -> 10002
A4: 10003 | B4: Ching Yi | C4: Huang | D4: Amilli Huang | E4: 36881 | F4: 48 | G4: GCM | I4: =A4 -> 10003
A5: 10004 | B5: Dan | C5: Yi | D5: Dan Yi | E5: 37038 | F5: 48 | G5: GCM | I5: =A5 -> 10004
A6: 10005 | B6: Di | C6: Niu | D6: Jodie Niu | E6: 32417 | F6: 76 | G6: GCM | I6: =A6 -> 10005
A7: 10006 | B7: Dianyu | C7: Wang | D7: Shephard wang | E7: 32528 | F7: 76 | G7: SS | I7: =A7 -> 10006
A8: 10007 | B8: Elissa | C8: Zhang | D8: Elissa Zhang | E8: 36422 | F8: 76 | G8: GCM | I8: =A8 -> 10007
A9: 10008 | B9: Elsie | C9: Chan | D9: Elsie Chan | E9: 36271 | F9: 76 | G9: GCM | I9: =A9 -> 10008
A10: 10009 | B10: Emon | C10: Peng | D10: Emon Peng | E10: 38294 | F10: 76 | G10: GCM | I10: =A10 -> 10009
A11: 10010 | B11: Erica Fong-de | C11: Jong | D11: Erica Fong-de Jong | E11: 36628 | F11: 76 | G11: GCM | I11: =A11 -> 10010
A12: 10011 | B12: FEI | C12: CAO | D12: Daniel Cao | E12: 34222 | F12: 76 | G12: GCM | I12: =A12 -> 10011
A13: 10012 | B13: Han | C13: Liu | D13: Jack Liu | E13: 35102 | F13: 76 | G13: GCM | H13: Level 3 | I13: =A13 -> 10012
A14: 10013 | B14: Hanbo | C14: Zhang | D14: Morris Zhang | E14: 36798 | F14: 48 | G14: GCM | I14: =A14 -> 10013
A15: 10014 | B15: Hanna | C15: Jeong | D15: Hanna Jeong | E15: 36559 | F15: 76 | G15: GCM | I15: =A15 -> 10014
A16: 10015 | B16: Haoxi | C16: Lu | D16: Simon Lu | E16: 37913 | F16: 76 | G16: GCM | H16: Level 3 | I16: =A16 -> 10015
A17: 10016 | B17: Haydn | C17: Gao | D17: Haydn Gao | E17: 38227 | F17: 76 | G17: GCM | I17: =A17 -> 10016
A18: 10017 | B18: Jenny | C18: Cao | D18: Jenny Cao | E18: 37993 | F18: 76 | G18: GCM | I18: =A18 -> 10017
A19: 10018 | B19: JIA | C19: AN | D19: Anthony An | E19: 35489 | F19: 76 | G19: GCM | I19: =A19 -> 10018
A20: 10019 | B20: Jiaojiao | C20: Pan | D20: Josia Pan | E20: 35403 | F20: 76 | G20: GCM | I20: =A20 -> 10019
A21: 10020 | B21: Jiayu | C21: He | D21: Jiayu He | E21: 36886 | F21: 76 | G21: GCM | I21: =A21 -> 10020
A22: 10021 | B22: Jie | C22: Liu | D22: Genny Liu | E22: 35725 | F22: 76 | G22: GCM | I22: =A22 -> 10021
A23: 10022 | B23: Jingwen | C23: Chen | D23: Jingwen Chen | E23: 35862 | F23: 76 | G23: GCM | H23: Level 3 | I23: =A23 -> 10022
A24: 10023 | B24: Jinyi | C24: Wu | E24: 34717 | F24: 76 | G24: GCM | I24: =A24 -> 10023
A25: 10024 | B25: Kunlawach | C25: Aroonwing | D25: Jayden Aroonwing | E25: 35194 | F25: 76 | G25: GCM | I25: =A25 -> 10024
A26: 10025 | B26: LINGYI | C26: LIU | D26: Aurora Liu | E26: 37388 | F26: 48 | G26: GCM | I26: =A26 -> 10025
A27: 10026 | B27: Mohan | C27: Li | D27: Mohan Li | E27: 36209 | F27: 76 | G27: GCM | I27: =A27 -> 10026
A28: 10027 | B28: Nancy | C28: Huang | D28: Nancy Huang | E28: 37716 | F28: 76 | G28: GCM | I28: =A28 -> 10027
A29: 10028 | B29: Onnida | C29: Tantinijkun | D29: Onny Tantinijkun | E29: 36036 | F29: 4880 | G29: MSC | I29: =A29 -> 10028
A30: 10029 | B30: Phuong | C30: Le | D30: Phuong Le | E30: 36819 | F30: 76 | G30: GCM | I30: =A30 -> 10029
A31: 10030 | B31: PO Yang | C31: Cheng | D31: Eric Cheng | E31: 35798 | F31: 48 | G31: GCM | I31: =A31 -> 10030
A32: 10031 | B32: Qinyi | C32: ZHOU | D32: Cordelia Zhou | E32: 35679 | F32: 48 | G32: GCM | I32: =A32 -> 10031
A33: 10032 | B33: Reynardo | C33: Tjhin | D33: Reynardo Tjhin | E33: 36733 | F33: 76 | G33: GCM | I33: =A33 -> 10032
A34: 10033 | B34: Rui | C34: Yin | D34: Rick Yin | E34: 36142 | F34: 76 | G34: GCM | I34: =A34 -> 10033
A35: 10034 | B35: Shanxi | C35: Li | D35: Freya Li | E35: 35108 | F35: 76 | G35: GCM | I35: =A35 -> 10034
A36: 10035 | B36: Shanzhi | C36: Chen | D36: Chloe Chen | E36: 35436 | F36: 48 | G36: GCM | I36: =A36 -> 10035
... A40: 10039 | B40: Tianshuo | C40: Liu | D40: Kris Liu | E40: 34280 | F40: 76 | G40: GCM | I40: =A40 -> 10039
A41: 10040 | B41: Tran Thu Hang | C41: Vu | D41: Zoe Vu | E41: 37068 | F41: 76 | G41: GCM | H41: Level 3 | I41: =A41 -> 10040
A42: 10041 | B42: Treerut | C42: Thadthai | D42: Bonnie Thadthai | E42: 35284 | F42: 76 | G42: GCM | I42: =A42 -> 10041
A43: 10042 | B43: Van My | C43: Nguyen | D43: Van My Nguyen | E43: 36161 | F43: 76 | G43: GCM | I43: =A43 -> 10042
A44: 10043 | B44: Wai Ching Catherine | C44: Choi | D44: Catherine Choi | E44: 37272 | F44: 76 | G44: GCM | I44: =A44 -> 10043
A45: 10044 | B45: Wai Jet | C45: Lim | E45: 33435 | F45: 76 | G45: GCM | I45: =A45 -> 10044
A46: 10045 | B46: Wei-Jing | C46: Li | D46: Angel Li | E46: 35301 | F46: 4880 | G46: GCM | I46: =A46 -> 10045
A47: 10046 | B47: Xiao-jia | C47: Liu | D47: Jessica Liu | E47: 36986 | F47: 76 | G47: GCM | I47: =A47 -> 10046
A48: 10047 | B48: Xin | C48: Chen | D48: Henry Chen | E48: 35330 | F48: 76 | G48: GCM | I48: =A48 -> 10047
A49: 10048 | B49: Xinqi | C49: Liang | D49: Kiki liang | E49: 35083 | F49: 48 | G49: GCM | I49: =A49 -> 10048
A50: 10049 | B50: Yajun | C50: Chen | D50: Sabrina chen | E50: 35096 | F50: 76 | G50: GCM | I50: =A50 -> 10049
A51: 10050 | B51: Yang | C51: Wang | D51: Wylla Wang | E51: 35193 | F51: 76 | G51: GCM | I51: =A51 -> 10050
A52: 10051 | B52: Yang | C52: Zhang | D52: Antonio Zhang | E52: 35454 | F52: 76 | G52: GCM | I52: =A52 -> 10051
A53: 10052 | B53: Yeyu | C53: Deng | D53: Derek Deng | E53: 35308 | F53: 76 | G53: GCM | I53: =A53 -> 10052
A54: 10053 | B54: Yi-Jing | C54: Huang | D54: Yijing Huang | E54: 32003 | F54: 48 | G54: GCM | I54: =A54 -> 10053
A55: 10054 | B55: Yiran | C55: Zhang | D55: EOS Zhang | E55: 37182 | F55: 76 | G55: SS | I55: =A55 -> 10054
A56: 10055 | B56: Yu | C56: Lee | D56: Aurie Lee | E56: 36727 | F56: 48 | G56: GCM | I56: =A56 -> 10055
A57: 10056 | B57: Yue | C57: Xiao | D57: Kayla Xiao | E57: 35983 | F57: 76 | G57: GCM | I57: =A57 -> 10056
... A61: 10060 | B61: Rotsakon | C61: Surisihasathian | D61: Riley Surisihasathian | E61: 34540 | F61: 76 | G61: GCM | I61: =A61 -> 10060
A62: 10061 | B62: Adrian | C62: Lim | D62: Adrian Lim | E62: 36386 | F62: 76 | G62: HL | H62: Level 3 | I62: =A62 -> 10061
A63: 10062 | B63: Aidan | C63: Cloke | D63: Aidan Cloke | E63: 38748 | F63: 76 | G63: HL | I63: =A63 -> 10062
A64: 10063 | B64: Alex | C64: Khuu | D64: Alex Khuu | E64: 38463 | F64: 76 | G64: HL | I64: =A64 -> 10063
A65: 10064 | B65: Alice | C65: Ruan | D65: Alice Ruan | E65: 38081 | F65: 76 | G65: HL | I65: =A65 -> 10064
A66: 10065 | B66: Alma | C66: Espinoza | D66: Victoria Espinoza | E66: 36354 | F66: 76 | G66: HL | I66: =A66 -> 10065
A67: 10066 | B67: Arundhathi | C67: Madhu | D67: Ammu Madhu | E67: 37867 | F67: 76 | G67: HL | I67: =A67 -> 10066
A68: 10067 | B68: Bhavya | C68: Sharma | D68: Bhavya Sharma | E68: 34508 | F68: 76 | G68: HL | I68: =A68 -> 10067
A69: 10068 | B69: Catherine | C69: Rubite | D69: Catherine Rubite | E69: 37566 | F69: 76 | G69: HL | I69: =A69 -> 10068
A70: 10069 | B70: Chantelle | C70: Abenoja | D70: Chantelle Jade Abenoja | E70: 38483 | F70: 76 | G70: HL | I70: =A70 -> 10069
A71: 10070 | B71: Chantelle Dela | C71: Cruz | D71: Chantelle Bea Dela Cruz | E71: 38175 | F71: 76 | G71: HL | I71: =A71 -> 10070
A72: 10071 | B72: Chiara | C72: King | D72: Chiara King | E72: 38303 | F72: 76 | G72: HL | I72: =A72 -> 10071
A73: 10072 | B73: Chun | C73: Li | D73: Betty Li | E73: 35410 | F73: 76 | G73: HL | I73: =A73 -> 10072
A74: 10073 | B74: Cindy | C74: Mach | D74: Cindy Mach | E74: 38121 | F74: 76 | G74: HL | I74: =A74 -> 10073
... A90: 10089 | B90: HOOI | C90: LIM | D90: Wei Wei | E90: 35131 | F90: 76 | G90: HL | I90: =A90 -> 10089
A91: 10090 | B91: Hsin-Yi | C91: CHIANG | D91: Ava Chiang | E91: 33945 | F91: 76 | G91: HL | H91: Level 3 | I91: =A91 -> 10090
A92: 10091 | B92: Huaming | C92: Rao | D92: Michael Rao | E92: 37208 | F92: 48 | G92: HL | I92: =A92 -> 10091
A93: 10092 | B93: Hy Anh | C93: Nguyen | D93: Hy Anh Nguyen | E93: 37772 | F93: 76 | G93: HL | I93: =A93 -> 10092
A94: 10093 | B94: Isha | C94: Bondoc | D94: Isha Faith Bondoc | E94: 38290 | F94: 76 | G94: HL | I94: =A94 -> 10093
A95: 10094 | B95: Ishrat Jahan | C95: Sadia | D95: Ishrat Jahan Sadia | E95: 36889 | F95: 76 | G95: HL | I95: =A95 -> 10094
A96: 10095 | B96: Jeeva | C96: Tan | D96: Jeeva Tan | E96: 36967 | F96: 76 | G96: HL | I96: =A96 -> 10095
A97: 10096 | B97: Jessy Lee Ai | C97: Chng | D97: Jessy Chng | E97: 29368 | F97: 76 | G97: HL | I97: =A97 -> 10096
A98: 10097 | B98: Jie | C98: Wei | D98: Mini | E98: 32547 | F98: 100 | G98: HL | I98: =A98 -> 10097
A99: 10098 | B99: Jimmy | C99: Huynh | D99: Jimmy Huynh | E99: 37885 | F99: 76 | G99: HL | I99: =A99 -> 10098
A100: 10099 | B100: Jinyi | C100: Wu | D100: Jinyi Wu | E100: 34717 | F100: 76 | G100: HL | I100: =A100 -> 10099
A101: 10100 | B101: Joma | C101: Velasco | D101: Joma velasco | E101: 36411 | F101: 76 | G101: HL | I101: =A101 -> 10100
A102: 10101 | B102: Jun | C102: Chen | D102: Deven chen | E102: 35497 | F102: 76 | G102: HL | I102: =A102 -> 10101
A103: 10102 | B103: Justin | C103: Roxas | D103: Justin Roxas | E103: 38134 | F103: 76 | G103: HL | I103: =A103 -> 10102
... A148: 10147 | B148: Ye | C148: Xu | D148: Abi Xu | E148: 36932 | F148: 100 | G148: HL | I148: =A148 -> 10147
A149: 10148 | B149: Yeng Ting | C149: Luo | D149: Yeng Ting Luo | E149: 36453 | F149: 76 | G149: HL | H149: Level 3 | I149: =A149 -> 10148
A150: 10149 | B150: Yilong | C150: Zhu | D150: Bruce | E150: 35642 | F150: 76 | G150: HL | I150: =A150 -> 10149
A151: 10150 | B151: YingYing | C151: Nian | D151: Erica Nian | E151: 33094 | F151: 76 | G151: HL | I151: =A151 -> 10150
A152: 10151 | B152: Zishan | C152: Xie | D152: Zishan Xie | E152: 36756 | F152: 76 | G152: HL | I152: =A152 -> 10151
A153: 10152 | B153: Zizhuo | C153: Zhang | D153: Tom Zhang | E153: 37203 | F153: 76 | G153: HL | I153: =A153 -> 10152
A154: 10153 | B154: Duc Minh | C154: Pham | D154: Victor Pham | E154: 28/10/2001 | F154: 76 | G154: HL | I154: =A154 -> 10153
A155: 10154 | B155: Jiazheng | C155: Xian | D155: Donald Xian | E155: 36809 | F155: 200 | G155: HL | I155: =A155 -> 10154
A156: 10155 | B156: Qianyu | C156: Liu | D156: Carrie Liu | E156: 35234 | F156: 76 | G156: SS | H156: Level 3 | I156: =A156 -> 10155
A157: 10156 | B157: Chau Kim | C157: Quach | D157: Chau | E157: 34555 | F157: 4880 | G157: HL | I157: =A157 -> 10156
A158: 10157 | B158: Kaiming | C158: Wang | D158: Ming Wang | E158: 34427 | F158: 76 | G158: HL | I158: =A158 -> 10157
A159: 10158 | B159: Wenzhe | C159: Tan | D159: Sam Tan | E159: 32933 | F159: 76 | G159: HL | I159: =A159 -> 10158
A160: 10159 | B160: Duy | C160: Chu | D160: Jim Chu | E160: 37096 | F160: 48 | G160: GCM | I160: =A160 -> 10159
A161: 10160 | B161: Pulin | C161: Pan | D161: Lexi Pan | E161: 36402 | F161: 76 | G161: GCM | I161: =A161 -> 10160
A162: 10161 | B162: Zihan | C162: Wang | D162: Amber Wang | E162: 37115 | F162: 76 | G162: GCM | I162: =A162 -> 10161
A163: 10162 | B163: YINGJUN | C163: CHEN | D163: Cecilia Chen | E163: 36157 | F163: 76 | G163: GCM | I163: =A163 -> 10162
